Workbook

Sheet Credit Summary
C2: Quanex credit underwriting summary
C4: Case selected: | D4: =Assumptions!$D$4 -> Base
C5: Phase 8 model — final credit recommendation pending Phase 10
C7: Transaction and opening position | H7: Warnings, protections and unresolved conditions
C8: Borrower | D8: Quanex Building Products Corporation | H8: Status | I8: Date / value | J8: Interpretation
C9: Information cutoff | D9: 46006 | H9: First warning | I9: ='Scenario Comparison'!S5 -> N/D | J9: Analyst warning; does not terminate draws
C10: Hypothetical closing | D10: 46053 | H10: First covenant breach | I10: ='Scenario Comparison'!T5 -> N/D | J10: Proposed maintenance test
C11: Selected structure | D11: $635m term / $300m revolver / $15m conditional source | H11: First draw shutoff | I11: ='Scenario Comparison'!U5 -> N/D | J11: Path-specific no-waiver convention
C12: Bank hold cap | D12: 50 | H12: First mandatory-payment failure | I12: ='Scenario Comparison'!V5 -> N/D | J12: Separate from covenant and liquidity status
C13: Opening total funded debt | D13: =Transaction!D17 -> 727.51672 | H13: Maturity gap | I13: ='Scenario Comparison'!X5 -> 324.77971 | J13: No maturity refinancing assumed
C14: Opening gross leverage | D14: =Transaction!D18 -> 3.2284717
C16: Selected-case outcomes | H16: Type | I16: Item | J16: Status
C17: FY2026 post-closing lender-base EBITDA | D17: ='Scenario Comparison'!F5 -> 190.24864 | H17: Risk | I17: Tyman integration / $302.284m impairment | J17: Major adverse forecasting signal
C18: Modeled operating cash | D18: ='Scenario Comparison'!H5 -> 794.48407 | H18: Risk | I18: Adjustment-heavy earnings / cash conversion | J18: Monitor
C19: CFADS through maturity | D19: ='Scenario Comparison'!I5 -> 640.30851 | H19: Protection | I19: 3.50x / 3.25x / 3.00x gross leverage covenant | J19: Proposed
C20: Cash interest | D20: ='Scenario Comparison'!J5 -> 167.38575 | H20: Protection | I20: 50% ECF sweep / distribution restrictions | J20: Proposed
C21: Opening usable liquidity | D21: ='Scenario Comparison'!N5 -> 263.90228 | H21: Condition | I21: $15m source / separate $25m cash floor | J21: Pending information
C22: Subsequent minimum liquidity | D22: ='Scenario Comparison'!O5 -> 270.34135 | H22: Condition | I22: Closing LTM interest / official compliance | J22: N/D
C23: All-in minimum liquidity | D23: ='Scenario Comparison'!P5 -> 263.90228 | H23: Condition | I23: Debt / EBITDA / ECF / cure / draw definitions | J23: Pending legal diligence
C24: Maximum gross leverage | D24: ='Scenario Comparison'!Q5 -> 3.2284717 | H24: Alternative | I24: Retain or amend existing facilities | J24: Live alternative; amendment economics N/D
C25: Minimum cash-interest coverage | D25: ='Scenario Comparison'!R5 -> 5.3859581
C26: Closing cash-interest coverage | D26: N/D
C27: Common-horizon ending funded debt | D27: ='Scenario Comparison'!W5 -> 514.75371
C28: Unsupported maturity gap | D28: ='Scenario Comparison'!X5 -> 324.77971

Sheet Assumptions
C2: Quanex underwriting assumptions
C4: Case selected: | D4: Base
C5: Scenario ID | D5: =INDEX($BE$41:$BE$49,MATCH($D$4,$BD$41:$BD$49,0)) -> BASE
C6: Approved input version | D6: 58e1b83a644021b785162d851e1539dd65dff9f5
C7: Current input signature | D7: =ROUND(SUMPRODUCT($D$12:$D$35,ROW($D$12:$D$35))+SUMPRODUCT($L$41:$L$364,ROW($L$41:$L$364))/1000+SUMPRODUCT($N$41:$N$364,ROW($N$41:$N$364))/10000,6) -> 1712129.8
C8: Source-file hash | D8: 126ef393472d5f74abd447b237b1319643c1effb36a37f052496b114af1a6fe1
C10: Financing, covenant and sensitivity controls | H10: Policy, status and unresolved-definition register
C11: Control | D11: Value | E11: Units | F11: Source / assumption ID | G11: Status / limitation | H11: Area | I11: Approved rule / unresolved item | J11: Status | K11: Source | L11: Workbook treatment
C12: Term commitment | D12: 635 | E12: USD millions | F12: P7FA-002 | G12: Owner-reviewed provisional | H12: Repurchases | I12: No directly debt-funded repurchases; none while revolver is outstanding | J12: Owner reviewed | K12: P7FA-030 | L12: No unapproved cash-flow benefit
C13: Conditional non-debt contribution | D13: 15 | E13: USD millions | F13: P7FA-007 | G13: Pending evidence; separate from cash floor | H13: Dividends | I13: Require no default, gross leverage <=3.00x and usable liquidity >=$75m after payment | J13: Owner reviewed | K13: P7FA-030 | L13: Approved Phase 7 scenario cash flows retained
C14: Revolver commitment | D14: 300 | E14: USD millions | F14: P7FA-009 | G14: Owner-reviewed provisional | H14: Warning | I14: Suspends repurchases and triggers enhanced reporting | J14: Owner reviewed | K14: P7FA-027/P7FA-028 | L14: Warning alone does not terminate draws
C15: Opening revolver | D15: =679.89771875-D12-D13 -> 29.897719 | E15: USD millions | F15: Formula | G15: Reference uses less term and contribution | H15: Covenant breach | I15: Suspends all restricted payments | J15: Owner reviewed | K15: P7FA-030 | L15: Reported separately from warning
C16: Letters of credit | D16: 6.2 | E16: USD millions | F16: P7FA-010 | G16: Inherited reference | H16: Drawability | I16: Analytical shutoff, covenant-linked no-waiver and continued-draw paths remain distinct | J16: Owner reviewed | K16: P7FA-031 | L16: Selector preserves all approved paths
C17: Retained other funded debt | D17: 62.619 | E17: USD millions | F17: P7FA-013 | G17: Conservative proxy | H17: Covenant cash | I17: Eligible covenant cash | J17: N/D | K17: P7FA-012 | L17: Zero cash netting in proposed leverage tests
C18: Annual term amortization | D18: 0.075 | E18: percent | F18: P7FA-016 | G18: Paid quarterly | H18: Book-cash leverage | I18: Book cash may not equal accessible covenant cash | J18: Diagnostic only | K18: P7FA-012 | L18: Not covenant or lender net leverage
C19: Modeled all-in interest rate | D19: 0.0657 | E19: percent | F19: P7FA-020 | G19: Testing assumption | H19: Conditional source | I19: $15m non-debt contribution availability and accessibility | J19: Condition precedent | K19: P7FA-007 | L19: Displayed separately; not verified cash
C20: Incremental interest spread | D20: 0 | E20: percent | F20: Phase 8 control | G20: Sensitivity overlay | H20: Closing coverage | I20: Complete closing LTM cash interest | J20: N/D | K20: P7FA-019 | L20: Closing coverage remains N/D
C21: EBITDA overlay | D21: 0 | E21: percent | F21: Phase 8 control | G21: Sensitivity overlay; zero in approved case | H21: Legal definitions | I21: Debt, EBITDA, ECF, cure, draw, default and waiver definitions | J21: Pending information | K21: P7FA-026 | L21: Not presented as official compliance
C22: Base DSO | D22: 41.5 | E22: days | F22: P5A-004 | G22: Approved testing input
C23: DSO change | D23: 0 | E23: days | F23: Phase 8 control | G23: Sensitivity overlay
C24: Operating cash floor | D24: 25 | E24: USD millions | F24: P7FA-021 | G24: Separate operating control
C25: Liquidity overlay per period | D25: 0 | E25: USD millions | F25: Phase 8 control | G25: Sensitivity overlay
C26: ECF sweep | D26: 0.5 | E26: percent | F26: P7FA-029 | G26: After revolver repayment and safeguards
C27: Initial leverage covenant | D27: 3.5 | E27: turns | F27: P7FA-022 | G27: Through 10/31/27
C28: Step 1 leverage covenant | D28: 3.25 | E28: turns | F28: P7FA-023 | G28: Through 10/31/28
C29: Step 2 leverage covenant | D29: 3 | E29: turns | F29: P7FA-024 | G29: Thereafter
C30: Interest coverage covenant | D30: 3 | E30: turns | F30: P7FA-025 | G30: Minimum
C31: Liquidity covenant | D31: 50 | E31: USD millions | F31: P7FA-026 | G31: Minimum usable liquidity
C32: Initial leverage warning | D32: 3.25 | E32: turns | F32: P7FA-027 | G32: Inclusive warning
C33: Coverage warning | D33: 3.5 | E33: turns | F33: P7FA-028 | G33: Minimum analyst warning
... C35: Maturity | D35: 47879 | E35: date | F35: P7FA-017 | G35: No refinancing assumed
C40: scenario name | D40: scenario id | E40: model period id | F40: frequency | G40: period start | H40: period end | I40: fiscal year | J40: quarter | K40: days in period | L40: revenue | M40: base gross margin percent | N40: lender base ebitda | O40: depreciation and amortization | P40: cash tax proxy | Q40: working capital cash flow | R40: capital expenditures | S40: other operating cash uses | T40: cfads before cash interest | U40: opening cash | V40: ending cash | W40: opening term principal | X40: scheduled term principal due | Y40: scheduled term principal paid | Z40: cash sweep | AA40: maturity principal due | AB40: maturity principal paid | AC40: ending term principal | AD40: opening revolver | AE40: revolver draw | AF40: revolver repayment | AG40: ending revolver | AH40: cash interest due | AI40: cash interest paid | AJ40: retained obligation paid | AK40: dividend paid | AL40: repurchase paid | AM40: failed obligation unpaid amount | AN40: gross funded debt | AO40: minimum usable liquidity | AP40: peak revolver | AQ40: nominal revolver availability | AR40: drawability status | AS40: drawability shutoff date | AT40: ttm lender base ebitda | AU40: gross funded leverage | AV40: ebitda cash interest coverage | AW40: unsupported maturity gap | AX40: maturity event | AY40: mandatory payment failure flag | AZ40: model status | BA40: source ids | BB40: upstream ids | BD40: scenario name | BE40: scenario id | BF40: first warning | BG40: first breach | BH40: first shutoff | BI40: first payment failure | BJ40: common ending debt | BK40: maturity gap | BL40: opening liquidity | BM40: subsequent minimum | BN40: all in minimum | BO40: maximum leverage | BP40: minimum coverage
C41: Base | D41: BASE | E41: P001 | F41: monthly | G41: 46054 | H41: 46081 | I41: FY2026 | J41: Q2 | K41: 28 | L41: 150.82223 | M41: 28.869322 | N41: 21.062659 | O41: -8.4900849 | P41: -3.1431434 | Q41: -0.024735049 | R41: -5.278778 | S41: -0.23333333 | T41: 12.382669 | U41: 25 | V41: 25 | W41: 635 | X41: 0 | Y41: 0 | Z41: 0 | AA41: 0 | AB41: 0 | AC41: 635 | AD41: 29.897719 | AE41: 0 | AF41: 6.4390641 | AG41: 23.458655 | AH41: 3.6226881 | AI41: 3.6226881 | AJ41: 0.69591667 | AK41: 1.2083333 | AL41: 0.41666667 | AM41: 0 | AN41: 721.07765 | AO41: 270.34135 | AP41: 23.458655 | AQ41: 270.34135 | AR41: available_before_analytical_shutoff | AW41: 0 | AX41: no | AY41: no | AZ41: PASS | BA41: SRC-001;SRC-002;SRC-003 | BB41: P6M-BASE-P-0001:P6M-BASE-P-0001 | BD41: Base | BE41: BASE | BF41: N/D | BG41: N/D | BH41: N/D | BI41: N/D | BJ41: 514.75371 | BK41: 324.77971 | BL41: 263.90228 | BM41: 270.34135 | BN41: 263.90228 | BO41: 3.2284717 | BP41: 5.3859581
C42: Base | D42: BASE | E42: P002 | F42: monthly | G42: 46082 | H42: 46112 | I42: FY2026 | J42: Q2 | K42: 31 | L42: 150.82223 | M42: 28.869322 | N42: 21.062659 | O42: -8.4900849 | P42: -3.1431434 | Q42: -0.024735049 | R42: -5.278778 | S42: -0.23333333 | T42: 12.382669 | U42: 25 | V42: 25 | W42: 635 | X42: 0 | Y42: 0 | Z42: 0 | AA42: 0 | AB42: 0 | AC42: 635 | AD42: 23.458655 | AE42: 0 | AF42: 6.4744148 | AG42: 16.98424 | AH42: 3.5873374 | AI42: 3.5873374 | AJ42: 0.69591667 | AK42: 1.2083333 | AL42: 0.41666667 | AM42: 0 | AN42: 714.60324 | AO42: 276.81576 | AP42: 16.98424 | AQ42: 276.81576 | AR42: available_before_analytical_shutoff | AW42: 0 | AX42: no | AY42: no | AZ42: PASS | BA42: SRC-001;SRC-002;SRC-003 | BB42: P6M-BASE-P-0002:P6M-BASE-P-0002 | BD42: Moderate unmitigated | BE42: MODERATE_UNMITIGATED | BF42: 2026-10-31 | BG42: 2026-10-31 | BH42: N/D | BI42: N/D | BL42: 263.90228 | BM42: 165.07841 | BN42: 165.07841 | BO42: 4.4892502 | BP42: 3.2103738
C43: Base | D43: BASE | E43: P003 | F43: monthly | G43: 46113 | H43: 46142 | I43: FY2026 | J43: Q2 | K43: 30 | L43: 150.82223 | M43: 28.869322 | N43: 21.062659 | O43: -8.4900849 | P43: -3.1431434 | Q43: -0.024735049 | R43: -5.278778 | S43: -0.23333333 | T43: 12.382669 | U43: 25 | V43: 25 | W43: 635 | X43: 11.90625 | Y43: 11.90625 | Z43: 0 | AA43: 0 | AB43: 0 | AC43: 623.09375 | AD43: 16.98424 | AE43: 5.3962905 | AF43: 0 | AG43: 22.38053 | AH43: 3.5517927 | AI43: 3.5517927 | AJ43: 0.69591667 | AK43: 1.2083333 | AL43: 0.41666667 | AM43: 0 | AN43: 708.09328 | AO43: 271.41947 | AP43: 22.38053 | AQ43: 271.41947 | AR43: available_before_analytical_shutoff | AW43: 0 | AX43: no | AY43: no | AZ43: PASS | BA43: SRC-001;SRC-002;SRC-003 | BB43: P6M-BASE-P-0003:P6M-BASE-P-0003 | BD43: Moderate mitigated | BE43: MODERATE_MITIGATED | BF43: 2026-10-31 | BG43: 2026-10-31 | BH43: N/D | BI43: N/D | BL43: 263.90228 | BM43: 168.93692 | BN43: 168.93692 | BO43: 4.4670061 | BP43: 3.2168341
C44: Base | D44: BASE | E44: P004 | F44: monthly | G44: 46143 | H44: 46173 | I44: FY2026 | J44: Q3 | K44: 31 | L44: 165.08687 | M44: 27.690174 | N44: 21.108129 | O44: -9.2930702 | P44: -2.9537647 | Q44: -0.027069577 | R44: -5.7780405 | S44: 0 | T44: 12.349254 | U44: 25 | V44: 25 | W44: 623.09375 | X44: 0 | Y44: 0 | Z44: 0 | AA44: 0 | AB44: 0 | AC44: 623.09375 | AD44: 22.38053 | AE44: 0 | AF44: 6.512193 | AG44: 15.868337 | AH44: 3.5161446 | AI44: 3.5161446 | AJ44: 0.69591667 | AK44: 1.2083333 | AL44: 0.41666667 | AM44: 0 | AN44: 701.58109 | AO44: 277.93166 | AP44: 15.868337 | AQ44: 277.93166 | AR44: available_before_analytical_shutoff | AW44: 0 | AX44: no | AY44: no | AZ44: PASS | BA44: SRC-001;SRC-002;SRC-003 | BB44: P6M-BASE-P-0004:P6M-BASE-P-0004 | BD44: Severe unmitigated | BE44: SEVERE_UNMITIGATED | BF44: 2026-04-30 | BG44: 2026-10-31 | BH44: N/D | BI44: 2027-12-31 | BL44: 263.90228 | BM44: 0 | BN44: 0 | BO44: 7.0574015 | BP44: 1.7819351
C45: Base | D45: BASE | E45: P005 | F45: monthly | G45: 46174 | H45: 46203 | I45: FY2026 | J45: Q3 | K45: 30 | L45: 165.08687 | M45: 27.690174 | N45: 21.108129 | O45: -9.2930702 | P45: -2.9537647 | Q45: -0.027069577 | R45: -5.7780405 | S45: 0 | T45: 12.349254 | U45: 25 | V45: 25 | W45: 623.09375 | X45: 0 | Y45: 0 | Z45: 0 | AA45: 0 | AB45: 0 | AC45: 623.09375 | AD45: 15.868337 | AE45: 0 | AF45: 6.5479451 | AG45: 9.3203922 | AH45: 3.4803924 | AI45: 3.4803924 | AJ45: 0.69591667 | AK45: 1.2083333 | AL45: 0.41666667 | AM45: 0 | AN45: 695.03314 | AO45: 284.47961 | AP45: 9.3203922 | AQ45: 284.47961 | AR45: available_before_analytical_shutoff | AW45: 0 | AX45: no | AY45: no | AZ45: PASS | BA45: SRC-001;SRC-002;SRC-003 | BB45: P6M-BASE-P-0005:P6M-BASE-P-0005 | BD45: Severe mitigated | BE45: SEVERE_MITIGATED | BF45: 2026-04-30 | BG45: 2026-10-31 | BH45: N/D | BI45: 2028-01-31 | BL45: 263.90228 | BM45: 0 | BN45: 0 | BO45: 6.9528556 | BP45: 1.800808
C46: Base | D46: BASE | E46: P006 | F46: monthly | G46: 46204 | H46: 46234 | I46: FY2026 | J46: Q3 | K46: 31 | L46: 165.08687 | M46: 27.690174 | N46: 21.108129 | O46: -9.2930702 | P46: -2.9537647 | Q46: -0.027069577 | R46: -5.7780405 | S46: 0 | T46: 12.349254 | U46: 25 | V46: 25 | W46: 623.09375 | X46: 11.90625 | Y46: 11.90625 | Z46: 0 | AA46: 0 | AB46: 0 | AC46: 611.1875 | AD46: 9.3203922 | AE46: 5.3223565 | AF46: 0 | AG46: 14.642749 | AH46: 3.444444 | AI46: 3.444444 | AJ46: 0.69591667 | AK46: 1.2083333 | AL46: 0.41666667 | AM46: 0 | AN46: 688.44925 | AO46: 279.15725 | AP46: 14.642749 | AQ46: 279.15725 | AR46: available_before_analytical_shutoff | AW46: 0 | AX46: no | AY46: no | AZ46: PASS | BA46: SRC-001;SRC-002;SRC-003 | BB46: P6M-BASE-P-0006:P6M-BASE-P-0006 | BD46: Moderate Phase 6 analytical shutoff | BE46: MODERATE_NO_WAIVER | BF46: 2026-10-31 | BG46: 2026-10-31 | BH46: 2026-11-30 | BI46: N/D | BL46: 263.90228 | BM46: 0 | BN46: 0 | BO46: 4.3787434 | BP46: 3.2181715
C47: Base | D47: BASE | E47: P007 | F47: monthly | G47: 46235 | H47: 46265 | I47: FY2026 | J47: Q4 | K47: 31 | L47: 163.27792 | M47: 27.915917 | N47: 21.245425 | O47: -9.1912406 | P47: -3.013546 | Q47: -0.026773886 | R47: -5.7147271 | S47: 0 | T47: 12.490378 | U47: 25 | V47: 25 | W47: 611.1875 | X47: 0 | Y47: 0 | Z47: 0 | AA47: 0 | AB47: 0 | AC47: 611.1875 | AD47: 14.642749 | AE47: 0 | AF47: 6.76155 | AG47: 7.8811987 | AH47: 3.4079109 | AI47: 3.4079109 | AJ47: 0.69591667 | AK47: 1.2083333 | AL47: 0.41666667 | AM47: 0 | AN47: 681.6877 | AO47: 285.9188 | AP47: 7.8811987 | AQ47: 285.9188 | AR47: available_before_analytical_shutoff | AW47: 0 | AX47: no | AY47: no | AZ47: PASS | BA47: SRC-001;SRC-002;SRC-003 | BB47: P6M-BASE-P-0007:P6M-BASE-P-0007 | BD47: Severe Phase 6 analytical shutoff | BE47: SEVERE_NO_WAIVER | BF47: 2026-04-30 | BG47: 2026-10-31 | BH47: 2026-11-30 | BI47: 2027-02-28 | BL47: 263.90228 | BM47: 0 | BN47: 0 | BO47: 6.8131589 | BP47: 1.861981
C48: Base | D48: BASE | E48: P008 | F48: monthly | G48: 46266 | H48: 46295 | I48: FY2026 | J48: Q4 | K48: 30 | L48: 163.27792 | M48: 27.915917 | N48: 21.245425 | O48: -9.1912406 | P48: -3.013546 | Q48: -0.026773886 | R48: -5.7147271 | S48: 0 | T48: 12.490378 | U48: 25 | V48: 25 | W48: 611.1875 | X48: 0 | Y48: 0 | Z48: 0 | AA48: 0 | AB48: 0 | AC48: 611.1875 | AD48: 7.8811987 | AE48: 0 | AF48: 6.7986711 | AG48: 1.0825276 | AH48: 3.3707898 | AI48: 3.3707898 | AJ48: 0.69591667 | AK48: 1.2083333 | AL48: 0.41666667 | AM48: 0 | AN48: 674.88903 | AO48: 292.71747 | AP48: 1.0825276 | AQ48: 292.71747 | AR48: available_before_analytical_shutoff | AW48: 0 | AX48: no | AY48: no | AZ48: PASS | BA48: SRC-001;SRC-002;SRC-003 | BB48: P6M-BASE-P-0008:P6M-BASE-P-0008 | BD48: Moderate Phase 7 covenant-linked no-waiver | BE48: MODERATE_PHASE7_COVENANT_NO_WAIVER | BF48: 2026-10-31 | BG48: 2026-10-31 | BH48: 2026-11-30 | BI48: N/D | BL48: 263.90228 | BM48: 0 | BN48: 0 | BO48: 4.3787434 | BP48: 3.2181715
C49: Base | D49: BASE | E49: P009 | F49: monthly | G49: 46296 | H49: 46326 | I49: FY2026 | J49: Q4 | K49: 31 | L49: 163.27792 | M49: 27.915917 | N49: 21.245425 | O49: -9.1912406 | P49: -3.013546 | Q49: -0.026773886 | R49: -5.7147271 | S49: 0 | T49: 12.490378 | U49: 25 | V49: 25 | W49: 611.1875 | X49: 11.90625 | Y49: 11.90625 | Z49: 0 | AA49: 0 | AB49: 0 | AC49: 599.28125 | AD49: 1.0825276 | AE49: 5.070254 | AF49: 0 | AG49: 6.1527815 | AH49: 3.3334649 | AI49: 3.3334649 | AJ49: 0.69591667 | AK49: 1.2083333 | AL49: 0.41666667 | AM49: 0 | AN49: 668.05303 | AO49: 287.64722 | AP49: 6.1527815 | AQ49: 287.64722 | AR49: available_before_analytical_shutoff | AT49: 222.27366 | AU49: 3.0055429 | AW49: 0 | AX49: no | AY49: no | AZ49: PASS | BA49: SRC-001;SRC-002;SRC-003 | BB49: P6M-BASE-P-0009:P6M-BASE-P-0009 | BD49: Severe Phase 7 covenant-linked no-waiver | BE49: SEVERE_PHASE7_COVENANT_NO_WAIVER | BF49: 2026-04-30 | BG49: 2026-10-31 | BH49: 2026-11-30 | BI49: 2027-02-28 | BL49: 263.90228 | BM49: 0 | BN49: 0 | BO49: 6.8131589 | BP49: 1.861981
C50: Base | D50: BASE | E50: P010 | F50: monthly | G50: 46327 | H50: 46356 | I50: FY2027 | J50: Q1 | K50: 30 | L50: 133.34133 | M50: 22.909675 | N50: 10.674741 | O50: -7.5060503 | P50: -0.79217268 | Q50: 0.00050841992 | R50: -4.6669466 | S50: 0 | T50: 5.2161301 | U50: 25 | V50: 25 | W50: 599.28125 | X50: 0 | Y50: 0 | Z50: 0 | AA50: 0 | AB50: 0 | AC50: 599.28125 | AD50: 6.1527815 | AE50: 0.39394964 | AF50: 0 | AG50: 6.5467312 | AH50: 3.3158298 | AI50: 3.3158298 | AJ50: 0.66925 | AK50: 1.2083333 | AL50: 0.41666667 | AM50: 0 | AN50: 668.44698 | AO50: 287.25327 | AP50: 6.5467312 | AQ50: 287.25327 | AR50: available_before_analytical_shutoff | AT50: 222.27339 | AU50: 3.0073189 | AW50: 0 | AX50: no | AY50: no | AZ50: PASS | BA50: SRC-001;SRC-002;SRC-003 | BB50: P6M-BASE-P-0010:P6M-BASE-P-0010
C51: Base | D51: BASE | E51: P011 | F51: monthly | G51: 46357 | H51: 46387 | I51: FY2027 | J51: Q1 | K51: 31 | L51: 133.34133 | M51: 22.909675 | N51: 10.674741 | O51: -7.5060503 | P51: -0.79217268 | Q51: 0.00050841992 | R51: -4.6669466 | S51: 0 | T51: 5.2161301 | U51: 25 | V51: 25 | W51: 599.28125 | X51: 0 | Y51: 0 | Z51: 0 | AA51: 0 | AB51: 0 | AC51: 599.28125 | AD51: 6.5467312 | AE51: 0.39611243 | AF51: 0 | AG51: 6.9428436 | AH51: 3.3179926 | AI51: 3.3179926 | AJ51: 0.66925 | AK51: 1.2083333 | AL51: 0.41666667 | AM51: 0 | AN51: 668.84309 | AO51: 286.85716 | AP51: 6.9428436 | AQ51: 286.85716 | AR51: available_before_analytical_shutoff | AT51: 222.27313 | AU51: 3.0091046 | AW51: 0 | AX51: no | AY51: no | AZ51: PASS | BA51: SRC-001;SRC-002;SRC-003 | BB51: P6M-BASE-P-0011:P6M-BASE-P-0011
C52: Base | D52: BASE | E52: P012 | F52: monthly | G52: 46388 | H52: 46418 | I52: FY2027 | J52: Q1 | K52: 31 | L52: 133.34133 | M52: 22.909675 | N52: 10.674741 | O52: -7.5060503 | P52: -0.79217268 | Q52: 0.00050841992 | R52: -4.6669466 | S52: 0 | T52: 5.2161301 | U52: 25 | V52: 25 | W52: 599.28125 | X52: 11.90625 | Y52: 11.90625 | Z52: 0 | AA52: 0 | AB52: 0 | AC52: 587.375 | AD52: 6.9428436 | AE52: 12.304537 | AF52: 0 | AG52: 19.247381 | AH52: 3.3201672 | AI52: 3.3201672 | AJ52: 0.66925 | AK52: 1.2083333 | AL52: 0.41666667 | AM52: 0 | AN52: 669.24138 | AO52: 274.55262 | AP52: 19.247381 | AQ52: 274.55262 | AR52: available_before_analytical_shutoff | AT52: 222.27286 | AU52: 3.0109001 | AV52: 5.3859581 | AW52: 0 | AX52: no | AY52: no | AZ52: PASS | BA52: SRC-001;SRC-002;SRC-003 | BB52: P6M-BASE-P-0012:P6M-BASE-P-0012
C53: Base | D53: BASE | E53: P013 | F53: monthly | G53: 46419 | H53: 46446 | I53: FY2027 | J53: Q2 | K53: 28 | L53: 150.81846 | M53: 28.869322 | N53: 21.062132 | O53: -8.4898727 | P53: -3.1430649 | Q53: 0.00055246986 | R53: -5.2786461 | S53: 0 | T53: 12.640974 | U53: 25 | V53: 25 | W53: 587.375 | X53: 0 | Y53: 0 | Z53: 0 | AA53: 0 | AB53: 0 | AC53: 587.375 | AD53: 19.247381 | AE53: 0 | AF53: 7.0447512 | AG53: 12.20263 | AH53: 3.3019725 | AI53: 3.3019725 | AJ53: 0.66925 | AK53: 1.2083333 | AL53: 0.41666667 | AM53: 0 | AN53: 662.19663 | AO53: 281.59737 | AP53: 12.20263 | AQ53: 281.59737 | AR53: available_before_analytical_shutoff | AT53: 222.27233 | AU53: 2.979213 | AV53: 5.4281293 | AW53: 0 | AX53: no | AY53: no | AZ53: PASS | BA53: SRC-001;SRC-002;SRC-003 | BB53: P6M-BASE-P-0013:P6M-BASE-P-0013
C54: Base | D54: BASE | E54: P014 | F54: monthly | G54: 46447 | H54: 46477 | I54: FY2027 | J54: Q2 | K54: 31 | L54: 150.81846 | M54: 28.869322 | N54: 21.062132 | O54: -8.4898727 | P54: -3.1430649 | Q54: 0.00055246986 | R54: -5.2786461 | S54: 0 | T54: 12.640974 | U54: 25 | V54: 25 | W54: 587.375 | X54: 0 | Y54: 0 | Z54: 0 | AA54: 0 | AB54: 0 | AC54: 587.375 | AD54: 12.20263 | AE54: 0 | AF54: 7.0834271 | AG54: 5.1192024 | AH54: 3.2632966 | AI54: 3.2632966 | AJ54: 0.66925 | AK54: 1.2083333 | AL54: 0.41666667 | AM54: 0 | AN54: 655.1132 | AO54: 288.6808 | AP54: 5.1192024 | AQ54: 288.6808 | AR54: available_before_analytical_shutoff | AT54: 222.27181 | AU54: 2.9473518 | AV54: 5.471414 | AW54: 0 | AX54: no | AY54: no | AZ54: PASS | BA54: SRC-001;SRC-002;SRC-003 | BB54: P6M-BASE-P-0014:P6M-BASE-P-0014
C55: Base | D55: BASE | E55: P015 | F55: monthly | G55: 46478 | H55: 46507 | I55: FY2027 | J55: Q2 | K55: 30 | L55: 150.81846 | M55: 28.869322 | N55: 21.062132 | O55: -8.4898727 | P55: -3.1430649 | Q55: 0.00055246986 | R55: -5.2786461 | S55: 0 | T55: 12.640974 | U55: 25 | V55: 25 | W55: 587.375 | X55: 11.90625 | Y55: 11.90625 | Z55: 0 | AA55: 0 | AB55: 0 | AC55: 575.46875 | AD55: 5.1192024 | AE55: 4.7839347 | AF55: 0 | AG55: 9.9031372 | AH55: 3.2244084 | AI55: 3.2244084 | AJ55: 0.66925 | AK55: 1.2083333 | AL55: 0.41666667 | AM55: 0 | AN55: 647.99089 | AO55: 283.89686 | AP55: 9.9031372 | AQ55: 283.89686 | AR55: available_before_analytical_shutoff | AT55: 222.27128 | AU55: 2.9153154 | AV55: 5.5158525 | AW55: 0 | AX55: no | AY55: no | AZ55: PASS | BA55: SRC-001;SRC-002;SRC-003 | BB55: P6M-BASE-P-0015:P6M-BASE-P-0015
C56: Base | D56: BASE | E56: P016 | F56: monthly | G56: 46508 | H56: 46538 | I56: FY2027 | J56: Q3 | K56: 31 | L56: 165.08275 | M56: 27.690174 | N56: 21.107601 | O56: -9.2928379 | P56: -2.9536909 | Q56: 0.00060961406 | R56: -5.7778961 | S56: 0 | T56: 12.376624 | U56: 25 | V56: 25 | W56: 575.46875 | X56: 0 | Y56: 0 | Z56: 0 | AA56: 0 | AB56: 0 | AC56: 575.46875 | AD56: 9.9031372 | AE56: 0 | AF56: 6.8963416 | AG56: 3.0067955 | AH56: 3.1860323 | AI56: 3.1860323 | AJ56: 0.66925 | AK56: 1.2083333 | AL56: 0.41666667 | AM56: 0 | AN56: 641.09455 | AO56: 290.7932 | AP56: 3.0067955 | AQ56: 290.7932 | AR56: available_before_analytical_shutoff | AT56: 222.27075 | AU56: 2.8842956 | AV56: 5.5613985 | AW56: 0 | AX56: no | AY56: no | AZ56: PASS | BA56: SRC-001;SRC-002;SRC-003 | BB56: P6M-BASE-P-0016:P6M-BASE-P-0016
C57: Base | D57: BASE | E57: P017 | F57: monthly | G57: 46539 | H57: 46568 | I57: FY2027 | J57: Q3 | K57: 30 | L57: 165.08275 | M57: 27.690174 | N57: 21.107601 | O57: -9.2928379 | P57: -2.9536909 | Q57: 0.00060961406 | R57: -5.7778961 | S57: 0 | T57: 12.376624 | U57: 25 | V57: 28.916656 | W57: 575.46875 | X57: 0 | Y57: 0 | Z57: 0 | AA57: 0 | AB57: 0 | AC57: 575.46875 | AD57: 3.0067955 | AE57: 0 | AF57: 3.0067955 | AG57: 0 | AH57: 3.1589225 | AI57: 3.1589225 | AJ57: 0.66925 | AK57: 1.2083333 | AL57: 0.41666667 | AM57: 0 | AN57: 638.08775 | AO57: 297.71666 | AP57: 0 | AQ57: 293.8 | AR57: available_before_analytical_shutoff | AT57: 222.27023 | AU57: 2.8707748 | AV57: 5.6064807 | AW57: 0 | AX57: no | AY57: no | AZ57: PASS | BA57: SRC-001;SRC-002;SRC-003 | BB57: P6M-BASE-P-0017:P6M-BASE-P-0017
C58: Base | D58: BASE | E58: P018 | F58: monthly | G58: 46569 | H58: 46599 | I58: FY2027 | J58: Q3 | K58: 31 | L58: 165.08275 | M58: 27.690174 | N58: 21.107601 | O58: -9.2928379 | P58: -2.9536909 | Q58: 0.00060961406 | R58: -5.7778961 | S58: 0 | T58: 12.376624 | U58: 28.916656 | V58: 25 | W58: 575.46875 | X58: 11.90625 | Y58: 11.90625 | Z58: 0 | AA58: 0 | AB58: 0 | AC58: 563.5625 | AD58: 0 | AE58: 1.0281326 | AF58: 0 | AG58: 1.0281326 | AH58: 3.1209126 | AI58: 3.1209126 | AJ58: 0.66925 | AK58: 1.2083333 | AL58: 0.41666667 | AM58: 0 | AN58: 627.20963 | AO58: 292.77187 | AP58: 1.0281326 | AQ58: 292.77187 | AR58: available_before_analytical_shutoff | AT58: 222.2697 | AU58: 2.8218405 | AV58: 5.6525963 | AW58: 0 | AX58: no | AY58: no | AZ58: PASS | BA58: SRC-001;SRC-002;SRC-003 | BB58: P6M-BASE-P-0018:P6M-BASE-P-0018
C59: Base | D59: BASE | E59: P019 | F59: monthly | G59: 46600 | H59: 46630 | I59: FY2027 | J59: Q4 | K59: 31 | L59: 163.27384 | M59: 27.915917 | N59: 21.244893 | O59: -9.1910108 | P59: -3.0134707 | Q59: 0.00060200786 | R59: -5.7145843 | S59: 0 | T59: 12.517441 | U59: 25 | V59: 31.106739 | W59: 563.5625 | X59: 0 | Y59: 0 | Z59: 0 | AA59: 0 | AB59: 0 | AC59: 563.5625 | AD59: 1.0281326 | AE59: 0 | AF59: 1.0281326 | AG59: 0 | AH59: 3.0883192 | AI59: 3.0883192 | AJ59: 0.66925 | AK59: 1.2083333 | AL59: 0.41666667 | AM59: 0 | AN59: 626.1815 | AO59: 299.90674 | AP59: 0 | AQ59: 293.8 | AR59: available_before_analytical_shutoff | AT59: 222.26917 | AU59: 2.8172216 | AV59: 5.6989013 | AW59: 0 | AX59: no | AY59: no | AZ59: PASS | BA59: SRC-001;SRC-002;SRC-003 | BB59: P6M-BASE-P-0019:P6M-BASE-P-0019
C60: Base | D60: BASE | E60: P020 | F60: monthly | G60: 46631 | H60: 46660 | I60: FY2027 | J60: Q4 | K60: 30 | L60: 163.27384 | M60: 27.915917 | N60: 21.244893 | O60: -9.1910108 | P60: -3.0134707 | Q60: 0.00060200786 | R60: -5.7145843 | S60: 0 | T60: 12.517441 | U60: 31.106739 | V60: 38.244425 | W60: 563.5625 | X60: 0 | Y60: 0 | Z60: 0 | AA60: 0 | AB60: 0 | AC60: 563.5625 | AD60: 0 | AE60: 0 | AF60: 0 | AG60: 0 | AH60: 3.0855047 | AI60: 3.0855047 | AJ60: 0.66925 | AK60: 1.2083333 | AL60: 0.41666667 | AM60: 0 | AN60: 626.1815 | AO60: 307.04442 | AP60: 0 | AQ60: 293.8 | AR60: available_before_analytical_shutoff | AT60: 222.26864 | AU60: 2.8172284 | AV60: 5.74088 | AW60: 0 | AX60: no | AY60: no | AZ60: PASS | BA60: SRC-001;SRC-002;SRC-003 | BB60: P6M-BASE-P-0020:P6M-BASE-P-0020
C61: Base | D61: BASE | E61: P021 | F61: monthly | G61: 46661 | H61: 46691 | I61: FY2027 | J61: Q4 | K61: 31 | L61: 163.27384 | M61: 27.915917 | N61: 21.244893 | O61: -9.1910108 | P61: -3.0134707 | Q61: 0.00060200786 | R61: -5.7145843 | S61: 0 | T61: 12.517441 | U61: 38.244425 | V61: 29.254227 | W61: 563.5625 | X61: 11.90625 | Y61: 11.90625 | Z61: 4.2542269 | AA61: 0 | AB61: 0 | AC61: 547.40202 | AD61: 0 | AE61: 0 | AF61: 0 | AG61: 0 | AH61: 3.0529113 | AI61: 3.0529113 | AJ61: 0.66925 | AK61: 1.2083333 | AL61: 0.41666667 | AM61: 0 | AN61: 610.02102 | AO61: 298.05423 | AP61: 0 | AQ61: 293.8 | AR61: available_before_analytical_shutoff | AT61: 222.2681 | AU61: 2.7445279 | AV61: 5.7827699 | AW61: 0 | AX61: no | AY61: no | AZ61: PASS | BA61: SRC-001;SRC-002;SRC-003 | BB61: P6M-BASE-P-0021:P6M-BASE-P-0021
C62: Base | D62: BASE | E62: P022 | F62: monthly | G62: 46692 | H62: 46721 | I62: FY2028 | J62: Q1 | K62: 30 | L62: 133.338 | M62: 22.909675 | N62: 10.674474 | O62: -7.5058626 | P62: -0.79215288 | Q62: 0.00050840721 | R62: -4.66683 | S62: 0 | T62: 5.2159997 | U62: 29.254227 | V62: 29.279034 | W62: 547.40202 | X62: 0 | Y62: 0 | Z62: 0 | AA62: 0 | AB62: 0 | AC62: 547.40202 | AD62: 0 | AE62: 0 | AF62: 0 | AG62: 0 | AH62: 2.9970261 | AI62: 2.9970261 | AJ62: 0.56916667 | AK62: 1.2083333 | AL62: 0.41666667 | AM62: 0 | AN62: 610.02102 | AO62: 298.07903 | AP62: 0 | AQ62: 293.8 | AR62: available_before_analytical_shutoff | AT62: 222.26784 | AU62: 2.7445312 | AV62: 5.8311283 | AW62: 0 | AX62: no | AY62: no | AZ62: PASS | BA62: SRC-001;SRC-002;SRC-003 | BB62: P6M-BASE-P-0022:P6M-BASE-P-0022
C63: Base | D63: BASE | E63: P023 | F63: monthly | G63: 46722 | H63: 46752 | I63: FY2028 | J63: Q1 | K63: 31 | L63: 133.338 | M63: 22.909675 | N63: 10.674474 | O63: -7.5058626 | P63: -0.79215288 | Q63: 0.00050840721 | R63: -4.66683 | S63: 0 | T63: 5.2159997 | U63: 29.279034 | V63: 29.303841 | W63: 547.40202 | X63: 0 | Y63: 0 | Z63: 0 | AA63: 0 | AB63: 0 | AC63: 547.40202 | AD63: 0 | AE63: 0 | AF63: 0 | AG63: 0 | AH63: 2.9970261 | AI63: 2.9970261 | AJ63: 0.56916667 | AK63: 1.2083333 | AL63: 0.41666667 | AM63: 0 | AN63: 610.02102 | AO63: 298.10384 | AP63: 0 | AQ63: 293.8 | AR63: available_before_analytical_shutoff | AT63: 222.26757 | AU63: 2.7445345 | AV63: 5.880639 | AW63: 0 | AX63: no | AY63: no | AZ63: PASS | BA63: SRC-001;SRC-002;SRC-003 | BB63: P6M-BASE-P-0023:P6M-BASE-P-0023
... C76: Base | D76: BASE | E76: P036 | F76: quarterly | G76: 47788 | H76: 47879 | I76: FY2031 | J76: Q1 | K76: 92 | L76: 399.984 | M76: 22.909675 | N76: 32.021021 | O76: -22.515899 | P76: -2.3762804 | Q76: 0.0015251072 | R76: -13.99944 | S76: 0 | T76: 15.646826 | U76: 48.214666 | V76: 25 | W76: 351.48908 | X76: 11.90625 | Y76: 11.90625 | Z76: 0 | AA76: 339.58283 | AB76: 14.803127 | AC76: 324.77971 | AD76: 0 | AE76: 0 | AF76: 0 | AG76: 0 | AH76: 5.7406148 | AI76: 5.7406148 | AJ76: 1.5365 | AK76: 3.625 | AL76: 1.25 | AM76: 0 | AN76: 387.39871 | AO76: 0 | AP76: 0 | AQ76: 0 | AR76: available_before_analytical_shutoff | AT76: 222.25063 | AU76: 1.7430713 | AV76: 8.7916563 | AW76: 324.77971 | AX76: yes | AY76: no | AZ76: MATURITY_SHORTFALL | BA76: SRC-001;SRC-002;SRC-003 | BB76: P6M-BASE-P-0058:P6M-BASE-P-0060
C77: Moderate unmitigated | D77: MODERATE_UNMITIGATED | E77: P001 | F77: monthly | G77: 46054 | H77: 46081 | I77: FY2026 | J77: Q2 | K77: 28 | L77: 84.611271 | M77: 28.869322 | N77: 10.123926 | O77: -8.4900849 | P77: -1.3402471 | Q77: -14.685874 | R77: -2.9613945 | S77: -0.44 | T77: -9.3035892 | U77: 25 | V77: 25 | W77: 635 | X77: 0 | Y77: 0 | Z77: 0 | AA77: 0 | AB77: 0 | AC77: 635 | AD77: 29.897719 | AE77: 15.868956 | AF77: 0 | AG77: 45.766674 | AH77: 4.2444498 | AI77: 4.2444498 | AJ77: 0.69591667 | AK77: 1.2083333 | AL77: 0.41666667 | AM77: 0 | AN77: 743.38567 | AO77: 248.03333 | AP77: 45.766674 | AQ77: 248.03333 | AR77: available_before_analytical_shutoff | AW77: 0 | AX77: no | AY77: no | AZ77: PASS | BA77: SRC-001;SRC-002;SRC-003 | BB77: P6M-MODERATE_UNMITIGATED-P-0001:P6M-MODERATE_UNMITIGATED-P-0001
C78: Moderate unmitigated | D78: MODERATE_UNMITIGATED | E78: P002 | F78: monthly | G78: 46082 | H78: 46112 | I78: FY2026 | J78: Q2 | K78: 31 | L78: 126.91691 | M78: 28.869322 | N78: 15.185889 | O78: -8.4900849 | P78: -2.0103707 | Q78: -22.028811 | R78: -4.4420917 | S78: -0.66 | T78: -13.955384 | U78: 25 | V78: 25 | W78: 635 | X78: 0 | Y78: 0 | Z78: 0 | AA78: 0 | AB78: 0 | AC78: 635 | AD78: 45.766674 | AE78: 20.635893 | AF78: 0 | AG78: 66.402567 | AH78: 4.3595921 | AI78: 4.3595921 | AJ78: 0.69591667 | AK78: 1.2083333 | AL78: 0.41666667 | AM78: 0 | AN78: 764.02157 | AO78: 227.39743 | AP78: 66.402567 | AQ78: 227.39743 | AR78: available_before_analytical_shutoff | AW78: 0 | AX78: no | AY78: no | AZ78: PASS | BA78: SRC-001;SRC-002;SRC-003 | BB78: P6M-MODERATE_UNMITIGATED-P-0002:P6M-MODERATE_UNMITIGATED-P-0002
C79: Moderate unmitigated | D79: MODERATE_UNMITIGATED | E79: P003 | F79: monthly | G79: 46113 | H79: 46142 | I79: FY2026 | J79: Q2 | K79: 30 | L79: 211.52818 | M79: 28.869322 | N79: 25.309815 | O79: -8.4900849 | P79: -3.3506178 | Q79: -36.714684 | R79: -7.4034862 | S79: -1.1 | T79: -23.258973 | U79: 25 | V79: 25 | W79: 635 | X79: 11.90625 | Y79: 11.90625 | Z79: 0 | AA79: 0 | AB79: 0 | AC79: 623.09375 | AD79: 66.402567 | AE79: 42.00576 | AF79: 0 | AG79: 108.40833 | AH79: 4.5196201 | AI79: 4.5196201 | AJ79: 0.69591667 | AK79: 1.2083333 | AL79: 0.41666667 | AM79: 0 | AN79: 794.12108 | AO79: 185.39167 | AP79: 108.40833 | AQ79: 185.39167 | AR79: available_before_analytical_shutoff | AW79: 0 | AX79: no | AY79: no | AZ79: PASS | BA79: SRC-001;SRC-002;SRC-003 | BB79: P6M-MODERATE_UNMITIGATED-P-0003:P6M-MODERATE_UNMITIGATED-P-0003
C80: Moderate unmitigated | D80: MODERATE_UNMITIGATED | E80: P004 | F80: monthly | G80: 46143 | H80: 46173 | I80: FY2026 | J80: Q3 | K80: 31 | L80: 92.613736 | M80: 27.690174 | N80: 9.9893857 | O80: -9.2930702 | P80: -1.1939933 | Q80: 0.95451854 | R80: -3.2414807 | S80: -0.3 | T80: 6.2084302 | U80: 25 | V80: 25 | W80: 623.09375 | X80: 0 | Y80: 0 | Z80: 0 | AA80: 0 | AB80: 0 | AC80: 623.09375 | AD80: 108.40833 | AE80: 0.72934593 | AF80: 0 | AG80: 109.13767 | AH80: 4.6168594 | AI80: 4.6168594 | AJ80: 0.69591667 | AK80: 1.2083333 | AL80: 0.41666667 | AM80: 0 | AN80: 794.85042 | AO80: 184.66233 | AP80: 109.13767 | AQ80: 184.66233 | AR80: available_before_analytical_shutoff | AW80: 0 | AX80: no | AY80: no | AZ80: PASS | BA80: SRC-001;SRC-002;SRC-003 | BB80: P6M-MODERATE_UNMITIGATED-P-0004:P6M-MODERATE_UNMITIGATED-P-0004
C81: Moderate unmitigated | D81: MODERATE_UNMITIGATED | E81: P005 | F81: monthly | G81: 46174 | H81: 46203 | I81: FY2026 | J81: Q3 | K81: 30 | L81: 138.9206 | M81: 27.690174 | N81: 14.984079 | O81: -9.2930702 | P81: -1.79099 | Q81: 1.4317778 | R81: -4.8622211 | S81: -0.45 | T81: 9.3126452 | U81: 25 | V81: 25 | W81: 623.09375 | X81: 0 | Y81: 0 | Z81: 0 | AA81: 0 | AB81: 0 | AC81: 623.09375 | AD81: 109.13767 | AE81: 0 | AF81: 2.3800758 | AG81: 106.7576 | AH81: 4.6116527 | AI81: 4.6116527 | AJ81: 0.69591667 | AK81: 1.2083333 | AL81: 0.41666667 | AM81: 0 | AN81: 792.47035 | AO81: 187.0424 | AP81: 106.7576 | AQ81: 187.0424 | AR81: available_before_analytical_shutoff | AW81: 0 | AX81: no | AY81: no | AZ81: PASS | BA81: SRC-001;SRC-002;SRC-003 | BB81: P6M-MODERATE_UNMITIGATED-P-0005:P6M-MODERATE_UNMITIGATED-P-0005
C82: Moderate unmitigated | D82: MODERATE_UNMITIGATED | E82: P006 | F82: monthly | G82: 46204 | H82: 46234 | I82: FY2026 | J82: Q3 | K82: 31 | L82: 231.53434 | M82: 27.690174 | N82: 24.973464 | O82: -9.2930702 | P82: -2.9849833 | Q82: 2.3862964 | R82: -8.1037019 | S82: -0.75 | T82: 15.521075 | U82: 25 | V82: 25 | W82: 623.09375 | X82: 11.90625 | Y82: 11.90625 | Z82: 0 | AA82: 0 | AB82: 0 | AC82: 611.1875 | AD82: 106.7576 | AE82: 3.2830378 | AF82: 0 | AG82: 110.04063 | AH82: 4.5769465 | AI82: 4.5769465 | AJ82: 0.69591667 | AK82: 1.2083333 | AL82: 0.41666667 | AM82: 0 | AN82: 783.84713 | AO82: 183.75937 | AP82: 110.04063 | AQ82: 183.75937 | AR82: available_before_analytical_shutoff | AW82: 0 | AX82: no | AY82: no | AZ82: PASS | BA82: SRC-001;SRC-002;SRC-003 | BB82: P6M-MODERATE_UNMITIGATED-P-0006:P6M-MODERATE_UNMITIGATED-P-0006
C83: Moderate unmitigated | D83: MODERATE_UNMITIGATED | E83: P007 | F83: monthly | G83: 46235 | H83: 46265 | I83: FY2026 | J83: Q4 | K83: 31 | L83: 91.598912 | M83: 27.915917 | N83: 10.086705 | O83: -9.1912406 | P83: -1.2326048 | Q83: 0.94214784 | R83: -3.2059619 | S83: 0 | T83: 6.5902861 | U83: 25 | V83: 25 | W83: 611.1875 | X83: 0 | Y83: 0 | Z83: 0 | AA83: 0 | AB83: 0 | AC83: 611.1875 | AD83: 110.04063 | AE83: 0.28126519 | AF83: 0 | AG83: 110.3219 | AH83: 4.5506346 | AI83: 4.5506346 | AJ83: 0.69591667 | AK83: 1.2083333 | AL83: 0.41666667 | AM83: 0 | AN83: 784.1284 | AO83: 183.4781 | AP83: 110.3219 | AQ83: 183.4781 | AR83: available_before_analytical_shutoff | AW83: 0 | AX83: no | AY83: no | AZ83: PASS | BA83: SRC-001;SRC-002;SRC-003 | BB83: P6M-MODERATE_UNMITIGATED-P-0007:P6M-MODERATE_UNMITIGATED-P-0007
C84: Moderate unmitigated | D84: MODERATE_UNMITIGATED | E84: P008 | F84: monthly | G84: 46266 | H84: 46295 | I84: FY2026 | J84: Q4 | K84: 30 | L84: 137.39837 | M84: 27.915917 | N84: 15.130057 | O84: -9.1912406 | P84: -1.8489071 | Q84: 1.4132218 | R84: -4.8089429 | S84: 0 | T84: 9.8854292 | U84: 25 | V84: 25 | W84: 611.1875 | X84: 0 | Y84: 0 | Z84: 0 | AA84: 0 | AB84: 0 | AC84: 611.1875 | AD84: 110.3219 | AE84: 0 | AF84: 3.0225243 | AG84: 107.29938 | AH84: 4.5419883 | AI84: 4.5419883 | AJ84: 0.69591667 | AK84: 1.2083333 | AL84: 0.41666667 | AM84: 0 | AN84: 781.10588 | AO84: 186.50062 | AP84: 107.29938 | AQ84: 186.50062 | AR84: available_before_analytical_shutoff | AW84: 0 | AX84: no | AY84: no | AZ84: PASS | BA84: SRC-001;SRC-002;SRC-003 | BB84: P6M-MODERATE_UNMITIGATED-P-0008:P6M-MODERATE_UNMITIGATED-P-0008
C85: Moderate unmitigated | D85: MODERATE_UNMITIGATED | E85: P009 | F85: monthly | G85: 46296 | H85: 46326 | I85: FY2026 | J85: Q4 | K85: 31 | L85: 228.99728 | M85: 27.915917 | N85: 25.216762 | O85: -9.1912406 | P85: -3.0815119 | Q85: 2.3553696 | R85: -8.0149048 | S85: 0 | T85: 16.475715 | U85: 25 | V85: 25 | W85: 611.1875 | X85: 11.90625 | Y85: 11.90625 | Z85: 0 | AA85: 0 | AB85: 0 | AC85: 599.28125 | AD85: 107.29938 | AE85: 2.2534596 | AF85: 0 | AG85: 109.55284 | AH85: 4.5020082 | AI85: 4.5020082 | AJ85: 0.69591667 | AK85: 1.2083333 | AL85: 0.41666667 | AM85: 0 | AN85: 771.45309 | AO85: 184.24716 | AP85: 109.55284 | AQ85: 184.24716 | AR85: continued_draw_or_waiver_after_warning | AT85: 183.02511 | AU85: 4.2150123 | AW85: 0 | AX85: no | AY85: no | AZ85: BREACHED_ANALYTICAL_THRESHOLD | BA85: SRC-001;SRC-002;SRC-003 | BB85: P6M-MODERATE_UNMITIGATED-P-0009:P6M-MODERATE_UNMITIGATED-P-0009
C86: Moderate unmitigated | D86: MODERATE_UNMITIGATED | E86: P010 | F86: monthly | G86: 46327 | H86: 46356 | I86: FY2027 | J86: Q1 | K86: 30 | L86: 74.804488 | M86: 22.909675 | N86: 4.49244 | O86: -7.5060503 | P86: -0.070386437 | Q86: 0.82176262 | R86: -2.6181571 | S86: 0 | T86: 2.6256591 | U86: 25 | V86: 25 | W86: 599.28125 | X86: 0 | Y86: 0 | Z86: 0 | AA86: 0 | AB86: 0 | AC86: 599.28125 | AD86: 109.55284 | AE86: 4.1532527 | AF86: 0 | AG86: 113.70609 | AH86: 4.4846617 | AI86: 4.4846617 | AJ86: 0.66925 | AK86: 1.2083333 | AL86: 0.41666667 | AM86: 0 | AN86: 775.60634 | AO86: 180.09391 | AP86: 113.70609 | AQ86: 180.09391 | AR86: continued_draw_or_waiver_after_warning | AT86: 176.84254 | AU86: 4.3858584 | AW86: 0 | AX86: no | AY86: no | AZ86: BREACHED_ANALYTICAL_THRESHOLD | BA86: SRC-001;SRC-002;SRC-003 | BB86: P6M-MODERATE_UNMITIGATED-P-0010:P6M-MODERATE_UNMITIGATED-P-0010
C87: Moderate unmitigated | D87: MODERATE_UNMITIGATED | E87: P011 | F87: monthly | G87: 46357 | H87: 46387 | I87: FY2027 | J87: Q1 | K87: 31 | L87: 112.20673 | M87: 22.909675 | N87: 6.7386599 | O87: -7.5060503 | P87: -0.10557965 | Q87: 1.2326439 | R87: -3.9272356 | S87: 0 | T87: 3.9384886 | U87: 25 | V87: 25 | W87: 599.28125 | X87: 0 | Y87: 0 | Z87: 0 | AA87: 0 | AB87: 0 | AC87: 599.28125 | AD87: 113.70609 | AE87: 2.8625521 | AF87: 0 | AG87: 116.56864 | AH87: 4.5067908 | AI87: 4.5067908 | AJ87: 0.66925 | AK87: 1.2083333 | AL87: 0.41666667 | AM87: 0 | AN87: 778.46889 | AO87: 177.23136 | AP87: 116.56864 | AQ87: 177.23136 | AR87: continued_draw_or_waiver_after_warning | AT87: 172.90619 | AU87: 4.5022615 | AW87: 0 | AX87: no | AY87: no | AZ87: BREACHED_ANALYTICAL_THRESHOLD | BA87: SRC-001;SRC-002;SRC-003 | BB87: P6M-MODERATE_UNMITIGATED-P-0011:P6M-MODERATE_UNMITIGATED-P-0011
C88: Moderate unmitigated | D88: MODERATE_UNMITIGATED | E88: P012 | F88: monthly | G88: 46388 | H88: 46418 | I88: FY2027 | J88: Q1 | K88: 31 | L88: 187.01122 | M88: 22.909675 | N88: 11.2311 | O88: -7.5060503 | P88: -0.17596609 | Q88: 2.0544065 | R88: -6.5453927 | S88: 0 | T88: 6.5641477 | U88: 25 | V88: 25 | W88: 599.28125 | X88: 11.90625 | Y88: 11.90625 | Z88: 0 | AA88: 0 | AB88: 0 | AC88: 587.375 | AD88: 116.56864 | AE88: 12.15295 | AF88: 0 | AG88: 128.72159 | AH88: 4.5165979 | AI88: 4.5165979 | AJ88: 0.66925 | AK88: 1.2083333 | AL88: 0.41666667 | AM88: 0 | AN88: 778.71559 | AO88: 165.07841 | AP88: 128.72159 | AQ88: 165.07841 | AR88: continued_draw_or_waiver_after_warning | AT88: 173.46228 | AU88: 4.4892502 | AV88: 3.2103738 | AW88: 0 | AX88: no | AY88: no | AZ88: BREACHED_ANALYTICAL_THRESHOLD | BA88: SRC-001;SRC-002;SRC-003 | BB88: P6M-MODERATE_UNMITIGATED-P-0012:P6M-MODERATE_UNMITIGATED-P-0012
C89: Moderate unmitigated | D89: MODERATE_UNMITIGATED | E89: P013 | F89: monthly | G89: 46419 | H89: 46446 | I89: FY2027 | J89: Q2 | K89: 28 | L89: 86.079635 | M89: 28.869322 | N89: 10.730017 | O89: -8.4898727 | P89: -1.4711056 | Q89: 3.4826496 | R89: -3.0127872 | S89: 0 | T89: 9.7287742 | U89: 25 | V89: 25 | W89: 587.375 | X89: 0 | Y89: 0 | Z89: 0 | AA89: 0 | AB89: 0 | AC89: 587.375 | AD89: 128.72159 | AE89: 0 | AF89: 3.0757159 | AG89: 125.64587 | AH89: 4.3588083 | AI89: 4.3588083 | AJ89: 0.66925 | AK89: 1.2083333 | AL89: 0.41666667 | AM89: 0 | AN89: 775.63987 | AO89: 168.15413 | AP89: 125.64587 | AQ89: 168.15413 | AR89: continued_draw_or_waiver_after_warning | AT89: 174.06837 | AU89: 4.4559494 | AV89: 3.214787 | AW89: 0 | AX89: no | AY89: no | AZ89: BREACHED_ANALYTICAL_THRESHOLD | BA89: SRC-001;SRC-002;SRC-003 | BB89: P6M-MODERATE_UNMITIGATED-P-0013:P6M-MODERATE_UNMITIGATED-P-0013
C90: Moderate unmitigated | D90: MODERATE_UNMITIGATED | E90: P014 | F90: monthly | G90: 46447 | H90: 46477 | I90: FY2027 | J90: Q2 | K90: 31 | L90: 129.11945 | M90: 28.869322 | N90: 16.095026 | O90: -8.4898727 | P90: -2.2066585 | Q90: 5.2239745 | R90: -4.5191809 | S90: 0 | T90: 14.593161 | U90: 25 | V90: 25 | W90: 587.375 | X90: 0 | Y90: 0 | Z90: 0 | AA90: 0 | AB90: 0 | AC90: 587.375 | AD90: 125.64587 | AE90: 0 | AF90: 7.973804 | AG90: 117.67207 | AH90: 4.3251072 | AI90: 4.3251072 | AJ90: 0.66925 | AK90: 1.2083333 | AL90: 0.41666667 | AM90: 0 | AN90: 767.66607 | AO90: 176.12793 | AP90: 117.67207 | AQ90: 176.12793 | AR90: continued_draw_or_waiver_after_warning | AT90: 174.97751 | AU90: 4.387227 | AV90: 3.2336369 | AW90: 0 | AX90: no | AY90: no | AZ90: BREACHED_ANALYTICAL_THRESHOLD | BA90: SRC-001;SRC-002;SRC-003 | BB90: P6M-MODERATE_UNMITIGATED-P-0014:P6M-MODERATE_UNMITIGATED-P-0014
C91: Moderate unmitigated | D91: MODERATE_UNMITIGATED | E91: P015 | F91: monthly | G91: 46478 | H91: 46507 | I91: FY2027 | J91: Q2 | K91: 30 | L91: 215.19909 | M91: 28.869322 | N91: 26.825044 | O91: -8.4898727 | P91: -3.6777641 | Q91: 8.7066241 | R91: -7.5319681 | S91: 0 | T91: 24.321935 | U91: 25 | V91: 25 | W91: 587.375 | X91: 11.90625 | Y91: 11.90625 | Z91: 0 | AA91: 0 | AB91: 0 | AC91: 575.46875 | AD91: 117.67207 | AE91: 0 | AF91: 5.8748807 | AG91: 111.79719 | AH91: 4.2465547 | AI91: 4.2465547 | AJ91: 0.66925 | AK91: 1.2083333 | AL91: 0.41666667 | AM91: 0 | AN91: 749.88494 | AO91: 182.00281 | AP91: 111.79719 | AQ91: 182.00281 | AR91: continued_draw_or_waiver_after_warning | AT91: 176.49274 | AU91: 4.2488147 | AV91: 3.2781816 | AW91: 0 | AX91: no | AY91: no | AZ91: BREACHED_ANALYTICAL_THRESHOLD | BA91: SRC-001;SRC-002;SRC-003 | BB91: P6M-MODERATE_UNMITIGATED-P-0015:P6M-MODERATE_UNMITIGATED-P-0015
C92: Moderate unmitigated | D92: MODERATE_UNMITIGATED | E92: P016 | F92: monthly | G92: 46508 | H92: 46538 | I92: FY2027 | J92: Q3 | K92: 31 | L92: 95.830534 | M92: 27.690174 | N92: 11.294657 | O92: -9.2928379 | P92: -1.4750412 | Q92: 3.2672336 | R92: -3.3540687 | S92: 0 | T92: 9.7327809 | U92: 25 | V92: 25 | W92: 575.46875 | X92: 0 | Y92: 0 | Z92: 0 | AA92: 0 | AB92: 0 | AC92: 575.46875 | AD92: 111.79719 | AE92: 0 | AF92: 3.3994032 | AG92: 108.39779 | AH92: 4.0391278 | AI92: 4.0391278 | AJ92: 0.66925 | AK92: 1.2083333 | AL92: 0.41666667 | AM92: 0 | AN92: 746.48554 | AO92: 185.40221 | AP92: 108.39779 | AQ92: 185.40221 | AR92: continued_draw_or_waiver_after_warning | AT92: 177.79801 | AU92: 4.1985033 | AV92: 3.3382478 | AW92: 0 | AX92: no | AY92: no | AZ92: BREACHED_ANALYTICAL_THRESHOLD | BA92: SRC-001;SRC-002;SRC-003 | BB92: P6M-MODERATE_UNMITIGATED-P-0016:P6M-MODERATE_UNMITIGATED-P-0016
C93: Moderate unmitigated | D93: MODERATE_UNMITIGATED | E93: P017 | F93: monthly | G93: 46539 | H93: 46568 | I93: FY2027 | J93: Q3 | K93: 30 | L93: 143.7458 | M93: 27.690174 | N93: 16.941986 | O93: -9.2928379 | P93: -2.2125618 | Q93: 4.9008504 | R93: -5.031103 | S93: 0 | T93: 14.599171 | U93: 25 | V93: 25 | W93: 575.46875 | X93: 0 | Y93: 0 | Z93: 0 | AA93: 0 | AB93: 0 | AC93: 575.46875 | AD93: 108.39779 | AE93: 0 | AF93: 8.3002589 | AG93: 100.09753 | AH93: 4.0046625 | AI93: 4.0046625 | AJ93: 0.66925 | AK93: 1.2083333 | AL93: 0.41666667 | AM93: 0 | AN93: 738.18528 | AO93: 193.70247 | AP93: 100.09753 | AQ93: 193.70247 | AR93: continued_draw_or_waiver_after_warning | AT93: 179.75592 | AU93: 4.1065979 | AV93: 3.4139154 | AW93: 0 | AX93: no | AY93: no | AZ93: BREACHED_ANALYTICAL_THRESHOLD | BA93: SRC-001;SRC-002;SRC-003 | BB93: P6M-MODERATE_UNMITIGATED-P-0017:P6M-MODERATE_UNMITIGATED-P-0017
C94: Moderate unmitigated | D94: MODERATE_UNMITIGATED | E94: P018 | F94: monthly | G94: 46569 | H94: 46599 | I94: FY2027 | J94: Q3 | K94: 31 | L94: 239.57633 | M94: 27.690174 | N94: 28.236643 | O94: -9.2928379 | P94: -3.687603 | Q94: 8.168084 | R94: -8.3851717 | S94: 0 | T94: 24.331952 | U94: 25 | V94: 25 | W94: 575.46875 | X94: 11.90625 | Y94: 11.90625 | Z94: 0 | AA94: 0 | AB94: 0 | AC94: 563.5625 | AD94: 100.09753 | AE94: 0 | AF94: 6.2045925 | AG94: 93.892935 | AH94: 3.9268598 | AI94: 3.9268598 | AJ94: 0.66925 | AK94: 1.2083333 | AL94: 0.41666667 | AM94: 0 | AN94: 720.07444 | AO94: 199.90706 | AP94: 93.892935 | AQ94: 199.90706 | AR94: continued_draw_or_waiver_after_warning | AT94: 183.0191 | AU94: 3.9344224 | AV94: 3.5193407 | AW94: 0 | AX94: no | AY94: no | AZ94: BREACHED_ANALYTICAL_THRESHOLD | BA94: SRC-001;SRC-002;SRC-003 | BB94: P6M-MODERATE_UNMITIGATED-P-0018:P6M-MODERATE_UNMITIGATED-P-0018
C95: Moderate unmitigated | D95: MODERATE_UNMITIGATED | E95: P019 | F95: monthly | G95: 46600 | H95: 46630 | I95: FY2027 | J95: Q4 | K95: 31 | L95: 96.372382 | M95: 27.915917 | N95: 12.057936 | O95: -9.1910108 | P95: -1.6582356 | Q95: 3.1248994 | R95: -3.3730334 | S95: 0 | T95: 10.151567 | U95: 25 | V95: 25 | W95: 563.5625 | X95: 0 | Y95: 0 | Z95: 0 | AA95: 0 | AB95: 0 | AC95: 563.5625 | AD95: 93.892935 | AE95: 0 | AF95: 4.1325218 | AG95: 89.760413 | AH95: 3.7247951 | AI95: 3.7247951 | AJ95: 0.66925 | AK95: 1.2083333 | AL95: 0.41666667 | AM95: 0 | AN95: 715.94191 | AO95: 204.03959 | AP95: 89.760413 | AQ95: 204.03959 | AR95: continued_draw_or_waiver_after_warning | AT95: 184.99033 | AU95: 3.8701586 | AV95: 3.6146482 | AW95: 0 | AX95: no | AY95: no | AZ95: BREACHED_ANALYTICAL_THRESHOLD | BA95: SRC-001;SRC-002;SRC-003 | BB95: P6M-MODERATE_UNMITIGATED-P-0019:P6M-MODERATE_UNMITIGATED-P-0019
C96: Moderate unmitigated | D96: MODERATE_UNMITIGATED | E96: P020 | F96: monthly | G96: 46631 | H96: 46660 | I96: FY2027 | J96: Q4 | K96: 30 | L96: 144.55857 | M96: 27.915917 | N96: 18.086905 | O96: -9.1910108 | P96: -2.4873534 | Q96: 4.6873491 | R96: -5.05955 | S96: 0 | T96: 15.22735 | U96: 25 | V96: 25 | W96: 563.5625 | X96: 0 | Y96: 0 | Z96: 0 | AA96: 0 | AB96: 0 | AC96: 563.5625 | AD96: 89.760413 | AE96: 0 | AF96: 9.2463235 | AG96: 80.51409 | AH96: 3.6867769 | AI96: 3.6867769 | AJ96: 0.66925 | AK96: 1.2083333 | AL96: 0.41666667 | AM96: 0 | AN96: 706.69559 | AO96: 213.28591 | AP96: 80.51409 | AQ96: 213.28591 | AR96: continued_draw_or_waiver_after_warning | AT96: 187.94718 | AU96: 3.7600756 | AV96: 3.7348351 | AW96: 0 | AX96: no | AY96: no | AZ96: BREACHED_ANALYTICAL_THRESHOLD | BA96: SRC-001;SRC-002;SRC-003 | BB96: P6M-MODERATE_UNMITIGATED-P-0020:P6M-MODERATE_UNMITIGATED-P-0020
C97: Moderate unmitigated | D97: MODERATE_UNMITIGATED | E97: P021 | F97: monthly | G97: 46661 | H97: 46691 | I97: FY2027 | J97: Q4 | K97: 31 | L97: 240.93095 | M97: 27.915917 | N97: 30.144841 | O97: -9.1910108 | P97: -4.145589 | Q97: 7.8122486 | R97: -8.4325834 | S97: 0 | T97: 25.378917 | U97: 25 | V97: 25 | W97: 563.5625 | X97: 11.90625 | Y97: 11.90625 | Z97: 0 | AA97: 0 | AB97: 0 | AC97: 551.65625 | AD97: 80.51409 | AE97: 0 | AF97: 7.5732697 | AG97: 72.94082 | AH97: 3.6051476 | AI97: 3.6051476 | AJ97: 0.66925 | AK97: 1.2083333 | AL97: 0.41666667 | AM97: 0 | AN97: 687.21607 | AO97: 220.85918 | AP97: 72.94082 | AQ97: 220.85918 | AR97: continued_draw_or_waiver_after_warning | AT97: 192.87526 | AU97: 3.563008 | AV97: 3.9023122 | AW97: 0 | AX97: no | AY97: no | AZ97: PASS | BA97: SRC-001;SRC-002;SRC-003 | BB97: P6M-MODERATE_UNMITIGATED-P-0021:P6M-MODERATE_UNMITIGATED-P-0021
C98: Moderate unmitigated | D98: MODERATE_UNMITIGATED | E98: P022 | F98: monthly | G98: 46692 | H98: 46721 | I98: FY2028 | J98: Q1 | K98: 30 | L98: 133.338 | M98: 22.909675 | N98: 10.674474 | O98: -7.5058626 | P98: -0.79215288 | Q98: 5.2154227 | R98: -4.66683 | S98: 0 | T98: 10.430914 | U98: 25 | V98: 25 | W98: 551.65625 | X98: 0 | Y98: 0 | Z98: 0 | AA98: 0 | AB98: 0 | AC98: 551.65625 | AD98: 72.94082 | AE98: 0 | AF98: 4.8303013 | AG98: 68.110519 | AH98: 3.406446 | AI98: 3.406446 | AJ98: 0.56916667 | AK98: 1.2083333 | AL98: 0.41666667 | AM98: 0 | AN98: 682.38577 | AO98: 225.68948 | AP98: 68.110519 | AQ98: 225.68948 | AR98: continued_draw_or_waiver_after_warning | AT98: 199.05729 | AU98: 3.4280873 | AV98: 4.117205 | AW98: 0 | AX98: no | AY98: no | AZ98: BREACHED_ANALYTICAL_THRESHOLD | BA98: SRC-001;SRC-002;SRC-003 | BB98: P6M-MODERATE_UNMITIGATED-P-0022:P6M-MODERATE_UNMITIGATED-P-0022
C99: Moderate unmitigated | D99: MODERATE_UNMITIGATED | E99: P023 | F99: monthly | G99: 46722 | H99: 46752 | I99: FY2028 | J99: Q1 | K99: 31 | L99: 133.338 | M99: 22.909675 | N99: 10.674474 | O99: -7.5058626 | P99: -0.79215288 | Q99: 5.2154227 | R99: -4.66683 | S99: 0 | T99: 10.430914 | U99: 25 | V99: 25 | W99: 551.65625 | X99: 0 | Y99: 0 | Z99: 0 | AA99: 0 | AB99: 0 | AC99: 551.65625 | AD99: 68.110519 | AE99: 0 | AF99: 4.8568198 | AG99: 63.253699 | AH99: 3.3799275 | AI99: 3.3799275 | AJ99: 0.56916667 | AK99: 1.2083333 | AL99: 0.41666667 | AM99: 0 | AN99: 677.52895 | AO99: 230.5463 | AP99: 63.253699 | AQ99: 230.5463 | AR99: continued_draw_or_waiver_after_warning | AT99: 202.9931 | AU99: 3.3376944 | AV99: 4.2988059 | AW99: 0 | AX99: no | AY99: no | AZ99: BREACHED_ANALYTICAL_THRESHOLD | BA99: SRC-001;SRC-002;SRC-003 | BB99: P6M-MODERATE_UNMITIGATED-P-0023:P6M-MODERATE_UNMITIGATED-P-0023
... C112: Moderate unmitigated | D112: MODERATE_UNMITIGATED | E112: P036 | F112: quarterly | G112: 47788 | H112: 47879 | I112: FY2031 | J112: Q1 | K112: 92 | L112: 399.984 | M112: 22.909675 | N112: 32.021021 | O112: -22.515899 | P112: -2.3762804 | Q112: 0.0015251072 | R112: -13.99944 | S112: 0 | T112: 15.646826 | U112: 25 | V112: 25 | W112: 408.78125 | X112: 11.90625 | Y112: 11.90625 | Z112: 0 | AA112: 408.37522 | AB112: 0 | AC112: 396.875 | AD112: 2.1010885 | AE112: 11.065963 | AF112: 1.6668356 | AG112: 11.500216 | AH112: 6.7282028 | AI112: 6.7282028 | AJ112: 1.5365 | AK112: 3.625 | AL112: 1.25 | AM112: 0 | AN112: 470.99422 | AO112: 0 | AP112: 11.500216 | AQ112: 0 | AR112: continued_draw_or_waiver_after_warning | AT112: 222.25063 | AU112: 2.119203 | AV112: 7.7306312 | AW112: 408.37522 | AX112: yes | AY112: no | AZ112: MATURITY_SHORTFALL | BA112: SRC-001;SRC-002;SRC-003 | BB112: P6M-MODERATE_UNMITIGATED-P-0058:P6M-MODERATE_UNMITIGATED-P-0060
C113: Moderate mitigated | D113: MODERATE_MITIGATED | E113: P001 | F113: monthly | G113: 46054 | H113: 46081 | I113: FY2026 | J113: Q2 | K113: 28 | L113: 84.611271 | M113: 28.869322 | N113: 10.123926 | O113: -8.4900849 | P113: -1.3402471 | Q113: -14.685874 | R113: -2.9613945 | S113: -0.44 | T113: -9.3035892 | U113: 25 | V113: 25 | W113: 635 | X113: 0 | Y113: 0 | Z113: 0 | AA113: 0 | AB113: 0 | AC113: 635 | AD113: 29.897719 | AE113: 15.868956 | AF113: 0 | AG113: 45.766674 | AH113: 4.2444498 | AI113: 4.2444498 | AJ113: 0.69591667 | AK113: 1.2083333 | AL113: 0.41666667 | AM113: 0 | AN113: 743.38567 | AO113: 248.03333 | AP113: 45.766674 | AQ113: 248.03333 | AR113: available_before_analytical_shutoff | AW113: 0 | AX113: no | AY113: no | AZ113: PASS | BA113: SRC-001;SRC-002;SRC-003 | BB113: P6M-MODERATE_MITIGATED-P-0001:P6M-MODERATE_MITIGATED-P-0001
C114: Moderate mitigated | D114: MODERATE_MITIGATED | E114: P002 | F114: monthly | G114: 46082 | H114: 46112 | I114: FY2026 | J114: Q2 | K114: 31 | L114: 126.91691 | M114: 28.869322 | N114: 15.185889 | O114: -8.4900849 | P114: -2.0103707 | Q114: -22.028811 | R114: -4.4420917 | S114: -0.66 | T114: -13.955384 | U114: 25 | V114: 25 | W114: 635 | X114: 0 | Y114: 0 | Z114: 0 | AA114: 0 | AB114: 0 | AC114: 635 | AD114: 45.766674 | AE114: 20.635893 | AF114: 0 | AG114: 66.402567 | AH114: 4.3595921 | AI114: 4.3595921 | AJ114: 0.69591667 | AK114: 1.2083333 | AL114: 0.41666667 | AM114: 0 | AN114: 764.02157 | AO114: 227.39743 | AP114: 66.402567 | AQ114: 227.39743 | AR114: available_before_analytical_shutoff | AW114: 0 | AX114: no | AY114: no | AZ114: PASS | BA114: SRC-001;SRC-002;SRC-003 | BB114: P6M-MODERATE_MITIGATED-P-0002:P6M-MODERATE_MITIGATED-P-0002
C115: Moderate mitigated | D115: MODERATE_MITIGATED | E115: P003 | F115: monthly | G115: 46113 | H115: 46142 | I115: FY2026 | J115: Q2 | K115: 30 | L115: 211.52818 | M115: 28.869322 | N115: 25.309815 | O115: -8.4900849 | P115: -3.3506178 | Q115: -36.714684 | R115: -7.4034862 | S115: -1.1 | T115: -23.258973 | U115: 25 | V115: 25 | W115: 635 | X115: 11.90625 | Y115: 11.90625 | Z115: 0 | AA115: 0 | AB115: 0 | AC115: 623.09375 | AD115: 66.402567 | AE115: 42.00576 | AF115: 0 | AG115: 108.40833 | AH115: 4.5196201 | AI115: 4.5196201 | AJ115: 0.69591667 | AK115: 1.2083333 | AL115: 0.41666667 | AM115: 0 | AN115: 794.12108 | AO115: 185.39167 | AP115: 108.40833 | AQ115: 185.39167 | AR115: available_before_analytical_shutoff | AW115: 0 | AX115: no | AY115: no | AZ115: PASS | BA115: SRC-001;SRC-002;SRC-003 | BB115: P6M-MODERATE_MITIGATED-P-0003:P6M-MODERATE_MITIGATED-P-0003
C116: Moderate mitigated | D116: MODERATE_MITIGATED | E116: P004 | F116: monthly | G116: 46143 | H116: 46173 | I116: FY2026 | J116: Q3 | K116: 31 | L116: 92.613736 | M116: 27.690174 | N116: 9.9893857 | O116: -9.2930702 | P116: -1.1939933 | Q116: 0.95451854 | R116: -3.2414807 | S116: -0.3 | T116: 6.2084302 | U116: 25 | V116: 25 | W116: 623.09375 | X116: 0 | Y116: 0 | Z116: 0 | AA116: 0 | AB116: 0 | AC116: 623.09375 | AD116: 108.40833 | AE116: 0.31136087 | AF116: 0 | AG116: 108.71969 | AH116: 4.615541 | AI116: 4.615541 | AJ116: 0.69591667 | AK116: 1.2083333 | AL116: 0 | AM116: 0 | AN116: 794.43244 | AO116: 185.08031 | AP116: 108.71969 | AQ116: 185.08031 | AR116: available_before_analytical_shutoff | AW116: 0 | AX116: no | AY116: no | AZ116: PASS | BA116: SRC-001;SRC-002;SRC-003 | BB116: P6M-MODERATE_MITIGATED-P-0004:P6M-MODERATE_MITIGATED-P-0004
C117: Moderate mitigated | D117: MODERATE_MITIGATED | E117: P005 | F117: monthly | G117: 46174 | H117: 46203 | I117: FY2026 | J117: Q3 | K117: 30 | L117: 138.9206 | M117: 27.690174 | N117: 14.984079 | O117: -9.2930702 | P117: -1.79099 | Q117: 1.4317778 | R117: -4.8622211 | S117: -0.45 | T117: 9.3126452 | U117: 25 | V117: 25 | W117: 623.09375 | X117: 0 | Y117: 0 | Z117: 0 | AA117: 0 | AB117: 0 | AC117: 623.09375 | AD117: 108.71969 | AE117: 0 | AF117: 2.800706 | AG117: 105.91898 | AH117: 4.6076892 | AI117: 4.6076892 | AJ117: 0.69591667 | AK117: 1.2083333 | AL117: 0 | AM117: 0 | AN117: 791.63173 | AO117: 187.88102 | AP117: 105.91898 | AQ117: 187.88102 | AR117: available_before_analytical_shutoff | AW117: 0 | AX117: no | AY117: no | AZ117: PASS | BA117: SRC-001;SRC-002;SRC-003 | BB117: P6M-MODERATE_MITIGATED-P-0005:P6M-MODERATE_MITIGATED-P-0005
C118: Moderate mitigated | D118: MODERATE_MITIGATED | E118: P006 | F118: monthly | G118: 46204 | H118: 46234 | I118: FY2026 | J118: Q3 | K118: 31 | L118: 231.53434 | M118: 27.690174 | N118: 24.973464 | O118: -9.2930702 | P118: -2.9849833 | Q118: 2.3862964 | R118: -8.1037019 | S118: -0.75 | T118: 15.521075 | U118: 25 | V118: 25 | W118: 623.09375 | X118: 11.90625 | Y118: 11.90625 | Z118: 0 | AA118: 0 | AB118: 0 | AC118: 611.1875 | AD118: 105.91898 | AE118: 2.8597458 | AF118: 0 | AG118: 108.77873 | AH118: 4.5703211 | AI118: 4.5703211 | AJ118: 0.69591667 | AK118: 1.2083333 | AL118: 0 | AM118: 0 | AN118: 782.58523 | AO118: 185.02127 | AP118: 108.77873 | AQ118: 185.02127 | AR118: available_before_analytical_shutoff | AW118: 0 | AX118: no | AY118: no | AZ118: PASS | BA118: SRC-001;SRC-002;SRC-003 | BB118: P6M-MODERATE_MITIGATED-P-0006:P6M-MODERATE_MITIGATED-P-0006
C119: Moderate mitigated | D119: MODERATE_MITIGATED | E119: P007 | F119: monthly | G119: 46235 | H119: 46265 | I119: FY2026 | J119: Q4 | K119: 31 | L119: 91.598912 | M119: 27.915917 | N119: 10.086705 | O119: -9.1912406 | P119: -1.2326048 | Q119: 0.94214784 | R119: -3.2059619 | S119: 0 | T119: 6.5902861 | U119: 25 | V119: 25 | W119: 611.1875 | X119: 0 | Y119: 0 | Z119: 0 | AA119: 0 | AB119: 0 | AC119: 611.1875 | AD119: 108.77873 | AE119: 0 | AF119: 0.1447056 | AG119: 108.63402 | AH119: 4.5413305 | AI119: 4.5413305 | AJ119: 0.69591667 | AK119: 1.2083333 | AL119: 0 | AM119: 0 | AN119: 782.44052 | AO119: 185.16598 | AP119: 108.63402 | AQ119: 185.16598 | AR119: available_before_analytical_shutoff | AW119: 0 | AX119: no | AY119: no | AZ119: PASS | BA119: SRC-001;SRC-002;SRC-003 | BB119: P6M-MODERATE_MITIGATED-P-0007:P6M-MODERATE_MITIGATED-P-0007
C120: Moderate mitigated | D120: MODERATE_MITIGATED | E120: P008 | F120: monthly | G120: 46266 | H120: 46295 | I120: FY2026 | J120: Q4 | K120: 30 | L120: 137.39837 | M120: 27.915917 | N120: 15.130057 | O120: -9.1912406 | P120: -1.8489071 | Q120: 1.4132218 | R120: -4.8089429 | S120: 0 | T120: 9.8854292 | U120: 25 | V120: 25 | W120: 611.1875 | X120: 0 | Y120: 0 | Z120: 0 | AA120: 0 | AB120: 0 | AC120: 611.1875 | AD120: 108.63402 | AE120: 0 | AF120: 3.4511907 | AG120: 105.18283 | AH120: 4.5299885 | AI120: 4.5299885 | AJ120: 0.69591667 | AK120: 1.2083333 | AL120: 0 | AM120: 0 | AN120: 778.98933 | AO120: 188.61717 | AP120: 105.18283 | AQ120: 188.61717 | AR120: available_before_analytical_shutoff | AW120: 0 | AX120: no | AY120: no | AZ120: PASS | BA120: SRC-001;SRC-002;SRC-003 | BB120: P6M-MODERATE_MITIGATED-P-0008:P6M-MODERATE_MITIGATED-P-0008
C121: Moderate mitigated | D121: MODERATE_MITIGATED | E121: P009 | F121: monthly | G121: 46296 | H121: 46326 | I121: FY2026 | J121: Q4 | K121: 31 | L121: 228.99728 | M121: 27.915917 | N121: 25.216762 | O121: -9.1912406 | P121: -3.0815119 | Q121: 2.3553696 | R121: -8.0149048 | S121: 0 | T121: 16.475715 | U121: 25 | V121: 25 | W121: 611.1875 | X121: 11.90625 | Y121: 11.90625 | Z121: 0 | AA121: 0 | AB121: 0 | AC121: 599.28125 | AD121: 105.18283 | AE121: 1.8220804 | AF121: 0 | AG121: 107.00491 | AH121: 4.4872957 | AI121: 4.4872957 | AJ121: 0.69591667 | AK121: 1.2083333 | AL121: 0 | AM121: 0 | AN121: 768.90516 | AO121: 186.79509 | AP121: 107.00491 | AQ121: 186.79509 | AR121: continued_draw_or_waiver_after_warning | AT121: 183.02511 | AU121: 4.2010912 | AW121: 0 | AX121: no | AY121: no | AZ121: BREACHED_ANALYTICAL_THRESHOLD | BA121: SRC-001;SRC-002;SRC-003 | BB121: P6M-MODERATE_MITIGATED-P-0009:P6M-MODERATE_MITIGATED-P-0009
C122: Moderate mitigated | D122: MODERATE_MITIGATED | E122: P010 | F122: monthly | G122: 46327 | H122: 46356 | I122: FY2027 | J122: Q1 | K122: 30 | L122: 74.804488 | M122: 22.909675 | N122: 4.49244 | O122: -7.5060503 | P122: -0.070386437 | Q122: 0.82176262 | R122: -2.6181571 | S122: 0 | T122: 2.6256591 | U122: 25 | V122: 25 | W122: 599.28125 | X122: 0 | Y122: 0 | Z122: 0 | AA122: 0 | AB122: 0 | AC122: 599.28125 | AD122: 107.00491 | AE122: 3.7191436 | AF122: 0 | AG122: 110.72406 | AH122: 4.4672193 | AI122: 4.4672193 | AJ122: 0.66925 | AK122: 1.2083333 | AL122: 0 | AM122: 0 | AN122: 772.62431 | AO122: 183.07594 | AP122: 110.72406 | AQ122: 183.07594 | AR122: continued_draw_or_waiver_after_warning | AT122: 176.84254 | AU122: 4.3689958 | AW122: 0 | AX122: no | AY122: no | AZ122: BREACHED_ANALYTICAL_THRESHOLD | BA122: SRC-001;SRC-002;SRC-003 | BB122: P6M-MODERATE_MITIGATED-P-0010:P6M-MODERATE_MITIGATED-P-0010
C123: Moderate mitigated | D123: MODERATE_MITIGATED | E123: P011 | F123: monthly | G123: 46357 | H123: 46387 | I123: FY2027 | J123: Q1 | K123: 31 | L123: 112.20673 | M123: 22.909675 | N123: 6.7386599 | O123: -7.5060503 | P123: -0.10557965 | Q123: 1.2326439 | R123: -3.9272356 | S123: 0 | T123: 3.9384886 | U123: 25 | V123: 25 | W123: 599.28125 | X123: 0 | Y123: 0 | Z123: 0 | AA123: 0 | AB123: 0 | AC123: 599.28125 | AD123: 110.72406 | AE123: 2.4256959 | AF123: 0 | AG123: 113.14975 | AH123: 4.4866012 | AI123: 4.4866012 | AJ123: 0.66925 | AK123: 1.2083333 | AL123: 0 | AM123: 0 | AN123: 775.05 | AO123: 180.65025 | AP123: 113.14975 | AQ123: 180.65025 | AR123: continued_draw_or_waiver_after_warning | AT123: 172.90619 | AU123: 4.4824884 | AW123: 0 | AX123: no | AY123: no | AZ123: BREACHED_ANALYTICAL_THRESHOLD | BA123: SRC-001;SRC-002;SRC-003 | BB123: P6M-MODERATE_MITIGATED-P-0011:P6M-MODERATE_MITIGATED-P-0011
C124: Moderate mitigated | D124: MODERATE_MITIGATED | E124: P012 | F124: monthly | G124: 46388 | H124: 46418 | I124: FY2027 | J124: Q1 | K124: 31 | L124: 187.01122 | M124: 22.909675 | N124: 11.2311 | O124: -7.5060503 | P124: -0.17596609 | Q124: 2.0544065 | R124: -6.5453927 | S124: 0 | T124: 6.5641477 | U124: 25 | V124: 25 | W124: 599.28125 | X124: 11.90625 | Y124: 11.90625 | Z124: 0 | AA124: 0 | AB124: 0 | AC124: 587.375 | AD124: 113.14975 | AE124: 11.713329 | AF124: 0 | AG124: 124.86308 | AH124: 4.4936437 | AI124: 4.4936437 | AJ124: 0.66925 | AK124: 1.2083333 | AL124: 0 | AM124: 0 | AN124: 774.85708 | AO124: 168.93692 | AP124: 124.86308 | AQ124: 168.93692 | AR124: continued_draw_or_waiver_after_warning | AT124: 173.46228 | AU124: 4.4670061 | AV124: 3.2168341 | AW124: 0 | AX124: no | AY124: no | AZ124: BREACHED_ANALYTICAL_THRESHOLD | BA124: SRC-001;SRC-002;SRC-003 | BB124: P6M-MODERATE_MITIGATED-P-0012:P6M-MODERATE_MITIGATED-P-0012
C125: Moderate mitigated | D125: MODERATE_MITIGATED | E125: P013 | F125: monthly | G125: 46419 | H125: 46446 | I125: FY2027 | J125: Q2 | K125: 28 | L125: 86.079635 | M125: 28.869322 | N125: 10.730017 | O125: -8.4898727 | P125: -1.4711056 | Q125: 3.4826496 | R125: -3.0127872 | S125: 0 | T125: 9.7287742 | U125: 25 | V125: 25 | W125: 587.375 | X125: 0 | Y125: 0 | Z125: 0 | AA125: 0 | AB125: 0 | AC125: 587.375 | AD125: 124.86308 | AE125: 0 | AF125: 3.5172662 | AG125: 121.34581 | AH125: 4.3339246 | AI125: 4.3339246 | AJ125: 0.66925 | AK125: 1.2083333 | AL125: 0 | AM125: 0 | AN125: 771.33981 | AO125: 172.45419 | AP125: 121.34581 | AQ125: 172.45419 | AR125: continued_draw_or_waiver_after_warning | AT125: 174.06837 | AU125: 4.4312461 | AV125: 3.2227265 | AW125: 0 | AX125: no | AY125: no | AZ125: BREACHED_ANALYTICAL_THRESHOLD | BA125: SRC-001;SRC-002;SRC-003 | BB125: P6M-MODERATE_MITIGATED-P-0013:P6M-MODERATE_MITIGATED-P-0013
C126: Moderate mitigated | D126: MODERATE_MITIGATED | E126: P014 | F126: monthly | G126: 46447 | H126: 46477 | I126: FY2027 | J126: Q2 | K126: 31 | L126: 129.11945 | M126: 28.869322 | N126: 16.095026 | O126: -8.4898727 | P126: -2.2066585 | Q126: 5.2239745 | R126: -4.5191809 | S126: 0 | T126: 14.593161 | U126: 25 | V126: 25 | W126: 587.375 | X126: 0 | Y126: 0 | Z126: 0 | AA126: 0 | AB126: 0 | AC126: 587.375 | AD126: 121.34581 | AE126: 0 | AF126: 8.418056 | AG126: 112.92776 | AH126: 4.2975219 | AI126: 4.2975219 | AJ126: 0.66925 | AK126: 1.2083333 | AL126: 0 | AM126: 0 | AN126: 762.92176 | AO126: 180.87224 | AP126: 112.92776 | AQ126: 180.87224 | AR126: continued_draw_or_waiver_after_warning | AT126: 174.97751 | AU126: 4.3601132 | AV126: 3.2432855 | AW126: 0 | AX126: no | AY126: no | AZ126: BREACHED_ANALYTICAL_THRESHOLD | BA126: SRC-001;SRC-002;SRC-003 | BB126: P6M-MODERATE_MITIGATED-P-0014:P6M-MODERATE_MITIGATED-P-0014
C127: Moderate mitigated | D127: MODERATE_MITIGATED | E127: P015 | F127: monthly | G127: 46478 | H127: 46507 | I127: FY2027 | J127: Q2 | K127: 30 | L127: 215.19909 | M127: 28.869322 | N127: 26.825044 | O127: -8.4898727 | P127: -3.6777641 | Q127: 8.7066241 | R127: -7.5319681 | S127: 0 | T127: 24.321935 | U127: 25 | V127: 25 | W127: 587.375 | X127: 11.90625 | Y127: 11.90625 | Z127: 0 | AA127: 0 | AB127: 0 | AC127: 575.46875 | AD127: 112.92776 | AE127: 0 | AF127: 6.321851 | AG127: 106.60591 | AH127: 4.2162511 | AI127: 4.2162511 | AJ127: 0.66925 | AK127: 1.2083333 | AL127: 0 | AM127: 0 | AN127: 744.69366 | AO127: 187.19409 | AP127: 106.60591 | AQ127: 187.19409 | AR127: continued_draw_or_waiver_after_warning | AT127: 176.49274 | AU127: 4.2194011 | AV127: 3.2898701 | AW127: 0 | AX127: no | AY127: no | AZ127: BREACHED_ANALYTICAL_THRESHOLD | BA127: SRC-001;SRC-002;SRC-003 | BB127: P6M-MODERATE_MITIGATED-P-0015:P6M-MODERATE_MITIGATED-P-0015
C128: Moderate mitigated | D128: MODERATE_MITIGATED | E128: P016 | F128: monthly | G128: 46508 | H128: 46538 | I128: FY2027 | J128: Q3 | K128: 31 | L128: 95.830534 | M128: 27.690174 | N128: 11.294657 | O128: -9.2928379 | P128: -1.4750412 | Q128: 3.2672336 | R128: -3.3540687 | S128: 0 | T128: 9.7327809 | U128: 25 | V128: 25 | W128: 575.46875 | X128: 0 | Y128: 0 | Z128: 0 | AA128: 0 | AB128: 0 | AC128: 575.46875 | AD128: 106.60591 | AE128: 0 | AF128: 3.8479766 | AG128: 102.75793 | AH128: 4.007221 | AI128: 4.007221 | AJ128: 0.66925 | AK128: 1.2083333 | AL128: 0 | AM128: 0 | AN128: 740.84568 | AO128: 191.04207 | AP128: 102.75793 | AQ128: 191.04207 | AR128: continued_draw_or_waiver_after_warning | AT128: 177.79801 | AU128: 4.1667827 | AV128: 3.3522122 | AW128: 0 | AX128: no | AY128: no | AZ128: BREACHED_ANALYTICAL_THRESHOLD | BA128: SRC-001;SRC-002;SRC-003 | BB128: P6M-MODERATE_MITIGATED-P-0016:P6M-MODERATE_MITIGATED-P-0016
C129: Moderate mitigated | D129: MODERATE_MITIGATED | E129: P017 | F129: monthly | G129: 46539 | H129: 46568 | I129: FY2027 | J129: Q3 | K129: 30 | L129: 143.7458 | M129: 27.690174 | N129: 16.941986 | O129: -9.2928379 | P129: -2.2125618 | Q129: 4.9008504 | R129: -5.031103 | S129: 0 | T129: 14.599171 | U129: 25 | V129: 25 | W129: 575.46875 | X129: 0 | Y129: 0 | Z129: 0 | AA129: 0 | AB129: 0 | AC129: 575.46875 | AD129: 102.75793 | AE129: 0 | AF129: 8.7514829 | AG129: 94.006448 | AH129: 3.9701051 | AI129: 3.9701051 | AJ129: 0.66925 | AK129: 1.2083333 | AL129: 0 | AM129: 0 | AN129: 732.0942 | AO129: 199.79355 | AP129: 94.006448 | AQ129: 199.79355 | AR129: continued_draw_or_waiver_after_warning | AT129: 179.75592 | AU129: 4.0727126 | AV129: 3.4303633 | AW129: 0 | AX129: no | AY129: no | AZ129: BREACHED_ANALYTICAL_THRESHOLD | BA129: SRC-001;SRC-002;SRC-003 | BB129: P6M-MODERATE_MITIGATED-P-0017:P6M-MODERATE_MITIGATED-P-0017
C130: Moderate mitigated | D130: MODERATE_MITIGATED | E130: P018 | F130: monthly | G130: 46569 | H130: 46599 | I130: FY2027 | J130: Q3 | K130: 31 | L130: 239.57633 | M130: 27.690174 | N130: 28.236643 | O130: -9.2928379 | P130: -3.687603 | Q130: 8.168084 | R130: -8.3851717 | S130: 0 | T130: 24.331952 | U130: 25 | V130: 25 | W130: 575.46875 | X130: 11.90625 | Y130: 11.90625 | Z130: 0 | AA130: 0 | AB130: 0 | AC130: 563.5625 | AD130: 94.006448 | AE130: 0 | AF130: 6.6584829 | AG130: 87.347965 | AH130: 3.8896361 | AI130: 3.8896361 | AJ130: 0.66925 | AK130: 1.2083333 | AL130: 0 | AM130: 0 | AN130: 713.52946 | AO130: 206.45204 | AP130: 87.347965 | AQ130: 206.45204 | AR130: continued_draw_or_waiver_after_warning | AT130: 183.0191 | AU130: 3.8986613 | AV130: 3.5386018 | AW130: 0 | AX130: no | AY130: no | AZ130: BREACHED_ANALYTICAL_THRESHOLD | BA130: SRC-001;SRC-002;SRC-003 | BB130: P6M-MODERATE_MITIGATED-P-0018:P6M-MODERATE_MITIGATED-P-0018
C131: Moderate mitigated | D131: MODERATE_MITIGATED | E131: P019 | F131: monthly | G131: 46600 | H131: 46630 | I131: FY2027 | J131: Q4 | K131: 31 | L131: 96.372382 | M131: 27.915917 | N131: 12.057936 | O131: -9.1910108 | P131: -1.6582356 | Q131: 3.1248994 | R131: -3.3730334 | S131: 0 | T131: 10.151567 | U131: 25 | V131: 25 | W131: 563.5625 | X131: 0 | Y131: 0 | Z131: 0 | AA131: 0 | AB131: 0 | AC131: 563.5625 | AD131: 87.347965 | AE131: 0 | AF131: 4.5876791 | AG131: 82.760286 | AH131: 3.6863045 | AI131: 3.6863045 | AJ131: 0.66925 | AK131: 1.2083333 | AL131: 0 | AM131: 0 | AN131: 708.94179 | AO131: 211.03971 | AP131: 82.760286 | AQ131: 211.03971 | AR131: continued_draw_or_waiver_after_warning | AT131: 184.99033 | AU131: 3.8323181 | AV131: 3.6368375 | AW131: 0 | AX131: no | AY131: no | AZ131: BREACHED_ANALYTICAL_THRESHOLD | BA131: SRC-001;SRC-002;SRC-003 | BB131: P6M-MODERATE_MITIGATED-P-0019:P6M-MODERATE_MITIGATED-P-0019
C132: Moderate mitigated | D132: MODERATE_MITIGATED | E132: P020 | F132: monthly | G132: 46631 | H132: 46660 | I132: FY2027 | J132: Q4 | K132: 30 | L132: 144.55857 | M132: 27.915917 | N132: 18.086905 | O132: -9.1910108 | P132: -2.4873534 | Q132: 4.6873491 | R132: -5.05955 | S132: 0 | T132: 15.22735 | U132: 25 | V132: 25 | W132: 563.5625 | X132: 0 | Y132: 0 | Z132: 0 | AA132: 0 | AB132: 0 | AC132: 563.5625 | AD132: 82.760286 | AE132: 0 | AF132: 9.704075 | AG132: 73.056211 | AH132: 3.6456921 | AI132: 3.6456921 | AJ132: 0.66925 | AK132: 1.2083333 | AL132: 0 | AM132: 0 | AN132: 699.23771 | AO132: 220.74379 | AP132: 73.056211 | AQ132: 220.74379 | AR132: continued_draw_or_waiver_after_warning | AT132: 187.94718 | AU132: 3.7203949 | AV132: 3.7603411 | AW132: 0 | AX132: no | AY132: no | AZ132: BREACHED_ANALYTICAL_THRESHOLD | BA132: SRC-001;SRC-002;SRC-003 | BB132: P6M-MODERATE_MITIGATED-P-0020:P6M-MODERATE_MITIGATED-P-0020
...

Sheet Scenario Comparison
C2: Live scenario and captured comparisons
C3: Case selected: | D3: =Assumptions!$D$4 -> Base
C4: View | D4: Scenario ID | E4: Status | F4: FY2026 post-close EBITDA | G4: EBITDA margin | H4: Modeled operating cash | I4: CFADS | J4: Cash interest | K4: Scheduled principal | L4: ECF sweep | M4: Peak revolver | N4: Opening liquidity | O4: Subsequent minimum | P4: All-in minimum | Q4: Maximum leverage | R4: Minimum coverage | S4: First warning | T4: First breach | U4: First draw shutoff | V4: First payment failure | W4: Common-horizon ending debt | X4: Maturity gap | Y4: Unpaid obligations
C5: ="LIVE" -> LIVE | D5: =Assumptions!D5 -> BASE | E5: ="Current selection" -> Current selection | F5: =SUM(Forecast!D14:F14) -> 190.24864 | G5: =SUM(Forecast!D14:F14)/SUM(Forecast!D10:F10) -> 0.13234126 | H5: =SUM(Forecast!D24:W24) -> 794.48407 | I5: =SUM(Forecast!D22:W22) -> 640.30851 | J5: =SUM('Debt Schedule'!T12:T47) -> 167.38575 | K5: =SUM('Debt Schedule'!K12:K47) -> 238.125 | L5: =SUM('Debt Schedule'!L12:L47) -> 57.292168 | M5: =MAX('Debt Schedule'!R12:R47) -> 23.458655 | N5: =Liquidity!D6 -> 263.90228 | O5: =Liquidity!D7 -> 270.34135 | P5: =Liquidity!D9 -> 263.90228 | Q5: =MAX(Covenants!H8:H27) -> 3.2284717 | R5: =MIN(Covenants!N8:N27) -> 5.3859581 | S5: =INDEX(Assumptions!$BF$41:$BF$49,MATCH(Assumptions!$D$4,Assumptions!$BD$41:$BD$49,0)) -> N/D | T5: =INDEX(Assumptions!$BG$41:$BG$49,MATCH(Assumptions!$D$4,Assumptions!$BD$41:$BD$49,0)) -> N/D | U5: =INDEX(Assumptions!$BH$41:$BH$49,MATCH(Assumptions!$D$4,Assumptions!$BD$41:$BD$49,0)) -> N/D | V5: =INDEX(Assumptions!$BI$41:$BI$49,MATCH(Assumptions!$D$4,Assumptions!$BD$41:$BD$49,0)) -> N/D | W5: =SUMIFS('Debt Schedule'!Z12:Z47,'Debt Schedule'!D12:D47,DATE(2029,7,31)) -> 514.75371 | X5: ='Debt Schedule'!X47 -> 324.77971 | Y5: =SUM('Debt Schedule'!AC12:AC47) -> 0
C6: Current selected-case results
C8: Captured comparisons are recalculated snapshots, not parallel live engines. Change in any modeled input makes the stale flag visible until the capture workflow is rerun.
C11: Scenario | D11: Scenario ID | E11: View | F11: FY2026 post-close EBITDA | G11: EBITDA margin | H11: Modeled operating cash | I11: CFADS | J11: Cash interest | K11: Scheduled principal | L11: ECF sweep | M11: Peak revolver | N11: Opening liquidity | O11: Subsequent minimum | P11: All-in minimum | Q11: Maximum leverage | R11: Minimum coverage | S11: First warning | T11: First breach | U11: First draw shutoff | V11: First payment failure | W11: Common-horizon ending debt | X11: Maturity gap | Y11: Unpaid obligations | Z11: Captured at | AA11: Input version | AB11: Source hash | AC11: Captured signature | AD11: Current signature | AE11: Stale status
C12: Base | D12: BASE | E12: =IF(C12=Assumptions!$D$4,"LIVE SELECTED","CAPTURED") -> LIVE SELECTED | F12: 190.24864 | G12: 0.13234126 | H12: 794.48407 | I12: 640.30851 | J12: 167.38575 | K12: 238.125 | L12: 57.292168 | M12: 23.458655 | N12: 263.90228 | O12: 270.34135 | P12: 263.90228 | Q12: 3.2284717 | R12: 5.3859581 | S12: N/D | T12: N/D | U12: N/D | V12: N/D | W12: 514.75371 | X12: 324.77971 | Y12: 0 | Z12: 2026-09-11T17:39:57Z | AA12: 58e1b83a644021b785162d851e1539dd65dff9f5 | AB12: 126ef393472d5f74abd447b237b1319643c1effb36a37f052496b114af1a6fe1 | AC12: 1712129.8 | AD12: =Assumptions!$D$7 -> 1712129.8 | AE12: =IF(ABS(AC12-AD12)<=0.000001,"CURRENT","STALE") -> CURRENT
C13: Moderate unmitigated | D13: MODERATE_UNMITIGATED | E13: =IF(C13=Assumptions!$D$4,"LIVE SELECTED","CAPTURED") -> CAPTURED | F13: 151.00008 | G13: 0.11234126 | H13: 705.09412 | I13: 589.29204 | J13: 199.96478 | K13: 238.125 | L13: 0 | M13: 128.72159 | N13: 263.90228 | O13: 165.07841 | P13: 165.07841 | Q13: 4.4892502 | R13: 3.2103738 | S13: 2026-10-31 | T13: 2026-10-31 | U13: N/D | V13: N/D | W13: 569.06713 | X13: 408.37522 | Y13: 0 | Z13: 2026-09-11T17:39:57Z | AA13: 58e1b83a644021b785162d851e1539dd65dff9f5 | AB13: 126ef393472d5f74abd447b237b1319643c1effb36a37f052496b114af1a6fe1 | AC13: 1712129.8 | AD13: =Assumptions!$D$7 -> 1712129.8 | AE13: =IF(ABS(AC13-AD13)<=0.000001,"CURRENT","STALE") -> CURRENT
C14: Moderate mitigated | D14: MODERATE_MITIGATED | E14: =IF(C14=Assumptions!$D$4,"LIVE SELECTED","CAPTURED") -> CAPTURED | F14: 151.00008 | G14: 0.11234126 | H14: 708.58676 | I14: 589.29204 | J14: 196.47214 | K14: 238.125 | L14: 11.825378 | M14: 124.86308 | N14: 263.90228 | O14: 168.93692 | P14: 168.93692 | Q14: 4.4670061 | R14: 3.2168341 | S14: 2026-10-31 | T14: 2026-10-31 | U14: N/D | V14: N/D | W14: 550.9112 | X14: 381.13258 | Y14: 0 | Z14: 2026-09-11T17:39:57Z | AA14: 58e1b83a644021b785162d851e1539dd65dff9f5 | AB14: 126ef393472d5f74abd447b237b1319643c1effb36a37f052496b114af1a6fe1 | AC14: 1712129.8 | AD14: =Assumptions!$D$7 -> 1712129.8 | AE14: =IF(ABS(AC14-AD14)<=0.000001,"CURRENT","STALE") -> CURRENT
C15: Severe unmitigated | D15: SEVERE_UNMITIGATED | E15: =IF(C15=Assumptions!$D$4,"LIVE SELECTED","CAPTURED") -> CAPTURED | F15: 115.88908 | G15: 0.094841257 | H15: 483.56215 | I15: 467.10058 | J15: 280.89648 | K15: 226.21875 | L15: 0 | M15: 293.8 | N15: 263.90228 | O15: 0 | P15: 0 | Q15: 7.0574015 | R15: 1.7819351 | S15: 2026-04-30 | T15: 2026-10-31 | U15: N/D | V15: 2027-12-31 | W15: 741.46447 | X15: 604.25801 | Y15: 9.8304704 | Z15: 2026-09-11T17:39:57Z | AA15: 58e1b83a644021b785162d851e1539dd65dff9f5 | AB15: 126ef393472d5f74abd447b237b1319643c1effb36a37f052496b114af1a6fe1 | AC15: 1712129.8 | AD15: =Assumptions!$D$7 -> 1712129.8 | AE15: =IF(ABS(AC15-AD15)<=0.000001,"CURRENT","STALE") -> CURRENT
C16: Severe mitigated | D16: SEVERE_MITIGATED | E16: =IF(C16=Assumptions!$D$4,"LIVE SELECTED","CAPTURED") -> CAPTURED | F16: 115.88908 | G16: 0.094841257 | H16: 480.37732 | I16: 467.10058 | J16: 284.0813 | K16: 234.53779 | L16: 0 | M16: 293.8 | N16: 263.90228 | O16: 0 | P16: 0 | Q16: 6.9528556 | R16: 1.800808 | S16: 2026-04-30 | T16: 2026-10-31 | U16: N/D | V16: 2028-01-31 | W16: 714.07259 | X16: 554.71819 | Y16: 3.6418421 | Z16: 2026-09-11T17:39:57Z | AA16: 58e1b83a644021b785162d851e1539dd65dff9f5 | AB16: 126ef393472d5f74abd447b237b1319643c1effb36a37f052496b114af1a6fe1 | AC16: 1712129.8 | AD16: =Assumptions!$D$7 -> 1712129.8 | AE16: =IF(ABS(AC16-AD16)<=0.000001,"CURRENT","STALE") -> CURRENT
C17: Moderate Phase 6 analytical shutoff | D17: MODERATE_NO_WAIVER | E17: =IF(C17=Assumptions!$D$4,"LIVE SELECTED","CAPTURED") -> CAPTURED | F17: 151.00008 | G17: 0.11234126 | H17: 706.25135 | I17: 589.29204 | J17: 198.80756 | K17: 238.125 | L17: 0 | M17: 110.3219 | N17: 263.90228 | O17: 183.4781 | P17: 183.4781 | Q17: 4.3787434 | R17: 3.2181715 | S17: 2026-10-31 | T17: 2026-10-31 | U17: 2026-11-30 | V17: N/D | W17: 563.79487 | X17: 396.875 | Y17: 0 | Z17: 2026-09-11T17:39:57Z | AA17: 58e1b83a644021b785162d851e1539dd65dff9f5 | AB17: 126ef393472d5f74abd447b237b1319643c1effb36a37f052496b114af1a6fe1 | AC17: 1712129.8 | AD17: =Assumptions!$D$7 -> 1712129.8 | AE17: =IF(ABS(AC17-AD17)<=0.000001,"CURRENT","STALE") -> CURRENT
C18: Severe Phase 6 analytical shutoff | D18: SEVERE_NO_WAIVER | E18: =IF(C18=Assumptions!$D$4,"LIVE SELECTED","CAPTURED") -> CAPTURED | F18: 115.88908 | G18: 0.094841257 | H18: 513.52483 | I18: 467.10058 | J18: 250.9338 | K18: 210.96251 | L18: 0 | M18: 239.69285 | N18: 263.90228 | O18: 54.107146 | P18: 54.107146 | Q18: 6.8131589 | R18: 1.861981 | S18: 2026-04-30 | T18: 2026-10-31 | U18: 2026-11-30 | V18: 2027-02-28 | W18: 689.71319 | X18: 538.04051 | Y18: 41.947002 | Z18: 2026-09-11T17:39:57Z | AA18: 58e1b83a644021b785162d851e1539dd65dff9f5 | AB18: 126ef393472d5f74abd447b237b1319643c1effb36a37f052496b114af1a6fe1 | AC18: 1712129.8 | AD18: =Assumptions!$D$7 -> 1712129.8 | AE18: =IF(ABS(AC18-AD18)<=0.000001,"CURRENT","STALE") -> CURRENT
C19: Moderate Phase 7 covenant-linked no-waiver | D19: MODERATE_PHASE7_COVENANT_NO_WAIVER | E19: =IF(C19=Assumptions!$D$4,"LIVE SELECTED","CAPTURED") -> CAPTURED | F19: 151.00008 | G19: 0.11234126 | H19: 706.25135 | I19: 589.29204 | J19: 198.80756 | K19: 238.125 | L19: 0 | M19: 110.3219 | N19: 263.90228 | O19: 183.4781 | P19: 183.4781 | Q19: 4.3787434 | R19: 3.2181715 | S19: 2026-10-31 | T19: 2026-10-31 | U19: 2026-11-30 | V19: N/D | W19: 563.79487 | X19: 396.875 | Y19: 0 | Z19: 2026-09-11T17:39:57Z | AA19: 58e1b83a644021b785162d851e1539dd65dff9f5 | AB19: 126ef393472d5f74abd447b237b1319643c1effb36a37f052496b114af1a6fe1 | AC19: 1712129.8 | AD19: =Assumptions!$D$7 -> 1712129.8 | AE19: =IF(ABS(AC19-AD19)<=0.000001,"CURRENT","STALE") -> CURRENT
C20: Severe Phase 7 covenant-linked no-waiver | D20: SEVERE_PHASE7_COVENANT_NO_WAIVER | E20: =IF(C20=Assumptions!$D$4,"LIVE SELECTED","CAPTURED") -> CAPTURED | F20: 115.88908 | G20: 0.094841257 | H20: 513.52483 | I20: 467.10058 | J20: 250.9338 | K20: 210.96251 | L20: 0 | M20: 239.69285 | N20: 263.90228 | O20: 54.107146 | P20: 54.107146 | Q20: 6.8131589 | R20: 1.861981 | S20: 2026-04-30 | T20: 2026-10-31 | U20: 2026-11-30 | V20: 2027-02-28 | W20: 689.71319 | X20: 538.04051 | Y20: 41.947002 | Z20: 2026-09-11T17:39:57Z | AA20: 58e1b83a644021b785162d851e1539dd65dff9f5 | AB20: 126ef393472d5f74abd447b237b1319643c1effb36a37f052496b114af1a6fe1 | AC20: 1712129.8 | AD20: =Assumptions!$D$7 -> 1712129.8 | AE20: =IF(ABS(AC20-AD20)<=0.000001,"CURRENT","STALE") -> CURRENT

Sheet Historicals
C2: Quanex reported historical spread
C4: FY2021-FY2023 pre-Tyman; FY2024 includes approximately three months of Tyman; FY2025 is the first full post-Tyman year.
C6: Metric | D6: FY2021 | E6: FY2022 | F6: FY2023 | G6: FY2024 | H6: FY2025 | I6: Units | J6: Source IDs | K6: Status
C7: Income statement
C8: Revenue | D8: 1072.149 | E8: 1221.502 | F8: 1130.583 | G8: 1277.862 | H8: 1837.641 | I8: USD_millions | J8: SRC-014;SRC-001 | K8: supported
C9: Cost of sales before D&A | D9: -831.541 | E9: -953.004 | F9: -853.059 | G9: -972.238 | H9: -1338.413 | I9: USD_millions | J9: SRC-014;SRC-001 | K9: supported
C10: Gross profit | D10: 240.608 | E10: 268.498 | F10: 277.524 | G10: 305.624 | H10: 499.228 | I10: USD_millions | J10: SRC-014;SRC-001 | K10: supported
C11: SG&A | D11: -115.967 | E11: -117.108 | F11: -123.957 | G11: -190.47 | H11: -277.261 | I11: USD_millions | J11: SRC-014;SRC-001 | K11: supported
C12: D&A | D12: -42.732 | E12: -40.109 | F12: -42.866 | G12: -60.328 | H12: -103.444 | I12: USD_millions | J12: SRC-014;SRC-001 | K12: supported
C13: Goodwill impairment | D13: 0 | E13: 0 | F13: 0 | G13: 0 | H13: -302.284 | I13: USD_millions | J13: SRC-001 | K13: supported
C14: Operating income | D14: 81.87 | E14: 111.281 | F14: 110.701 | G14: 54.826 | H14: -193.952 | I14: USD_millions | J14: SRC-014;SRC-001 | K14: supported
C15: Interest expense | D15: -2.53 | E15: -2.559 | F15: -8.136 | G15: -20.593 | H15: -55.812 | I15: USD_millions | J15: SRC-014;SRC-001 | K15: supported
C16: Pretax income | D16: 80.094 | E16: 109.763 | F16: 97.046 | G16: 42.082 | H16: -242.593 | I16: USD_millions | J16: SRC-014;SRC-001 | K16: supported
C17: Income-tax expense | D17: -23.114 | E17: -21.427 | F17: -14.545 | G17: -9.023 | H17: -8.213 | I17: USD_millions | J17: SRC-014;SRC-001 | K17: supported
C18: Net income | D18: 56.98 | E18: 88.336 | F18: 82.501 | G18: 33.059 | H18: -250.806 | I18: USD_millions | J18: SRC-014;SRC-001 | K18: supported
C19: Cash flow
C20: Cash flow from operations | D20: 78.588 | E20: 97.965 | F20: 147.052 | G20: 88.812 | H20: 164.897 | I20: USD_millions | J20: SRC-014;SRC-001 | K20: supported
C21: Capital expenditures | D21: -24.008 | E21: -33.121 | F21: -37.39 | G21: -37.086 | H21: -62.642 | I21: USD_millions | J21: SRC-014;SRC-001 | K21: supported
C22: Free cash flow | D22: 54.58 | E22: 64.844 | F22: 109.662 | G22: 51.726 | H22: 102.255 | I22: USD_millions | J22: SRC-014;SRC-001 | K22: supported
C23: Acquisition cash flows | F23: -91.302 | G23: -398.554 | H23: 0 | I23: USD_millions | J23: SRC-001 | K23: supported
C24: Dividends paid | D24: -10.779 | E24: -10.598 | F24: -10.639 | G24: -11.972 | H24: -14.889 | I24: USD_millions | J24: SRC-014;SRC-001 | K24: supported
C25: Share repurchases | D25: -11.182 | E25: -6.6 | F25: -5.593 | G25: 0 | H25: -32.36 | I25: USD_millions | J25: SRC-014;SRC-001 | K25: supported
C26: Balance sheet
C27: Cash and cash equivalents | D27: 40.061 | E27: 55.093 | F27: 58.474 | G27: 97.744 | H27: 76.018 | I27: USD_millions | J27: SRC-014;SRC-012;SRC-001 | K27: supported
C28: Accounts receivable | D28: 108.309 | E28: 96.018 | F28: 97.311 | G28: 197.689 | H28: 205.384 | I28: USD_millions | J28: SRC-014;SRC-012;SRC-001 | K28: supported
C29: Inventory | D29: 92.529 | E29: 120.89 | F29: 97.959 | G29: 275.55 | H29: 254.122 | I29: USD_millions | J29: SRC-014;SRC-012;SRC-001 | K29: supported
C30: Accounts payable | D30: 86.765 | E30: 77.907 | F30: 74.371 | G30: 124.404 | H30: 131.307 | I30: USD_millions | J30: SRC-014;SRC-012;SRC-001 | K30: supported
C31: Current assets | D31: 249.047 | E31: 280.665 | F31: 273.6 | G31: 611.268 | H31: 573.775 | I31: USD_millions | J31: SRC-014;SRC-012;SRC-001 | K31: supported
C32: Current liabilities | D32: 158.001 | E32: 139.843 | F32: 134.663 | G32: 272.867 | H32: 281.545 | I32: USD_millions | J32: SRC-014;SRC-012;SRC-001 | K32: supported
C33: Total assets | D33: 717.323 | E33: 724.617 | F33: 831.143 | G33: 2319.788 | H33: 1968.233 | I33: USD_millions | J33: SRC-014;SRC-012;SRC-001 | K33: supported
C34: Total liabilities | D34: 297.541 | E34: 259.782 | F34: 285.589 | G34: 1309.042 | H34: 1242.054 | I34: USD_millions | J34: SRC-014;SRC-012;SRC-001 | K34: supported
C35: Shareholders' equity | D35: 419.782 | E35: 464.835 | F35: 545.554 | G35: 1010.746 | H35: 726.179 | I35: USD_millions | J35: SRC-014;SRC-012;SRC-001 | K35: supported
C36: Goodwill | D36: 149.205 | E36: 137.855 | F36: 182.956 | G36: 574.711 | H36: 271.346 | I36: USD_millions | J36: SRC-014;SRC-012;SRC-001 | K36: supported
C37: Intangible assets | D37: 82.41 | E37: 65.035 | F37: 74.115 | G37: 597.909 | H37: 549.137 | I37: USD_millions | J37: SRC-014;SRC-012;SRC-001 | K37: supported
C38: Debt
C39: Term-loan principal | D39: 0 | E39: 0 | F39: 0 | G39: 493.75 | H39: 468.75 | I39: USD_millions | J39: SRC-014;SRC-012;SRC-002 | K39: supported
C40: Revolver borrowings | D40: 38 | E40: 13 | F40: 15 | G40: 222.5 | H40: 172.5 | I40: USD_millions | J40: SRC-014;SRC-012;SRC-002 | K40: supported
C41: Total debt principal | D41: 53.537 | E41: 32.202 | F41: 70 | G41: 776.926 | H41: 703.869 | I41: USD_millions | J41: SRC-014;SRC-012;SRC-002 | K41: supported
C42: Total debt carrying amount | D42: 52.94 | E42: 30.674 | F42: 68.8 | G42: 762.943 | H42: 692.829 | I42: USD_millions | J42: SRC-014;SRC-012;SRC-001 | K42: supported
C43: Finance lease obligations | D43: 15.537 | E43: 19.202 | F43: 55 | G43: 60.676 | H43: 62.619 | I43: USD_millions | J43: SRC-014;SRC-012;SRC-002 | K43: supported
C45: Selected historical credit metrics
C46: Metric | D46: FY2021 | E46: FY2022 | F46: FY2023 | G46: FY2024 | H46: FY2025 | I46: Units | J46: Status | K46: Limitation
C47: gross margin | D47: 22.441657 | E47: 21.980971 | F47: 24.546982 | G47: 23.916824 | H47: 27.166786 | I47: percent | J47: calculated
C48: operating margin | D48: 7.6360655 | E48: 9.1101775 | F48: 9.791497 | G48: 4.2904476 | H48: -10.554401 | I48: percent | J48: calculated
C49: unadjusted ebitda margin | D49: 11.621706 | E49: 12.393758 | F49: 13.582992 | G49: 9.0114582 | H49: -4.9252275 | I49: percent | J49: calculated
C50: cash flow from operations | D50: 78.588 | E50: 97.965 | F50: 147.052 | G50: 88.812 | H50: 164.897 | I50: USD_millions | J50: reported
C51: free cash flow | D51: 54.58 | E51: 64.844 | F51: 109.662 | G51: 51.726 | H51: 102.255 | I51: USD_millions | J51: calculated | K51: Cash interest is already included in CFO and is not subtracted again.
C52: gross funded debt to provisional lender normalized ebitda | D52: 0.42966405 | E52: 0.2127089 | F52: 0.4558271 | G52: 4.3317053 | H52: 3.1235311 | I52: turns | J52: calculated
C53: current ratio | D53: 1.5762369 | E53: 2.0070007 | F53: 2.0317385 | G53: 2.2401683 | H53: 2.0379513 | I53: turns | J53: calculated
C54: days sales outstanding | E54: 30.527725 | F54: 31.207388 | G54: 42.246346 | H54: 40.030029 | I54: days | J54: calculated | K54: FY2024-FY2025 averages are acquisition-distorted.
C55: days inventory outstanding | E55: 40.869679 | F55: 46.819672 | G55: 70.303925 | H55: 72.223701 | I55: days | J55: calculated | K55: Cost of sales, not revenue, is used; FY2024-FY2025 averages are acquisition-distorted.
M58: Metric | N58: FY2021 | O58: FY2022 | P58: FY2023 | Q58: FY2024 | R58: FY2025
M59: CFO | N59: 78.588 | O59: 97.965 | P59: 147.052 | Q59: 88.812 | R59: 164.897
M60: FCF | N60: 54.58 | O60: 64.844 | P60: 109.662 | Q60: 51.726 | R60: 102.255

Sheet Credit Adjustments
C2: Earnings definitions and lender adjustments
S4: Earnings layer | T4: FY2024 | U4: FY2025
S5: Unadjusted EBITDA | T5: =D9 -> 115.154 | U5: =E9 -> -90.508
C6: Earnings layer | D6: FY2024 | E6: FY2025 | S6: Company-adjusted EBITDA | T6: =D11 -> 182.383 | U6: =E11 -> 242.89
C7: GAAP operating income | D7: 54.826 | E7: -193.952 | S7: Partial contractual | T7: =D12 -> 0 | U7: =E12 -> 229.642
C8: Add: D&A | D8: 60.328 | E8: 103.444 | S8: Lender-base EBITDA | T8: =D14 -> 179.358 | U8: =E14 -> 225.344
C9: Unadjusted EBITDA | D9: =SUM(D7:D8) -> 115.154 | E9: =SUM(E7:E8) -> -90.508
C10: Company adjustments | D10: =D11-D9 -> 67.229 | E10: =E11-E9 -> 333.398
C11: Company-adjusted EBITDA | D11: 182.383 | E11: 242.89
C12: Partial contractual reconstruction | E12: 229.642
C13: Owner-reviewed lender adjustments | D13: =SUMIFS($H$20:$H$30,$D$20:$D$30,D$6) -> 64.204 | E13: =SUMIFS($H$20:$H$30,$D$20:$D$30,E$6) -> 315.852
C14: Owner-reviewed lender-base EBITDA | D14: =D9+D13 -> 179.358 | E14: =E9+E13 -> 225.344
C16: Unofficial contractual reconstruction; AC-011 cash outflow retained; goodwill impairment remains a major adverse risk signal.
C19: Adjustment ID | D19: Period | E19: Description | F19: Reported | G19: Low | H19: Base | I19: High/company | J19: Cash status | K19: Recurrence | L19: Contractual status | M19: Owner review | N19: Lender rationale | O19: Source ID | P19: Limitation | Q19: Double count check
C20: AC-001 | D20: FY2025 | E20: Goodwill impairment | F20: 302.284 | G20: 302.284 | H20: 302.284 | I20: 302.284 | J20: noncash | K20: nonrecurring_charge_but_material_business_risk_signal | L20: likely_permitted_nonrecurring_noncash_or_intangible_write_down | M20: owner_reviewed | N20: Full mathematical reversal is appropriate because the charge is noncash; retain the impairment as a major asset-quality and forecasting warning. | O20: SRC-002 | P20: Official compliance certificate and lender calculation are unavailable. | Q20: Matches the FY2025 GAAP impairment and CFO noncash addback; do not add either again.
C21: AC-002 | D21: FY2025 | E21: Plant relocation cost recorded in cost of sales | F21: 1.432 | G21: 0 | H21: 0 | I21: 1.432 | J21: cash_status_not_disclosed | K21: temporary_but_execution_cost_may_recur_during_stabilization | L21: not_clearly_permitted_from_public_record | M21: owner_reviewed | N21: Owner-reviewed base acceptance is zero because the disclosure does not establish cash character, completion, or nonrecurrence; the full amount remains only in the company/high sensitivity. | O21: SRC-002 | P21: Invoice detail, cash timing, completion evidence, and contractual classification. | Q21: Paired with AC-003; neither may also be included through a broader restructuring line.
C22: AC-003 | D22: FY2025 | E22: Plant relocation cost recorded in SG&A | F22: 0.221 | G22: 0 | H22: 0 | I22: 0.221 | J22: cash_status_not_disclosed | K22: temporary_but_execution_cost_may_recur_during_stabilization | L22: not_clearly_permitted_from_public_record | M22: owner_reviewed | N22: Owner-reviewed base acceptance is zero because the disclosure does not establish cash character, completion, or nonrecurrence; the full amount remains only in the company/high sensitivity. | O22: SRC-002 | P22: Invoice detail, cash timing, completion evidence, and contractual classification. | Q22: Paired with AC-002; neither may also be included through a broader restructuring line.
C23: AC-004 | D23: FY2025 | E23: Inventory purchase-accounting step-up | F23: 9.007 | G23: 9.007 | H23: 9.007 | I23: 9.007 | J23: noncash_purchase_accounting_expense | K23: nonrecurring_for_acquired_inventory | L23: likely_permitted_nonrecurring_noncash_acquisition_accounting_subject_to_certificate | M23: owner_reviewed | N23: The fair-value step-up is a finite acquisition-accounting charge rather than recurring operating cost; full acceptance does not erase acquisition risk. | O23: SRC-002 | P23: Official contractual classification and compliance certificate. | Q23: Do not also add this amount through a pro forma purchase-accounting adjustment.
C24: AC-005 | D24: FY2025 | E24: Transaction, advisory, reorganization, and product-recall composite | F24: 10.263 | G24: 0 | H24: 0 | I24: 10.263 | J24: mixed_or_not_disclosed | K24: mixed_category_includes_potentially_recurring_operational_cost | L24: mixed_and_not_determinable_from_public_record | M24: owner_reviewed | N24: Base acceptance is zero because transaction, reorganization, and recall costs are inseparable; the full company amount is retained only as an upper case pending evidence. | O24: SRC-002 | P24: Component amounts, invoices, cash/noncash split, dates, recall scope, and recurrence evidence. | Q24: Potential overlap with acquisition costs, restructuring, and operating remediation; no other bridge may absorb it.
C25: AC-006 | D25: FY2025 | E25: Restructuring, severance, and software | F25: 10.191 | G25: 4.561 | H25: 4.561 | I25: 10.191 | J25: mixed_4.561_noncash_remainder_not_established_noncash | K25: partly_nonrecurring_with_cash_execution_risk | L25: only_identified_one_time_noncash_restructuring_component_clearly_permitted | M25: owner_reviewed | N25: Accept only the $4.561 million noncash restructuring amount reconciled in the cash-flow statement; defer the remaining $5.630 million. | O25: SRC-002 | P25: Cash payments, project completion, software write-off detail, and official covenant treatment. | Q25: The $4.561 million CFO addback is evidence of noncash character, not a second EBITDA adjustment.
C26: AC-007 | D26: FY2025 | E26: Tyman post-measurement-period deferred-tax correction | F26: 9 | G26: 0 | H26: 0 | I26: 0 | J26: noncash_deferred_tax_accounting | K26: nonrecurring_tax_measurement_correction | L26: tax_is_already_excluded_in_ebitda | M26: owner_reviewed | N26: The $9 million charge matters to adjusted net income and tax quality but cannot be added again to EBITDA because income taxes are already excluded. | O26: SRC-001 | P26: Cash-tax implications, if any, remain unavailable. | Q26: Adding it to EBITDA would double count the standard tax addback.
C27: AC-008 | D27: FY2024 | E27: Plant closure cost recorded in cost of sales | F27: 3.025 | G27: 0 | H27: 0 | I27: 3.025 | J27: cash_status_not_disclosed | K27: closure_related_but_recurrence_and_cash_timing_not_proven | L27: not_clearly_permitted_from_public_record | M27: owner_reviewed | N27: Owner-reviewed base acceptance is zero because closure specificity alone does not prove cash character, completion, or nonrecurrence; the full amount remains only in the company/high sensitivity. | O27: SRC-002 | P27: Cash/noncash split, closure completion, and contractual classification. | Q27: Must not overlap with other restructuring or disposition adjustments.
C28: AC-009 | D28: FY2024 | E28: Plant closure gain recorded in SG&A | F28: -4.196 | G28: -4.196 | H28: -4.196 | I28: -4.196 | J28: noncash_gain_component_with_separate_sale_proceeds | K28: nonrecurring_gain | L28: likely_required_deduction_for_unusual_or_disposition_gain | M28: owner_reviewed | N28: Deduct the gain in full, consistent with both the company bridge and lender conservatism; excluding losses while retaining gains would be asymmetric. | O28: SRC-002 | P28: Official compliance presentation is unavailable. | Q28: Do not also deduct the related disposition gain through another contractual line.
C29: AC-010 | D29: FY2024 | E29: Inventory and receivables purchase-accounting step-up | F29: 29.076 | G29: 29.076 | H29: 29.076 | I29: 29.076 | J29: noncash_purchase_accounting_expense | K29: nonrecurring_for_acquired_balances | L29: likely_permitted_acquisition_accounting_or_pro_forma_item_subject_to_certificate | M29: owner_reviewed | N29: Owner-reviewed full acceptance reflects a finite acquisition-accounting effect; collectability, cash-realization, integration, and pro forma limitations remain separate from the earnings normalization. | O29: SRC-002 | P29: Official contractual bridge, precise inventory/receivable split, and evidence on collectability and cash realization. | Q29: Do not also include it in a separate acquisition pro forma or working-capital adjustment.
C30: AC-011 | D30: FY2024 | E30: Tyman transaction and advisory fees | F30: 39.324 | G30: 39.324 | H30: 39.324 | I30: 39.324 | J30: cash | K30: nonrecurring_completed_acquisition_cost | L30: not_determinable_without_out_of_pocket_support_incurrence_dates_and_compliance_certificate | M30: owner_reviewed | N30: Owner-reviewed lender earnings normalization accepts the completed-transaction cost, but contractual eligibility remains unresolved and historical cash conversion continues to reflect the cash use. | O30: SRC-002 | P30: Invoices, payees, exact incurrence dates, and official compliance certificate. | Q30: Do not also add the same fees through a pro forma acquisition-cost line.

Sheet Transaction
C2: Transaction and financing alternatives
C4: Case selected: | D4: =Assumptions!$D$4 -> Base
C6: Selected refinancing sources and uses
C7: Source | D7: USD millions | F7: Use / control
C8: Term funding | D8: =Assumptions!D12 -> 635 | F8: Existing debt payoff and approved closing uses | G8: 679.89772
C9: Opening revolver | D9: =Assumptions!D15 -> 29.897719 | F9: Reference closing uses | G9: 679.89772
C10: Conditional non-debt source | D10: =Assumptions!D13 -> 15 | F10: Sources less uses | G10: =D11-G9 -> 0
C11: Total sources | D11: =SUM(D8:D10) -> 679.89772 | F11: Conditional source status | G11: Pending information / condition precedent
D12: =G10 -> 0 | F12: Sources and uses check | G12: =IF(ABS(G10)<=0.001,"PASS","FAIL") -> PASS
C14: Opening capitalization
C15: Opening bank debt | D15: =Assumptions!D12+Assumptions!D15 -> 664.89772
C16: Retained other funded debt | D16: =Assumptions!D17 -> 62.619
C17: Opening total funded debt | D17: =SUM(D15:D16) -> 727.51672
C18: Opening gross funded leverage | D18: =D17/'Credit Adjustments'!E14 -> 3.2284717
C20: Existing and refinancing comparison
C21: Alternative | D21: Opening funded debt | E21: Common-horizon ending debt | F21: Unsupported maturity gap | G21: All-in base liquidity
C22: Retain existing facilities | D22: 703.869 | E22: 495.36828 | F22: 432.74928 | G22: 261.40228
C23: Selected $635m refinancing | D23: =D17 -> 727.51672 | E23: 514.75371 | F23: 324.77971 | G23: 263.90228
C24: $650m reference refinancing | D24: 742.51672 | E24: 507.95366 | F24: 340.94783 | G24: 253.84583
C26: Limited amendment / extension | D26: N/D | E26: N/D | F26: N/D | G26: Public information is insufficient for quantitative modeling.
C28: Commitment and unresolved closing items
C29: Revolver commitment | D29: =Assumptions!D14 -> 300 | F29: Financing fees not already approved | G29: N/D
C30: Letters of credit | D30: =Assumptions!D16 -> 6.2 | F30: LC transition mechanics | G30: Pending information
C31: Gross availability | D31: =Assumptions!D14-Assumptions!D15 -> 270.10228 | F31: Final lender pricing | G31: Pending information
C32: Usable availability after LCs | D32: =Assumptions!D14-Assumptions!D16-Assumptions!D15 -> 263.90228 | F32: Final payoff and funds flow | G32: Pending information

Sheet Forecast
C2: Quarterly operating and cash forecast
C4: Case selected: | D4: =Assumptions!$D$4 -> Base
C7: Metric | D7: Q2:26 | E7: Q3:26 | F7: Q4:26 | G7: Q1:27 | H7: Q2:27 | I7: Q3:27 | J7: Q4:27 | K7: Q1:28 | L7: Q2:28 | M7: Q3:28 | N7: Q4:28 | O7: Q1:29 | P7: Q2:29 | Q7: Q3:29 | R7: Q4:29 | S7: Q1:30 | T7: Q2:30 | U7: Q3:30 | V7: Q4:30 | W7: Q1:31
D8: 46142 | E8: 46234 | F8: 46326 | G8: 46418 | H8: 46507 | I8: 46599 | J8: 46691 | K8: 46783 | L8: 46873 | M8: 46965 | N8: 47057 | O8: 47149 | P8: 47238 | Q8: 47330 | R8: 47422 | S8: 47514 | T8: 47603 | U8: 47695 | V8: 47787 | W8: 47879
C10: Revenue | D10: =SUMIFS(Assumptions!$L$41:$L$364,Assumptions!$C$41:$C$364,$D$4,Assumptions!$I$41:$I$364,"FY2026",Assumptions!$J$41:$J$364,"Q2") -> 452.46669 | E10: =SUMIFS(Assumptions!$L$41:$L$364,Assumptions!$C$41:$C$364,$D$4,Assumptions!$I$41:$I$364,"FY2026",Assumptions!$J$41:$J$364,"Q3") -> 495.26062 | F10: =SUMIFS(Assumptions!$L$41:$L$364,Assumptions!$C$41:$C$364,$D$4,Assumptions!$I$41:$I$364,"FY2026",Assumptions!$J$41:$J$364,"Q4") -> 489.83375 | G10: =SUMIFS(Assumptions!$L$41:$L$364,Assumptions!$C$41:$C$364,$D$4,Assumptions!$I$41:$I$364,"FY2027",Assumptions!$J$41:$J$364,"Q1") -> 400.024 | H10: =SUMIFS(Assumptions!$L$41:$L$364,Assumptions!$C$41:$C$364,$D$4,Assumptions!$I$41:$I$364,"FY2027",Assumptions!$J$41:$J$364,"Q2") -> 452.45538 | I10: =SUMIFS(Assumptions!$L$41:$L$364,Assumptions!$C$41:$C$364,$D$4,Assumptions!$I$41:$I$364,"FY2027",Assumptions!$J$41:$J$364,"Q3") -> 495.24824 | J10: =SUMIFS(Assumptions!$L$41:$L$364,Assumptions!$C$41:$C$364,$D$4,Assumptions!$I$41:$I$364,"FY2027",Assumptions!$J$41:$J$364,"Q4") -> 489.82151 | K10: =SUMIFS(Assumptions!$L$41:$L$364,Assumptions!$C$41:$C$364,$D$4,Assumptions!$I$41:$I$364,"FY2028",Assumptions!$J$41:$J$364,"Q1") -> 400.014 | L10: =SUMIFS(Assumptions!$L$41:$L$364,Assumptions!$C$41:$C$364,$D$4,Assumptions!$I$41:$I$364,"FY2028",Assumptions!$J$41:$J$364,"Q2") -> 452.44406 | M10: =SUMIFS(Assumptions!$L$41:$L$364,Assumptions!$C$41:$C$364,$D$4,Assumptions!$I$41:$I$364,"FY2028",Assumptions!$J$41:$J$364,"Q3") -> 495.23586 | N10: =SUMIFS(Assumptions!$L$41:$L$364,Assumptions!$C$41:$C$364,$D$4,Assumptions!$I$41:$I$364,"FY2028",Assumptions!$J$41:$J$364,"Q4") -> 489.80926 | O10: =SUMIFS(Assumptions!$L$41:$L$364,Assumptions!$C$41:$C$364,$D$4,Assumptions!$I$41:$I$364,"FY2029",Assumptions!$J$41:$J$364,"Q1") -> 400.004 | P10: =SUMIFS(Assumptions!$L$41:$L$364,Assumptions!$C$41:$C$364,$D$4,Assumptions!$I$41:$I$364,"FY2029",Assumptions!$J$41:$J$364,"Q2") -> 452.43275 | Q10: =SUMIFS(Assumptions!$L$41:$L$364,Assumptions!$C$41:$C$364,$D$4,Assumptions!$I$41:$I$364,"FY2029",Assumptions!$J$41:$J$364,"Q3") -> 495.22347 | R10: =SUMIFS(Assumptions!$L$41:$L$364,Assumptions!$C$41:$C$364,$D$4,Assumptions!$I$41:$I$364,"FY2029",Assumptions!$J$41:$J$364,"Q4") -> 489.79702 | S10: =SUMIFS(Assumptions!$L$41:$L$364,Assumptions!$C$41:$C$364,$D$4,Assumptions!$I$41:$I$364,"FY2030",Assumptions!$J$41:$J$364,"Q1") -> 399.994 | T10: =SUMIFS(Assumptions!$L$41:$L$364,Assumptions!$C$41:$C$364,$D$4,Assumptions!$I$41:$I$364,"FY2030",Assumptions!$J$41:$J$364,"Q2") -> 452.42144 | U10: =SUMIFS(Assumptions!$L$41:$L$364,Assumptions!$C$41:$C$364,$D$4,Assumptions!$I$41:$I$364,"FY2030",Assumptions!$J$41:$J$364,"Q3") -> 495.21109 | V10: =SUMIFS(Assumptions!$L$41:$L$364,Assumptions!$C$41:$C$364,$D$4,Assumptions!$I$41:$I$364,"FY2030",Assumptions!$J$41:$J$364,"Q4") -> 489.78477 | W10: =SUMIFS(Assumptions!$L$41:$L$364,Assumptions!$C$41:$C$364,$D$4,Assumptions!$I$41:$I$364,"FY2031",Assumptions!$J$41:$J$364,"Q1") -> 399.984
C11: Gross margin | D11: =AVERAGEIFS(Assumptions!$M$41:$M$364,Assumptions!$C$41:$C$364,$D$4,Assumptions!$I$41:$I$364,"FY2026",Assumptions!$J$41:$J$364,"Q2")/100 -> 0.28869322 | E11: =AVERAGEIFS(Assumptions!$M$41:$M$364,Assumptions!$C$41:$C$364,$D$4,Assumptions!$I$41:$I$364,"FY2026",Assumptions!$J$41:$J$364,"Q3")/100 -> 0.27690174 | F11: =AVERAGEIFS(Assumptions!$M$41:$M$364,Assumptions!$C$41:$C$364,$D$4,Assumptions!$I$41:$I$364,"FY2026",Assumptions!$J$41:$J$364,"Q4")/100 -> 0.27915917 | G11: =AVERAGEIFS(Assumptions!$M$41:$M$364,Assumptions!$C$41:$C$364,$D$4,Assumptions!$I$41:$I$364,"FY2027",Assumptions!$J$41:$J$364,"Q1")/100 -> 0.22909675 | H11: =AVERAGEIFS(Assumptions!$M$41:$M$364,Assumptions!$C$41:$C$364,$D$4,Assumptions!$I$41:$I$364,"FY2027",Assumptions!$J$41:$J$364,"Q2")/100 -> 0.28869322 | I11: =AVERAGEIFS(Assumptions!$M$41:$M$364,Assumptions!$C$41:$C$364,$D$4,Assumptions!$I$41:$I$364,"FY2027",Assumptions!$J$41:$J$364,"Q3")/100 -> 0.27690174 | J11: =AVERAGEIFS(Assumptions!$M$41:$M$364,Assumptions!$C$41:$C$364,$D$4,Assumptions!$I$41:$I$364,"FY2027",Assumptions!$J$41:$J$364,"Q4")/100 -> 0.27915917 | K11: =AVERAGEIFS(Assumptions!$M$41:$M$364,Assumptions!$C$41:$C$364,$D$4,Assumptions!$I$41:$I$364,"FY2028",Assumptions!$J$41:$J$364,"Q1")/100 -> 0.22909675 | L11: =AVERAGEIFS(Assumptions!$M$41:$M$364,Assumptions!$C$41:$C$364,$D$4,Assumptions!$I$41:$I$364,"FY2028",Assumptions!$J$41:$J$364,"Q2")/100 -> 0.28869322 | M11: =AVERAGEIFS(Assumptions!$M$41:$M$364,Assumptions!$C$41:$C$364,$D$4,Assumptions!$I$41:$I$364,"FY2028",Assumptions!$J$41:$J$364,"Q3")/100 -> 0.27690174 | N11: =AVERAGEIFS(Assumptions!$M$41:$M$364,Assumptions!$C$41:$C$364,$D$4,Assumptions!$I$41:$I$364,"FY2028",Assumptions!$J$41:$J$364,"Q4")/100 -> 0.27915917 | O11: =AVERAGEIFS(Assumptions!$M$41:$M$364,Assumptions!$C$41:$C$364,$D$4,Assumptions!$I$41:$I$364,"FY2029",Assumptions!$J$41:$J$364,"Q1")/100 -> 0.22909675 | P11: =AVERAGEIFS(Assumptions!$M$41:$M$364,Assumptions!$C$41:$C$364,$D$4,Assumptions!$I$41:$I$364,"FY2029",Assumptions!$J$41:$J$364,"Q2")/100 -> 0.28869322 | Q11: =AVERAGEIFS(Assumptions!$M$41:$M$364,Assumptions!$C$41:$C$364,$D$4,Assumptions!$I$41:$I$364,"FY2029",Assumptions!$J$41:$J$364,"Q3")/100 -> 0.27690174 | R11: =AVERAGEIFS(Assumptions!$M$41:$M$364,Assumptions!$C$41:$C$364,$D$4,Assumptions!$I$41:$I$364,"FY2029",Assumptions!$J$41:$J$364,"Q4")/100 -> 0.27915917 | S11: =AVERAGEIFS(Assumptions!$M$41:$M$364,Assumptions!$C$41:$C$364,$D$4,Assumptions!$I$41:$I$364,"FY2030",Assumptions!$J$41:$J$364,"Q1")/100 -> 0.22909675 | T11: =AVERAGEIFS(Assumptions!$M$41:$M$364,Assumptions!$C$41:$C$364,$D$4,Assumptions!$I$41:$I$364,"FY2030",Assumptions!$J$41:$J$364,"Q2")/100 -> 0.28869322 | U11: =AVERAGEIFS(Assumptions!$M$41:$M$364,Assumptions!$C$41:$C$364,$D$4,Assumptions!$I$41:$I$364,"FY2030",Assumptions!$J$41:$J$364,"Q3")/100 -> 0.27690174 | V11: =AVERAGEIFS(Assumptions!$M$41:$M$364,Assumptions!$C$41:$C$364,$D$4,Assumptions!$I$41:$I$364,"FY2030",Assumptions!$J$41:$J$364,"Q4")/100 -> 0.27915917 | W11: =AVERAGEIFS(Assumptions!$M$41:$M$364,Assumptions!$C$41:$C$364,$D$4,Assumptions!$I$41:$I$364,"FY2031",Assumptions!$J$41:$J$364,"Q1")/100 -> 0.22909675
C12: Gross profit | D12: =D10*D11 -> 130.62406 | E12: =E10*E11 -> 137.13852 | F12: =F10*F11 -> 136.74159 | G12: =G10*G11 -> 91.6442 | H12: =H10*H11 -> 130.6208 | I12: =I10*I11 -> 137.1351 | J12: =J10*J11 -> 136.73817 | K12: =K10*K11 -> 91.641909 | ... W12: =W10*W11 -> 91.635036
C13: Cash operating expenses | D13: =D12-D14 -> 67.436088 | E13: =E12-E14 -> 73.814138 | F13: =F12-F14 -> 73.005313 | G13: =G12-G14 -> 59.619977 | H13: =H12-H14 -> 67.434402 | I13: =I12-I14 -> 73.812292 | J13: =J12-J14 -> 73.003487 | K13: =K12-K14 -> 59.618486 | ... W13: =W12-W14 -> 59.614015
C14: Lender-base EBITDA | D14: =SUMIFS(Assumptions!$N$41:$N$364,Assumptions!$C$41:$C$364,$D$4,Assumptions!$I$41:$I$364,"FY2026",Assumptions!$J$41:$J$364,"Q2")*(1+Assumptions!$D$21) -> 63.187976 | E14: =SUMIFS(Assumptions!$N$41:$N$364,Assumptions!$C$41:$C$364,$D$4,Assumptions!$I$41:$I$364,"FY2026",Assumptions!$J$41:$J$364,"Q3")*(1+Assumptions!$D$21) -> 63.324387 | F14: =SUMIFS(Assumptions!$N$41:$N$364,Assumptions!$C$41:$C$364,$D$4,Assumptions!$I$41:$I$364,"FY2026",Assumptions!$J$41:$J$364,"Q4")*(1+Assumptions!$D$21) -> 63.736274 | G14: =SUMIFS(Assumptions!$N$41:$N$364,Assumptions!$C$41:$C$364,$D$4,Assumptions!$I$41:$I$364,"FY2027",Assumptions!$J$41:$J$364,"Q1")*(1+Assumptions!$D$21) -> 32.024223 | H14: =SUMIFS(Assumptions!$N$41:$N$364,Assumptions!$C$41:$C$364,$D$4,Assumptions!$I$41:$I$364,"FY2027",Assumptions!$J$41:$J$364,"Q2")*(1+Assumptions!$D$21) -> 63.186396 | I14: =SUMIFS(Assumptions!$N$41:$N$364,Assumptions!$C$41:$C$364,$D$4,Assumptions!$I$41:$I$364,"FY2027",Assumptions!$J$41:$J$364,"Q3")*(1+Assumptions!$D$21) -> 63.322804 | J14: =SUMIFS(Assumptions!$N$41:$N$364,Assumptions!$C$41:$C$364,$D$4,Assumptions!$I$41:$I$364,"FY2027",Assumptions!$J$41:$J$364,"Q4")*(1+Assumptions!$D$21) -> 63.73468 | K14: =SUMIFS(Assumptions!$N$41:$N$364,Assumptions!$C$41:$C$364,$D$4,Assumptions!$I$41:$I$364,"FY2028",Assumptions!$J$41:$J$364,"Q1")*(1+Assumptions!$D$21) -> 32.023422 | L14: =SUMIFS(Assumptions!$N$41:$N$364,Assumptions!$C$41:$C$364,$D$4,Assumptions!$I$41:$I$364,"FY2028",Assumptions!$J$41:$J$364,"Q2")*(1+Assumptions!$D$21) -> 63.184817 | M14: =SUMIFS(Assumptions!$N$41:$N$364,Assumptions!$C$41:$C$364,$D$4,Assumptions!$I$41:$I$364,"FY2028",Assumptions!$J$41:$J$364,"Q3")*(1+Assumptions!$D$21) -> 63.321221 | N14: =SUMIFS(Assumptions!$N$41:$N$364,Assumptions!$C$41:$C$364,$D$4,Assumptions!$I$41:$I$364,"FY2028",Assumptions!$J$41:$J$364,"Q4")*(1+Assumptions!$D$21) -> 63.733087 | O14: =SUMIFS(Assumptions!$N$41:$N$364,Assumptions!$C$41:$C$364,$D$4,Assumptions!$I$41:$I$364,"FY2029",Assumptions!$J$41:$J$364,"Q1")*(1+Assumptions!$D$21) -> 32.022622 | P14: =SUMIFS(Assumptions!$N$41:$N$364,Assumptions!$C$41:$C$364,$D$4,Assumptions!$I$41:$I$364,"FY2029",Assumptions!$J$41:$J$364,"Q2")*(1+Assumptions!$D$21) -> 63.183237 | Q14: =SUMIFS(Assumptions!$N$41:$N$364,Assumptions!$C$41:$C$364,$D$4,Assumptions!$I$41:$I$364,"FY2029",Assumptions!$J$41:$J$364,"Q3")*(1+Assumptions!$D$21) -> 63.319638 | R14: =SUMIFS(Assumptions!$N$41:$N$364,Assumptions!$C$41:$C$364,$D$4,Assumptions!$I$41:$I$364,"FY2029",Assumptions!$J$41:$J$364,"Q4")*(1+Assumptions!$D$21) -> 63.731494 | S14: =SUMIFS(Assumptions!$N$41:$N$364,Assumptions!$C$41:$C$364,$D$4,Assumptions!$I$41:$I$364,"FY2030",Assumptions!$J$41:$J$364,"Q1")*(1+Assumptions!$D$21) -> 32.021821 | T14: =SUMIFS(Assumptions!$N$41:$N$364,Assumptions!$C$41:$C$364,$D$4,Assumptions!$I$41:$I$364,"FY2030",Assumptions!$J$41:$J$364,"Q2")*(1+Assumptions!$D$21) -> 63.181658 | U14: =SUMIFS(Assumptions!$N$41:$N$364,Assumptions!$C$41:$C$364,$D$4,Assumptions!$I$41:$I$364,"FY2030",Assumptions!$J$41:$J$364,"Q3")*(1+Assumptions!$D$21) -> 63.318055 | V14: =SUMIFS(Assumptions!$N$41:$N$364,Assumptions!$C$41:$C$364,$D$4,Assumptions!$I$41:$I$364,"FY2030",Assumptions!$J$41:$J$364,"Q4")*(1+Assumptions!$D$21) -> 63.7299 | W14: =SUMIFS(Assumptions!$N$41:$N$364,Assumptions!$C$41:$C$364,$D$4,Assumptions!$I$41:$I$364,"FY2031",Assumptions!$J$41:$J$364,"Q1")*(1+Assumptions!$D$21) -> 32.021021
C15: EBITDA margin | D15: =IF(D10=0,"",D14/D10) -> 0.13965222 | E15: =IF(E10=0,"",E14/E10) -> 0.12786074 | F15: =IF(F10=0,"",F14/F10) -> 0.13011817 | G15: =IF(G10=0,"",G14/G10) -> 0.080055755 | H15: =IF(H10=0,"",H14/H10) -> 0.13965222 | I15: =IF(I10=0,"",I14/I10) -> 0.12786074 | J15: =IF(J10=0,"",J14/J10) -> 0.13011817 | K15: =IF(K10=0,"",K14/K10) -> 0.080055755 | ... W15: =IF(W10=0,"",W14/W10) -> 0.080055755
C16: Depreciation and amortization | D16: =SUMIFS(Assumptions!$O$41:$O$364,Assumptions!$C$41:$C$364,$D$4,Assumptions!$I$41:$I$364,"FY2026",Assumptions!$J$41:$J$364,"Q2") -> -25.470255 | E16: =SUMIFS(Assumptions!$O$41:$O$364,Assumptions!$C$41:$C$364,$D$4,Assumptions!$I$41:$I$364,"FY2026",Assumptions!$J$41:$J$364,"Q3") -> -27.879211 | F16: =SUMIFS(Assumptions!$O$41:$O$364,Assumptions!$C$41:$C$364,$D$4,Assumptions!$I$41:$I$364,"FY2026",Assumptions!$J$41:$J$364,"Q4") -> -27.573722 | G16: =SUMIFS(Assumptions!$O$41:$O$364,Assumptions!$C$41:$C$364,$D$4,Assumptions!$I$41:$I$364,"FY2027",Assumptions!$J$41:$J$364,"Q1") -> -22.518151 | H16: =SUMIFS(Assumptions!$O$41:$O$364,Assumptions!$C$41:$C$364,$D$4,Assumptions!$I$41:$I$364,"FY2027",Assumptions!$J$41:$J$364,"Q2") -> -25.469618 | I16: =SUMIFS(Assumptions!$O$41:$O$364,Assumptions!$C$41:$C$364,$D$4,Assumptions!$I$41:$I$364,"FY2027",Assumptions!$J$41:$J$364,"Q3") -> -27.878514 | J16: =SUMIFS(Assumptions!$O$41:$O$364,Assumptions!$C$41:$C$364,$D$4,Assumptions!$I$41:$I$364,"FY2027",Assumptions!$J$41:$J$364,"Q4") -> -27.573032 | K16: =SUMIFS(Assumptions!$O$41:$O$364,Assumptions!$C$41:$C$364,$D$4,Assumptions!$I$41:$I$364,"FY2028",Assumptions!$J$41:$J$364,"Q1") -> -22.517588 | L16: =SUMIFS(Assumptions!$O$41:$O$364,Assumptions!$C$41:$C$364,$D$4,Assumptions!$I$41:$I$364,"FY2028",Assumptions!$J$41:$J$364,"Q2") -> -25.468981 | M16: =SUMIFS(Assumptions!$O$41:$O$364,Assumptions!$C$41:$C$364,$D$4,Assumptions!$I$41:$I$364,"FY2028",Assumptions!$J$41:$J$364,"Q3") -> -27.877817 | N16: =SUMIFS(Assumptions!$O$41:$O$364,Assumptions!$C$41:$C$364,$D$4,Assumptions!$I$41:$I$364,"FY2028",Assumptions!$J$41:$J$364,"Q4") -> -27.572343 | O16: =SUMIFS(Assumptions!$O$41:$O$364,Assumptions!$C$41:$C$364,$D$4,Assumptions!$I$41:$I$364,"FY2029",Assumptions!$J$41:$J$364,"Q1") -> -22.517025 | P16: =SUMIFS(Assumptions!$O$41:$O$364,Assumptions!$C$41:$C$364,$D$4,Assumptions!$I$41:$I$364,"FY2029",Assumptions!$J$41:$J$364,"Q2") -> -25.468345 | Q16: =SUMIFS(Assumptions!$O$41:$O$364,Assumptions!$C$41:$C$364,$D$4,Assumptions!$I$41:$I$364,"FY2029",Assumptions!$J$41:$J$364,"Q3") -> -27.87712 | R16: =SUMIFS(Assumptions!$O$41:$O$364,Assumptions!$C$41:$C$364,$D$4,Assumptions!$I$41:$I$364,"FY2029",Assumptions!$J$41:$J$364,"Q4") -> -27.571654 | S16: =SUMIFS(Assumptions!$O$41:$O$364,Assumptions!$C$41:$C$364,$D$4,Assumptions!$I$41:$I$364,"FY2030",Assumptions!$J$41:$J$364,"Q1") -> -22.516462 | T16: =SUMIFS(Assumptions!$O$41:$O$364,Assumptions!$C$41:$C$364,$D$4,Assumptions!$I$41:$I$364,"FY2030",Assumptions!$J$41:$J$364,"Q2") -> -25.467708 | U16: =SUMIFS(Assumptions!$O$41:$O$364,Assumptions!$C$41:$C$364,$D$4,Assumptions!$I$41:$I$364,"FY2030",Assumptions!$J$41:$J$364,"Q3") -> -27.876423 | V16: =SUMIFS(Assumptions!$O$41:$O$364,Assumptions!$C$41:$C$364,$D$4,Assumptions!$I$41:$I$364,"FY2030",Assumptions!$J$41:$J$364,"Q4") -> -27.570964 | W16: =SUMIFS(Assumptions!$O$41:$O$364,Assumptions!$C$41:$C$364,$D$4,Assumptions!$I$41:$I$364,"FY2031",Assumptions!$J$41:$J$364,"Q1") -> -22.515899
C17: Operating profit | D17: =D14+D16 -> 37.717721 | E17: =E14+E16 -> 35.445176 | F17: =F14+F16 -> 36.162552 | G17: =G14+G16 -> 9.5060722 | H17: =H14+H16 -> 37.716778 | I17: =I14+I16 -> 35.44429 | J17: =J14+J16 -> 36.161648 | K17: =K14+K16 -> 9.5058345 | ... W17: =W14+W16 -> 9.5051216
C18: Cash taxes | D18: =SUMIFS(Assumptions!$P$41:$P$364,Assumptions!$C$41:$C$364,$D$4,Assumptions!$I$41:$I$364,"FY2026",Assumptions!$J$41:$J$364,"Q2") -> -9.4294303 | E18: =SUMIFS(Assumptions!$P$41:$P$364,Assumptions!$C$41:$C$364,$D$4,Assumptions!$I$41:$I$364,"FY2026",Assumptions!$J$41:$J$364,"Q3") -> -8.8612941 | F18: =SUMIFS(Assumptions!$P$41:$P$364,Assumptions!$C$41:$C$364,$D$4,Assumptions!$I$41:$I$364,"FY2026",Assumptions!$J$41:$J$364,"Q4") -> -9.040638 | G18: =SUMIFS(Assumptions!$P$41:$P$364,Assumptions!$C$41:$C$364,$D$4,Assumptions!$I$41:$I$364,"FY2027",Assumptions!$J$41:$J$364,"Q1") -> -2.376518 | H18: =SUMIFS(Assumptions!$P$41:$P$364,Assumptions!$C$41:$C$364,$D$4,Assumptions!$I$41:$I$364,"FY2027",Assumptions!$J$41:$J$364,"Q2") -> -9.4291946 | I18: =SUMIFS(Assumptions!$P$41:$P$364,Assumptions!$C$41:$C$364,$D$4,Assumptions!$I$41:$I$364,"FY2027",Assumptions!$J$41:$J$364,"Q3") -> -8.8610726 | J18: =SUMIFS(Assumptions!$P$41:$P$364,Assumptions!$C$41:$C$364,$D$4,Assumptions!$I$41:$I$364,"FY2027",Assumptions!$J$41:$J$364,"Q4") -> -9.040412 | K18: =SUMIFS(Assumptions!$P$41:$P$364,Assumptions!$C$41:$C$364,$D$4,Assumptions!$I$41:$I$364,"FY2028",Assumptions!$J$41:$J$364,"Q1") -> -2.3764586 | L18: =SUMIFS(Assumptions!$P$41:$P$364,Assumptions!$C$41:$C$364,$D$4,Assumptions!$I$41:$I$364,"FY2028",Assumptions!$J$41:$J$364,"Q2") -> -9.4289589 | M18: =SUMIFS(Assumptions!$P$41:$P$364,Assumptions!$C$41:$C$364,$D$4,Assumptions!$I$41:$I$364,"FY2028",Assumptions!$J$41:$J$364,"Q3") -> -8.860851 | N18: =SUMIFS(Assumptions!$P$41:$P$364,Assumptions!$C$41:$C$364,$D$4,Assumptions!$I$41:$I$364,"FY2028",Assumptions!$J$41:$J$364,"Q4") -> -9.040186 | O18: =SUMIFS(Assumptions!$P$41:$P$364,Assumptions!$C$41:$C$364,$D$4,Assumptions!$I$41:$I$364,"FY2029",Assumptions!$J$41:$J$364,"Q1") -> -2.3763992 | P18: =SUMIFS(Assumptions!$P$41:$P$364,Assumptions!$C$41:$C$364,$D$4,Assumptions!$I$41:$I$364,"FY2029",Assumptions!$J$41:$J$364,"Q2") -> -9.4287232 | Q18: =SUMIFS(Assumptions!$P$41:$P$364,Assumptions!$C$41:$C$364,$D$4,Assumptions!$I$41:$I$364,"FY2029",Assumptions!$J$41:$J$364,"Q3") -> -8.8606295 | R18: =SUMIFS(Assumptions!$P$41:$P$364,Assumptions!$C$41:$C$364,$D$4,Assumptions!$I$41:$I$364,"FY2029",Assumptions!$J$41:$J$364,"Q4") -> -9.03996 | S18: =SUMIFS(Assumptions!$P$41:$P$364,Assumptions!$C$41:$C$364,$D$4,Assumptions!$I$41:$I$364,"FY2030",Assumptions!$J$41:$J$364,"Q1") -> -2.3763398 | T18: =SUMIFS(Assumptions!$P$41:$P$364,Assumptions!$C$41:$C$364,$D$4,Assumptions!$I$41:$I$364,"FY2030",Assumptions!$J$41:$J$364,"Q2") -> -9.4284874 | U18: =SUMIFS(Assumptions!$P$41:$P$364,Assumptions!$C$41:$C$364,$D$4,Assumptions!$I$41:$I$364,"FY2030",Assumptions!$J$41:$J$364,"Q3") -> -8.860408 | V18: =SUMIFS(Assumptions!$P$41:$P$364,Assumptions!$C$41:$C$364,$D$4,Assumptions!$I$41:$I$364,"FY2030",Assumptions!$J$41:$J$364,"Q4") -> -9.039734 | W18: =SUMIFS(Assumptions!$P$41:$P$364,Assumptions!$C$41:$C$364,$D$4,Assumptions!$I$41:$I$364,"FY2031",Assumptions!$J$41:$J$364,"Q1") -> -2.3762804
C19: Working-capital cash flow | D19: =SUMIFS(Assumptions!$Q$41:$Q$364,Assumptions!$C$41:$C$364,$D$4,Assumptions!$I$41:$I$364,"FY2026",Assumptions!$J$41:$J$364,"Q2")+IF(D$8=$D$8,-D10/365*Assumptions!$D$23,0) -> -0.074205147 | E19: =SUMIFS(Assumptions!$Q$41:$Q$364,Assumptions!$C$41:$C$364,$D$4,Assumptions!$I$41:$I$364,"FY2026",Assumptions!$J$41:$J$364,"Q3")+IF(E$8=$D$8,-E10/365*Assumptions!$D$23,0) -> -0.081208732 | F19: =SUMIFS(Assumptions!$Q$41:$Q$364,Assumptions!$C$41:$C$364,$D$4,Assumptions!$I$41:$I$364,"FY2026",Assumptions!$J$41:$J$364,"Q4")+IF(F$8=$D$8,-F10/365*Assumptions!$D$23,0) -> -0.080321659 | G19: =SUMIFS(Assumptions!$Q$41:$Q$364,Assumptions!$C$41:$C$364,$D$4,Assumptions!$I$41:$I$364,"FY2027",Assumptions!$J$41:$J$364,"Q1")+IF(G$8=$D$8,-G10/365*Assumptions!$D$23,0) -> 0.0015252598 | H19: =SUMIFS(Assumptions!$Q$41:$Q$364,Assumptions!$C$41:$C$364,$D$4,Assumptions!$I$41:$I$364,"FY2027",Assumptions!$J$41:$J$364,"Q2")+IF(H$8=$D$8,-H10/365*Assumptions!$D$23,0) -> 0.0016574096 | I19: =SUMIFS(Assumptions!$Q$41:$Q$364,Assumptions!$C$41:$C$364,$D$4,Assumptions!$I$41:$I$364,"FY2027",Assumptions!$J$41:$J$364,"Q3")+IF(I$8=$D$8,-I10/365*Assumptions!$D$23,0) -> 0.0018288422 | J19: =SUMIFS(Assumptions!$Q$41:$Q$364,Assumptions!$C$41:$C$364,$D$4,Assumptions!$I$41:$I$364,"FY2027",Assumptions!$J$41:$J$364,"Q4")+IF(J$8=$D$8,-J10/365*Assumptions!$D$23,0) -> 0.0018060236 | K19: =SUMIFS(Assumptions!$Q$41:$Q$364,Assumptions!$C$41:$C$364,$D$4,Assumptions!$I$41:$I$364,"FY2028",Assumptions!$J$41:$J$364,"Q1")+IF(K$8=$D$8,-K10/365*Assumptions!$D$23,0) -> 0.0015252216 | L19: =SUMIFS(Assumptions!$Q$41:$Q$364,Assumptions!$C$41:$C$364,$D$4,Assumptions!$I$41:$I$364,"FY2028",Assumptions!$J$41:$J$364,"Q2")+IF(L$8=$D$8,-L10/365*Assumptions!$D$23,0) -> 0.0016573681 | M19: =SUMIFS(Assumptions!$Q$41:$Q$364,Assumptions!$C$41:$C$364,$D$4,Assumptions!$I$41:$I$364,"FY2028",Assumptions!$J$41:$J$364,"Q3")+IF(M$8=$D$8,-M10/365*Assumptions!$D$23,0) -> 0.0018287965 | N19: =SUMIFS(Assumptions!$Q$41:$Q$364,Assumptions!$C$41:$C$364,$D$4,Assumptions!$I$41:$I$364,"FY2028",Assumptions!$J$41:$J$364,"Q4")+IF(N$8=$D$8,-N10/365*Assumptions!$D$23,0) -> 0.0018059784 | O19: =SUMIFS(Assumptions!$Q$41:$Q$364,Assumptions!$C$41:$C$364,$D$4,Assumptions!$I$41:$I$364,"FY2029",Assumptions!$J$41:$J$364,"Q1")+IF(O$8=$D$8,-O10/365*Assumptions!$D$23,0) -> 0.0015251835 | P19: =SUMIFS(Assumptions!$Q$41:$Q$364,Assumptions!$C$41:$C$364,$D$4,Assumptions!$I$41:$I$364,"FY2029",Assumptions!$J$41:$J$364,"Q2")+IF(P$8=$D$8,-P10/365*Assumptions!$D$23,0) -> 0.0016573267 | Q19: =SUMIFS(Assumptions!$Q$41:$Q$364,Assumptions!$C$41:$C$364,$D$4,Assumptions!$I$41:$I$364,"FY2029",Assumptions!$J$41:$J$364,"Q3")+IF(Q$8=$D$8,-Q10/365*Assumptions!$D$23,0) -> 0.0018287507 | R19: =SUMIFS(Assumptions!$Q$41:$Q$364,Assumptions!$C$41:$C$364,$D$4,Assumptions!$I$41:$I$364,"FY2029",Assumptions!$J$41:$J$364,"Q4")+IF(R$8=$D$8,-R10/365*Assumptions!$D$23,0) -> 0.0018059333 | S19: =SUMIFS(Assumptions!$Q$41:$Q$364,Assumptions!$C$41:$C$364,$D$4,Assumptions!$I$41:$I$364,"FY2030",Assumptions!$J$41:$J$364,"Q1")+IF(S$8=$D$8,-S10/365*Assumptions!$D$23,0) -> 0.0015251454 | T19: =SUMIFS(Assumptions!$Q$41:$Q$364,Assumptions!$C$41:$C$364,$D$4,Assumptions!$I$41:$I$364,"FY2030",Assumptions!$J$41:$J$364,"Q2")+IF(T$8=$D$8,-T10/365*Assumptions!$D$23,0) -> 0.0016572853 | U19: =SUMIFS(Assumptions!$Q$41:$Q$364,Assumptions!$C$41:$C$364,$D$4,Assumptions!$I$41:$I$364,"FY2030",Assumptions!$J$41:$J$364,"Q3")+IF(U$8=$D$8,-U10/365*Assumptions!$D$23,0) -> 0.001828705 | V19: =SUMIFS(Assumptions!$Q$41:$Q$364,Assumptions!$C$41:$C$364,$D$4,Assumptions!$I$41:$I$364,"FY2030",Assumptions!$J$41:$J$364,"Q4")+IF(V$8=$D$8,-V10/365*Assumptions!$D$23,0) -> 0.0018058881 | W19: =SUMIFS(Assumptions!$Q$41:$Q$364,Assumptions!$C$41:$C$364,$D$4,Assumptions!$I$41:$I$364,"FY2031",Assumptions!$J$41:$J$364,"Q1")+IF(W$8=$D$8,-W10/365*Assumptions!$D$23,0) -> 0.0015251072
C20: Capital expenditures | D20: =SUMIFS(Assumptions!$R$41:$R$364,Assumptions!$C$41:$C$364,$D$4,Assumptions!$I$41:$I$364,"FY2026",Assumptions!$J$41:$J$364,"Q2") -> -15.836334 | E20: =SUMIFS(Assumptions!$R$41:$R$364,Assumptions!$C$41:$C$364,$D$4,Assumptions!$I$41:$I$364,"FY2026",Assumptions!$J$41:$J$364,"Q3") -> -17.334122 | F20: =SUMIFS(Assumptions!$R$41:$R$364,Assumptions!$C$41:$C$364,$D$4,Assumptions!$I$41:$I$364,"FY2026",Assumptions!$J$41:$J$364,"Q4") -> -17.144181 | G20: =SUMIFS(Assumptions!$R$41:$R$364,Assumptions!$C$41:$C$364,$D$4,Assumptions!$I$41:$I$364,"FY2027",Assumptions!$J$41:$J$364,"Q1") -> -14.00084 | H20: =SUMIFS(Assumptions!$R$41:$R$364,Assumptions!$C$41:$C$364,$D$4,Assumptions!$I$41:$I$364,"FY2027",Assumptions!$J$41:$J$364,"Q2") -> -15.835938 | I20: =SUMIFS(Assumptions!$R$41:$R$364,Assumptions!$C$41:$C$364,$D$4,Assumptions!$I$41:$I$364,"FY2027",Assumptions!$J$41:$J$364,"Q3") -> -17.333688 | J20: =SUMIFS(Assumptions!$R$41:$R$364,Assumptions!$C$41:$C$364,$D$4,Assumptions!$I$41:$I$364,"FY2027",Assumptions!$J$41:$J$364,"Q4") -> -17.143753 | K20: =SUMIFS(Assumptions!$R$41:$R$364,Assumptions!$C$41:$C$364,$D$4,Assumptions!$I$41:$I$364,"FY2028",Assumptions!$J$41:$J$364,"Q1") -> -14.00049 | L20: =SUMIFS(Assumptions!$R$41:$R$364,Assumptions!$C$41:$C$364,$D$4,Assumptions!$I$41:$I$364,"FY2028",Assumptions!$J$41:$J$364,"Q2") -> -15.835542 | M20: =SUMIFS(Assumptions!$R$41:$R$364,Assumptions!$C$41:$C$364,$D$4,Assumptions!$I$41:$I$364,"FY2028",Assumptions!$J$41:$J$364,"Q3") -> -17.333255 | N20: =SUMIFS(Assumptions!$R$41:$R$364,Assumptions!$C$41:$C$364,$D$4,Assumptions!$I$41:$I$364,"FY2028",Assumptions!$J$41:$J$364,"Q4") -> -17.143324 | O20: =SUMIFS(Assumptions!$R$41:$R$364,Assumptions!$C$41:$C$364,$D$4,Assumptions!$I$41:$I$364,"FY2029",Assumptions!$J$41:$J$364,"Q1") -> -14.00014 | P20: =SUMIFS(Assumptions!$R$41:$R$364,Assumptions!$C$41:$C$364,$D$4,Assumptions!$I$41:$I$364,"FY2029",Assumptions!$J$41:$J$364,"Q2") -> -15.835146 | Q20: =SUMIFS(Assumptions!$R$41:$R$364,Assumptions!$C$41:$C$364,$D$4,Assumptions!$I$41:$I$364,"FY2029",Assumptions!$J$41:$J$364,"Q3") -> -17.332822 | R20: =SUMIFS(Assumptions!$R$41:$R$364,Assumptions!$C$41:$C$364,$D$4,Assumptions!$I$41:$I$364,"FY2029",Assumptions!$J$41:$J$364,"Q4") -> -17.142896 | S20: =SUMIFS(Assumptions!$R$41:$R$364,Assumptions!$C$41:$C$364,$D$4,Assumptions!$I$41:$I$364,"FY2030",Assumptions!$J$41:$J$364,"Q1") -> -13.99979 | T20: =SUMIFS(Assumptions!$R$41:$R$364,Assumptions!$C$41:$C$364,$D$4,Assumptions!$I$41:$I$364,"FY2030",Assumptions!$J$41:$J$364,"Q2") -> -15.834751 | U20: =SUMIFS(Assumptions!$R$41:$R$364,Assumptions!$C$41:$C$364,$D$4,Assumptions!$I$41:$I$364,"FY2030",Assumptions!$J$41:$J$364,"Q3") -> -17.332388 | V20: =SUMIFS(Assumptions!$R$41:$R$364,Assumptions!$C$41:$C$364,$D$4,Assumptions!$I$41:$I$364,"FY2030",Assumptions!$J$41:$J$364,"Q4") -> -17.142467 | W20: =SUMIFS(Assumptions!$R$41:$R$364,Assumptions!$C$41:$C$364,$D$4,Assumptions!$I$41:$I$364,"FY2031",Assumptions!$J$41:$J$364,"Q1") -> -13.99944
C21: Other operating cash uses | D21: =SUMIFS(Assumptions!$S$41:$S$364,Assumptions!$C$41:$C$364,$D$4,Assumptions!$I$41:$I$364,"FY2026",Assumptions!$J$41:$J$364,"Q2") -> -0.7 | E21: =SUMIFS(Assumptions!$S$41:$S$364,Assumptions!$C$41:$C$364,$D$4,Assumptions!$I$41:$I$364,"FY2026",Assumptions!$J$41:$J$364,"Q3") -> 0 | F21: =SUMIFS(Assumptions!$S$41:$S$364,Assumptions!$C$41:$C$364,$D$4,Assumptions!$I$41:$I$364,"FY2026",Assumptions!$J$41:$J$364,"Q4") -> 0 | G21: =SUMIFS(Assumptions!$S$41:$S$364,Assumptions!$C$41:$C$364,$D$4,Assumptions!$I$41:$I$364,"FY2027",Assumptions!$J$41:$J$364,"Q1") -> 0 | H21: =SUMIFS(Assumptions!$S$41:$S$364,Assumptions!$C$41:$C$364,$D$4,Assumptions!$I$41:$I$364,"FY2027",Assumptions!$J$41:$J$364,"Q2") -> 0 | I21: =SUMIFS(Assumptions!$S$41:$S$364,Assumptions!$C$41:$C$364,$D$4,Assumptions!$I$41:$I$364,"FY2027",Assumptions!$J$41:$J$364,"Q3") -> 0 | J21: =SUMIFS(Assumptions!$S$41:$S$364,Assumptions!$C$41:$C$364,$D$4,Assumptions!$I$41:$I$364,"FY2027",Assumptions!$J$41:$J$364,"Q4") -> 0 | K21: =SUMIFS(Assumptions!$S$41:$S$364,Assumptions!$C$41:$C$364,$D$4,Assumptions!$I$41:$I$364,"FY2028",Assumptions!$J$41:$J$364,"Q1") -> 0 | L21: =SUMIFS(Assumptions!$S$41:$S$364,Assumptions!$C$41:$C$364,$D$4,Assumptions!$I$41:$I$364,"FY2028",Assumptions!$J$41:$J$364,"Q2") -> 0 | M21: =SUMIFS(Assumptions!$S$41:$S$364,Assumptions!$C$41:$C$364,$D$4,Assumptions!$I$41:$I$364,"FY2028",Assumptions!$J$41:$J$364,"Q3") -> 0 | N21: =SUMIFS(Assumptions!$S$41:$S$364,Assumptions!$C$41:$C$364,$D$4,Assumptions!$I$41:$I$364,"FY2028",Assumptions!$J$41:$J$364,"Q4") -> 0 | O21: =SUMIFS(Assumptions!$S$41:$S$364,Assumptions!$C$41:$C$364,$D$4,Assumptions!$I$41:$I$364,"FY2029",Assumptions!$J$41:$J$364,"Q1") -> 0 | P21: =SUMIFS(Assumptions!$S$41:$S$364,Assumptions!$C$41:$C$364,$D$4,Assumptions!$I$41:$I$364,"FY2029",Assumptions!$J$41:$J$364,"Q2") -> 0 | Q21: =SUMIFS(Assumptions!$S$41:$S$364,Assumptions!$C$41:$C$364,$D$4,Assumptions!$I$41:$I$364,"FY2029",Assumptions!$J$41:$J$364,"Q3") -> 0 | R21: =SUMIFS(Assumptions!$S$41:$S$364,Assumptions!$C$41:$C$364,$D$4,Assumptions!$I$41:$I$364,"FY2029",Assumptions!$J$41:$J$364,"Q4") -> 0 | S21: =SUMIFS(Assumptions!$S$41:$S$364,Assumptions!$C$41:$C$364,$D$4,Assumptions!$I$41:$I$364,"FY2030",Assumptions!$J$41:$J$364,"Q1") -> 0 | T21: =SUMIFS(Assumptions!$S$41:$S$364,Assumptions!$C$41:$C$364,$D$4,Assumptions!$I$41:$I$364,"FY2030",Assumptions!$J$41:$J$364,"Q2") -> 0 | U21: =SUMIFS(Assumptions!$S$41:$S$364,Assumptions!$C$41:$C$364,$D$4,Assumptions!$I$41:$I$364,"FY2030",Assumptions!$J$41:$J$364,"Q3") -> 0 | V21: =SUMIFS(Assumptions!$S$41:$S$364,Assumptions!$C$41:$C$364,$D$4,Assumptions!$I$41:$I$364,"FY2030",Assumptions!$J$41:$J$364,"Q4") -> 0 | W21: =SUMIFS(Assumptions!$S$41:$S$364,Assumptions!$C$41:$C$364,$D$4,Assumptions!$I$41:$I$364,"FY2031",Assumptions!$J$41:$J$364,"Q1") -> 0
C22: CFADS before cash interest | D22: =SUM(D14,D18:D21) -> 37.148007 | E22: =SUM(E14,E18:E21) -> 37.047763 | F22: =SUM(F14,F18:F21) -> 37.471133 | G22: =SUM(G14,G18:G21) -> 15.64839 | H22: =SUM(H14,H18:H21) -> 37.922921 | I22: =SUM(I14,I18:I21) -> 37.129872 | J22: =SUM(J14,J18:J21) -> 37.552322 | K22: =SUM(K14,K18:K21) -> 15.647999 | ... W22: =SUM(W14,W18:W21) -> 15.646826
C23: Cash interest | D23: =SUMIFS('Debt Schedule'!$T$12:$T$47,'Debt Schedule'!$F$12:$F$47,"FY2026",'Debt Schedule'!$G$12:$G$47,"Q2") -> 10.761818 | E23: =SUMIFS('Debt Schedule'!$T$12:$T$47,'Debt Schedule'!$F$12:$F$47,"FY2026",'Debt Schedule'!$G$12:$G$47,"Q3") -> 10.440981 | F23: =SUMIFS('Debt Schedule'!$T$12:$T$47,'Debt Schedule'!$F$12:$F$47,"FY2026",'Debt Schedule'!$G$12:$G$47,"Q4") -> 10.112165 | G23: =SUMIFS('Debt Schedule'!$T$12:$T$47,'Debt Schedule'!$F$12:$F$47,"FY2027",'Debt Schedule'!$G$12:$G$47,"Q1") -> 9.9539895 | H23: =SUMIFS('Debt Schedule'!$T$12:$T$47,'Debt Schedule'!$F$12:$F$47,"FY2027",'Debt Schedule'!$G$12:$G$47,"Q2") -> 9.7896776 | I23: =SUMIFS('Debt Schedule'!$T$12:$T$47,'Debt Schedule'!$F$12:$F$47,"FY2027",'Debt Schedule'!$G$12:$G$47,"Q3") -> 9.4658674 | J23: =SUMIFS('Debt Schedule'!$T$12:$T$47,'Debt Schedule'!$F$12:$F$47,"FY2027",'Debt Schedule'!$G$12:$G$47,"Q4") -> 9.2267352 | K23: =SUMIFS('Debt Schedule'!$T$12:$T$47,'Debt Schedule'!$F$12:$F$47,"FY2028",'Debt Schedule'!$G$12:$G$47,"Q1") -> 8.979196 | L23: =SUMIFS('Debt Schedule'!$T$12:$T$47,'Debt Schedule'!$F$12:$F$47,"FY2028",'Debt Schedule'!$G$12:$G$47,"Q2") -> 8.7840299 | M23: =SUMIFS('Debt Schedule'!$T$12:$T$47,'Debt Schedule'!$F$12:$F$47,"FY2028",'Debt Schedule'!$G$12:$G$47,"Q3") -> 8.5673646 | N23: =SUMIFS('Debt Schedule'!$T$12:$T$47,'Debt Schedule'!$F$12:$F$47,"FY2028",'Debt Schedule'!$G$12:$G$47,"Q4") -> 8.3718044 | O23: =SUMIFS('Debt Schedule'!$T$12:$T$47,'Debt Schedule'!$F$12:$F$47,"FY2029",'Debt Schedule'!$G$12:$G$47,"Q1") -> 7.9803997 | P23: =SUMIFS('Debt Schedule'!$T$12:$T$47,'Debt Schedule'!$F$12:$F$47,"FY2029",'Debt Schedule'!$G$12:$G$47,"Q2") -> 7.7848395 | Q23: =SUMIFS('Debt Schedule'!$T$12:$T$47,'Debt Schedule'!$F$12:$F$47,"FY2029",'Debt Schedule'!$G$12:$G$47,"Q3") -> 7.5892794 | R23: =SUMIFS('Debt Schedule'!$T$12:$T$47,'Debt Schedule'!$F$12:$F$47,"FY2029",'Debt Schedule'!$G$12:$G$47,"Q4") -> 7.3937192 | S23: =SUMIFS('Debt Schedule'!$T$12:$T$47,'Debt Schedule'!$F$12:$F$47,"FY2030",'Debt Schedule'!$G$12:$G$47,"Q1") -> 6.9041563 | T23: =SUMIFS('Debt Schedule'!$T$12:$T$47,'Debt Schedule'!$F$12:$F$47,"FY2030",'Debt Schedule'!$G$12:$G$47,"Q2") -> 6.7085962 | U23: =SUMIFS('Debt Schedule'!$T$12:$T$47,'Debt Schedule'!$F$12:$F$47,"FY2030",'Debt Schedule'!$G$12:$G$47,"Q3") -> 6.513036 | V23: =SUMIFS('Debt Schedule'!$T$12:$T$47,'Debt Schedule'!$F$12:$F$47,"FY2030",'Debt Schedule'!$G$12:$G$47,"Q4") -> 6.3174759 | W23: =SUMIFS('Debt Schedule'!$T$12:$T$47,'Debt Schedule'!$F$12:$F$47,"FY2031",'Debt Schedule'!$G$12:$G$47,"Q1") -> 5.7406148
C24: CFO proxy | D24: =SUM(D14,D18:D19,D21)-D23 -> 42.222523 | E24: =SUM(E14,E18:E19,E21)-E23 -> 43.940903 | F24: =SUM(F14,F18:F19,F21)-F23 -> 44.503149 | G24: =SUM(G14,G18:G19,G21)-G23 -> 19.695241 | H24: =SUM(H14,H18:H19,H21)-H23 -> 43.969182 | I24: =SUM(I14,I18:I19,I21)-I23 -> 44.997693 | J24: =SUM(J14,J18:J19,J21)-J23 -> 45.469339 | K24: =SUM(K14,K18:K19,K21)-K23 -> 20.669293 | ... W24: =SUM(W14,W18:W19,W21)-W23 -> 23.905651
C25: Free cash flow proxy | D25: =D24+D20 -> 26.386188 | E25: =E24+E20 -> 26.606782 | F25: =F24+F20 -> 27.358967 | G25: =G24+G20 -> 5.6944008 | H25: =H24+H20 -> 28.133244 | I25: =I24+I20 -> 27.664005 | J25: =J24+J20 -> 28.325586 | K25: =K24+K20 -> 6.6688031 | ... W25: =W24+W20 -> 9.9062108
C26: Distributions | D26: =SUMIFS(Assumptions!$AK$41:$AK$364,Assumptions!$C$41:$C$364,$D$4,Assumptions!$I$41:$I$364,"FY2026",Assumptions!$J$41:$J$364,"Q2")+SUMIFS(Assumptions!$AL$41:$AL$364,Assumptions!$C$41:$C$364,$D$4,Assumptions!$I$41:$I$364,"FY2026",Assumptions!$J$41:$J$364,"Q2") -> 4.875 | E26: =SUMIFS(Assumptions!$AK$41:$AK$364,Assumptions!$C$41:$C$364,$D$4,Assumptions!$I$41:$I$364,"FY2026",Assumptions!$J$41:$J$364,"Q3")+SUMIFS(Assumptions!$AL$41:$AL$364,Assumptions!$C$41:$C$364,$D$4,Assumptions!$I$41:$I$364,"FY2026",Assumptions!$J$41:$J$364,"Q3") -> 4.875 | F26: =SUMIFS(Assumptions!$AK$41:$AK$364,Assumptions!$C$41:$C$364,$D$4,Assumptions!$I$41:$I$364,"FY2026",Assumptions!$J$41:$J$364,"Q4")+SUMIFS(Assumptions!$AL$41:$AL$364,Assumptions!$C$41:$C$364,$D$4,Assumptions!$I$41:$I$364,"FY2026",Assumptions!$J$41:$J$364,"Q4") -> 4.875 | G26: =SUMIFS(Assumptions!$AK$41:$AK$364,Assumptions!$C$41:$C$364,$D$4,Assumptions!$I$41:$I$364,"FY2027",Assumptions!$J$41:$J$364,"Q1")+SUMIFS(Assumptions!$AL$41:$AL$364,Assumptions!$C$41:$C$364,$D$4,Assumptions!$I$41:$I$364,"FY2027",Assumptions!$J$41:$J$364,"Q1") -> 4.875 | H26: =SUMIFS(Assumptions!$AK$41:$AK$364,Assumptions!$C$41:$C$364,$D$4,Assumptions!$I$41:$I$364,"FY2027",Assumptions!$J$41:$J$364,"Q2")+SUMIFS(Assumptions!$AL$41:$AL$364,Assumptions!$C$41:$C$364,$D$4,Assumptions!$I$41:$I$364,"FY2027",Assumptions!$J$41:$J$364,"Q2") -> 4.875 | I26: =SUMIFS(Assumptions!$AK$41:$AK$364,Assumptions!$C$41:$C$364,$D$4,Assumptions!$I$41:$I$364,"FY2027",Assumptions!$J$41:$J$364,"Q3")+SUMIFS(Assumptions!$AL$41:$AL$364,Assumptions!$C$41:$C$364,$D$4,Assumptions!$I$41:$I$364,"FY2027",Assumptions!$J$41:$J$364,"Q3") -> 4.875 | J26: =SUMIFS(Assumptions!$AK$41:$AK$364,Assumptions!$C$41:$C$364,$D$4,Assumptions!$I$41:$I$364,"FY2027",Assumptions!$J$41:$J$364,"Q4")+SUMIFS(Assumptions!$AL$41:$AL$364,Assumptions!$C$41:$C$364,$D$4,Assumptions!$I$41:$I$364,"FY2027",Assumptions!$J$41:$J$364,"Q4") -> 4.875 | K26: =SUMIFS(Assumptions!$AK$41:$AK$364,Assumptions!$C$41:$C$364,$D$4,Assumptions!$I$41:$I$364,"FY2028",Assumptions!$J$41:$J$364,"Q1")+SUMIFS(Assumptions!$AL$41:$AL$364,Assumptions!$C$41:$C$364,$D$4,Assumptions!$I$41:$I$364,"FY2028",Assumptions!$J$41:$J$364,"Q1") -> 4.875 | L26: =SUMIFS(Assumptions!$AK$41:$AK$364,Assumptions!$C$41:$C$364,$D$4,Assumptions!$I$41:$I$364,"FY2028",Assumptions!$J$41:$J$364,"Q2")+SUMIFS(Assumptions!$AL$41:$AL$364,Assumptions!$C$41:$C$364,$D$4,Assumptions!$I$41:$I$364,"FY2028",Assumptions!$J$41:$J$364,"Q2") -> 4.875 | M26: =SUMIFS(Assumptions!$AK$41:$AK$364,Assumptions!$C$41:$C$364,$D$4,Assumptions!$I$41:$I$364,"FY2028",Assumptions!$J$41:$J$364,"Q3")+SUMIFS(Assumptions!$AL$41:$AL$364,Assumptions!$C$41:$C$364,$D$4,Assumptions!$I$41:$I$364,"FY2028",Assumptions!$J$41:$J$364,"Q3") -> 4.875 | N26: =SUMIFS(Assumptions!$AK$41:$AK$364,Assumptions!$C$41:$C$364,$D$4,Assumptions!$I$41:$I$364,"FY2028",Assumptions!$J$41:$J$364,"Q4")+SUMIFS(Assumptions!$AL$41:$AL$364,Assumptions!$C$41:$C$364,$D$4,Assumptions!$I$41:$I$364,"FY2028",Assumptions!$J$41:$J$364,"Q4") -> 4.875 | O26: =SUMIFS(Assumptions!$AK$41:$AK$364,Assumptions!$C$41:$C$364,$D$4,Assumptions!$I$41:$I$364,"FY2029",Assumptions!$J$41:$J$364,"Q1")+SUMIFS(Assumptions!$AL$41:$AL$364,Assumptions!$C$41:$C$364,$D$4,Assumptions!$I$41:$I$364,"FY2029",Assumptions!$J$41:$J$364,"Q1") -> 4.875 | P26: =SUMIFS(Assumptions!$AK$41:$AK$364,Assumptions!$C$41:$C$364,$D$4,Assumptions!$I$41:$I$364,"FY2029",Assumptions!$J$41:$J$364,"Q2")+SUMIFS(Assumptions!$AL$41:$AL$364,Assumptions!$C$41:$C$364,$D$4,Assumptions!$I$41:$I$364,"FY2029",Assumptions!$J$41:$J$364,"Q2") -> 4.875 | Q26: =SUMIFS(Assumptions!$AK$41:$AK$364,Assumptions!$C$41:$C$364,$D$4,Assumptions!$I$41:$I$364,"FY2029",Assumptions!$J$41:$J$364,"Q3")+SUMIFS(Assumptions!$AL$41:$AL$364,Assumptions!$C$41:$C$364,$D$4,Assumptions!$I$41:$I$364,"FY2029",Assumptions!$J$41:$J$364,"Q3") -> 4.875 | R26: =SUMIFS(Assumptions!$AK$41:$AK$364,Assumptions!$C$41:$C$364,$D$4,Assumptions!$I$41:$I$364,"FY2029",Assumptions!$J$41:$J$364,"Q4")+SUMIFS(Assumptions!$AL$41:$AL$364,Assumptions!$C$41:$C$364,$D$4,Assumptions!$I$41:$I$364,"FY2029",Assumptions!$J$41:$J$364,"Q4") -> 4.875 | S26: =SUMIFS(Assumptions!$AK$41:$AK$364,Assumptions!$C$41:$C$364,$D$4,Assumptions!$I$41:$I$364,"FY2030",Assumptions!$J$41:$J$364,"Q1")+SUMIFS(Assumptions!$AL$41:$AL$364,Assumptions!$C$41:$C$364,$D$4,Assumptions!$I$41:$I$364,"FY2030",Assumptions!$J$41:$J$364,"Q1") -> 4.875 | T26: =SUMIFS(Assumptions!$AK$41:$AK$364,Assumptions!$C$41:$C$364,$D$4,Assumptions!$I$41:$I$364,"FY2030",Assumptions!$J$41:$J$364,"Q2")+SUMIFS(Assumptions!$AL$41:$AL$364,Assumptions!$C$41:$C$364,$D$4,Assumptions!$I$41:$I$364,"FY2030",Assumptions!$J$41:$J$364,"Q2") -> 4.875 | U26: =SUMIFS(Assumptions!$AK$41:$AK$364,Assumptions!$C$41:$C$364,$D$4,Assumptions!$I$41:$I$364,"FY2030",Assumptions!$J$41:$J$364,"Q3")+SUMIFS(Assumptions!$AL$41:$AL$364,Assumptions!$C$41:$C$364,$D$4,Assumptions!$I$41:$I$364,"FY2030",Assumptions!$J$41:$J$364,"Q3") -> 4.875 | V26: =SUMIFS(Assumptions!$AK$41:$AK$364,Assumptions!$C$41:$C$364,$D$4,Assumptions!$I$41:$I$364,"FY2030",Assumptions!$J$41:$J$364,"Q4")+SUMIFS(Assumptions!$AL$41:$AL$364,Assumptions!$C$41:$C$364,$D$4,Assumptions!$I$41:$I$364,"FY2030",Assumptions!$J$41:$J$364,"Q4") -> 4.875 | W26: =SUMIFS(Assumptions!$AK$41:$AK$364,Assumptions!$C$41:$C$364,$D$4,Assumptions!$I$41:$I$364,"FY2031",Assumptions!$J$41:$J$364,"Q1")+SUMIFS(Assumptions!$AL$41:$AL$364,Assumptions!$C$41:$C$364,$D$4,Assumptions!$I$41:$I$364,"FY2031",Assumptions!$J$41:$J$364,"Q1") -> 4.875
C27: Cash available before financing | D27: =D22-D23-D26 -> 21.511188 | E27: =E22-E23-E26 -> 21.731782 | F27: =F22-F23-F26 -> 22.483967 | G27: =G22-G23-G26 -> 0.81940083 | H27: =H22-H23-H26 -> 23.258244 | I27: =I22-I23-I26 -> 22.789005 | J27: =J22-J23-J26 -> 23.450586 | K27: =K22-K23-K26 -> 1.7938031 | ... W27: =W22-W23-W26 -> 5.0312108
C28: Source IDs | D28: ="SRC-001;SRC-002;SRC-003" -> SRC-001;SRC-002;SRC-003 | E28: ="SRC-001;SRC-002;SRC-003" -> SRC-001;SRC-002;SRC-003 | F28: ="SRC-001;SRC-002;SRC-003" -> SRC-001;SRC-002;SRC-003 | G28: ="SRC-001;SRC-002;SRC-003" -> SRC-001;SRC-002;SRC-003 | H28: ="SRC-001;SRC-002;SRC-003" -> SRC-001;SRC-002;SRC-003 | I28: ="SRC-001;SRC-002;SRC-003" -> SRC-001;SRC-002;SRC-003 | J28: ="SRC-001;SRC-002;SRC-003" -> SRC-001;SRC-002;SRC-003 | K28: ="SRC-001;SRC-002;SRC-003" -> SRC-001;SRC-002;SRC-003 | ... W28: ="SRC-001;SRC-002;SRC-003" -> SRC-001;SRC-002;SRC-003

Sheet Debt Schedule
C2: Debt schedule: 24 monthly periods, then quarterly
C4: Case selected: | D4: =Assumptions!$D$4 -> Base
C7: Period ID | D7: Period end | E7: Frequency | F7: Fiscal year | G7: Quarter | H7: Days | I7: CFADS | J7: Opening term | K7: Scheduled principal | L7: ECF sweep | M7: Maturity principal paid | N7: Ending term | O7: Opening revolver | P7: Revolver draw | Q7: Revolver repayment | R7: Ending revolver | S7: Average bank debt | T7: Cash interest | U7: Retained debt payment | V7: Distributions | W7: Ending cash | X7: Total bank debt | Y7: Retained other debt | Z7: Total funded debt | AA7: Revolver availability | AB7: Usable liquidity | AC7: Unpaid obligations | AD7: Drawability
C9: Approved Phase 7 paths with live term, contribution, amortization, rate, EBITDA, DSO and liquidity controls.
C12: P001 | D12: 46081 | E12: monthly | F12: FY2026 | G12: Q2 | H12: 28 | I12: =SUMIFS(Assumptions!$T$41:$T$364,Assumptions!$C$41:$C$364,$D$4,Assumptions!$E$41:$E$364,$C12)+(Assumptions!$D$25+IF($C12="P001",-SUMIFS(Assumptions!$L$41:$L$364,Assumptions!$C$41:$C$364,$D$4,Assumptions!$E$41:$E$364,$C12)/365*Assumptions!$D$23,0)) -> 12.382669 | J12: =Assumptions!$D$12 -> 635 | K12: =SUMIFS(Assumptions!$Y$41:$Y$364,Assumptions!$C$41:$C$364,$D$4,Assumptions!$E$41:$E$364,$C12)*(Assumptions!$D$12/635)*(Assumptions!$D$18/7.5%) -> 0 | L12: =SUMIFS(Assumptions!$Z$41:$Z$364,Assumptions!$C$41:$C$364,$D$4,Assumptions!$E$41:$E$364,$C12)*(Assumptions!$D$26/50%)*IF(SUMIFS(Assumptions!$AO$41:$AO$364,Assumptions!$C$41:$C$364,$D$4,Assumptions!$E$41:$E$364,$C12)>Assumptions!$D$24,1,0) -> 0 | M12: =SUMIFS(Assumptions!$AB$41:$AB$364,Assumptions!$C$41:$C$364,$D$4,Assumptions!$E$41:$E$364,$C12) -> 0 | N12: =MAX(0,J12-K12-L12-M12) -> 635 | O12: =Assumptions!$D$15 -> 29.897719 | P12: =SUMIFS(Assumptions!$AE$41:$AE$364,Assumptions!$C$41:$C$364,$D$4,Assumptions!$E$41:$E$364,$C12)+IF((Assumptions!$D$25+IF($C12="P001",-SUMIFS(Assumptions!$L$41:$L$364,Assumptions!$C$41:$C$364,$D$4,Assumptions!$E$41:$E$364,$C12)/365*Assumptions!$D$23,0))<0,MIN(MAX(0,Assumptions!$D$14-Assumptions!$D$16-O12),-(Assumptions!$D$25+IF($C12="P001",-SUMIFS(Assumptions!$L$41:$L$364,Assumptions!$C$41:$C$364,$D$4,Assumptions!$E$41:$E$364,$C12)/365*Assumptions!$D$23,0))),0) -> 0 | Q12: =SUMIFS(Assumptions!$AF$41:$AF$364,Assumptions!$C$41:$C$364,$D$4,Assumptions!$E$41:$E$364,$C12)+IF((Assumptions!$D$25+IF($C12="P001",-SUMIFS(Assumptions!$L$41:$L$364,Assumptions!$C$41:$C$364,$D$4,Assumptions!$E$41:$E$364,$C12)/365*Assumptions!$D$23,0))>0,MIN(O12,(Assumptions!$D$25+IF($C12="P001",-SUMIFS(Assumptions!$L$41:$L$364,Assumptions!$C$41:$C$364,$D$4,Assumptions!$E$41:$E$364,$C12)/365*Assumptions!$D$23,0))),0) -> 6.4390641 | R12: =MAX(0,O12+P12-Q12) -> 23.458655 | S12: =(J12+N12+O12+R12)/2 -> 661.67819 | T12: =IF(Assumptions!$D$19="","",IF(((SUMIFS(Assumptions!$W$41:$W$364,Assumptions!$C$41:$C$364,$D$4,Assumptions!$E$41:$E$364,$C12)+SUMIFS(Assumptions!$AC$41:$AC$364,Assumptions!$C$41:$C$364,$D$4,Assumptions!$E$41:$E$364,$C12)+SUMIFS(Assumptions!$AD$41:$AD$364,Assumptions!$C$41:$C$364,$D$4,Assumptions!$E$41:$E$364,$C12)+SUMIFS(Assumptions!$AG$41:$AG$364,Assumptions!$C$41:$C$364,$D$4,Assumptions!$E$41:$E$364,$C12))/2)=0,0,SUMIFS(Assumptions!$AI$41:$AI$364,Assumptions!$C$41:$C$364,$D$4,Assumptions!$E$41:$E$364,$C12)*S12/((SUMIFS(Assumptions!$W$41:$W$364,Assumptions!$C$41:$C$364,$D$4,Assumptions!$E$41:$E$364,$C12)+SUMIFS(Assumptions!$AC$41:$AC$364,Assumptions!$C$41:$C$364,$D$4,Assumptions!$E$41:$E$364,$C12)+SUMIFS(Assumptions!$AD$41:$AD$364,Assumptions!$C$41:$C$364,$D$4,Assumptions!$E$41:$E$364,$C12)+SUMIFS(Assumptions!$AG$41:$AG$364,Assumptions!$C$41:$C$364,$D$4,Assumptions!$E$41:$E$364,$C12))/2)*(Assumptions!$D$19/6.57%))+Assumptions!$D$20*S12*H12/365) -> 3.6226881 | U12: =SUMIFS(Assumptions!$AJ$41:$AJ$364,Assumptions!$C$41:$C$364,$D$4,Assumptions!$E$41:$E$364,$C12) -> 0.69591667 | V12: =SUMIFS(Assumptions!$AK$41:$AK$364,Assumptions!$C$41:$C$364,$D$4,Assumptions!$E$41:$E$364,$C12)+SUMIFS(Assumptions!$AL$41:$AL$364,Assumptions!$C$41:$C$364,$D$4,Assumptions!$E$41:$E$364,$C12) -> 1.625 | W12: =SUMIFS(Assumptions!$U$41:$U$364,Assumptions!$C$41:$C$364,$D$4,Assumptions!$E$41:$E$364,$C12)+(SUMIFS(Assumptions!$V$41:$V$364,Assumptions!$C$41:$C$364,$D$4,Assumptions!$E$41:$E$364,$C12)-SUMIFS(Assumptions!$U$41:$U$364,Assumptions!$C$41:$C$364,$D$4,Assumptions!$E$41:$E$364,$C12))+(Assumptions!$D$25+IF($C12="P001",-SUMIFS(Assumptions!$L$41:$L$364,Assumptions!$C$41:$C$364,$D$4,Assumptions!$E$41:$E$364,$C12)/365*Assumptions!$D$23,0))+(IF((Assumptions!$D$25+IF($C12="P001",-SUMIFS(Assumptions!$L$41:$L$364,Assumptions!$C$41:$C$364,$D$4,Assumptions!$E$41:$E$364,$C12)/365*Assumptions!$D$23,0))<0,MIN(MAX(0,Assumptions!$D$14-Assumptions!$D$16-O12),-(Assumptions!$D$25+IF($C12="P001",-SUMIFS(Assumptions!$L$41:$L$364,Assumptions!$C$41:$C$364,$D$4,Assumptions!$E$41:$E$364,$C12)/365*Assumptions!$D$23,0))),0))-(IF((Assumptions!$D$25+IF($C12="P001",-SUMIFS(Assumptions!$L$41:$L$364,Assumptions!$C$41:$C$364,$D$4,Assumptions!$E$41:$E$364,$C12)/365*Assumptions!$D$23,0))>0,MIN(O12,(Assumptions!$D$25+IF($C12="P001",-SUMIFS(Assumptions!$L$41:$L$364,Assumptions!$C$41:$C$364,$D$4,Assumptions!$E$41:$E$364,$C12)/365*Assumptions!$D$23,0))),0)) -> 25 | X12: =N12+R12 -> 658.45865 | Y12: =Assumptions!$D$17 -> 62.619 | Z12: =X12+Y12 -> 721.07765 | AA12: =MAX(0,Assumptions!$D$14-Assumptions!$D$16-R12) -> 270.34135 | AB12: =MAX(0,W12-Assumptions!$D$24)+AA12 -> 270.34135 | AC12: =SUMIFS(Assumptions!$AM$41:$AM$364,Assumptions!$C$41:$C$364,$D$4,Assumptions!$E$41:$E$364,$C12)+MAX(0,-W12) -> 0 | AD12: =IF(COUNTIFS(Assumptions!$C$41:$C$364,$D$4,Assumptions!$E$41:$E$364,$C12,Assumptions!$AR$41:$AR$364,"*shutoff_active*")>0,"SHUTOFF","AVAILABLE") -> AVAILABLE
C13: P002 | D13: 46112 | E13: monthly | F13: FY2026 | G13: Q2 | H13: 31 | I13: =SUMIFS(Assumptions!$T$41:$T$364,Assumptions!$C$41:$C$364,$D$4,Assumptions!$E$41:$E$364,$C13)+(Assumptions!$D$25+IF($C13="P001",-SUMIFS(Assumptions!$L$41:$L$364,Assumptions!$C$41:$C$364,$D$4,Assumptions!$E$41:$E$364,$C13)/365*Assumptions!$D$23,0)) -> 12.382669 | J13: =N12 -> 635 | K13: =SUMIFS(Assumptions!$Y$41:$Y$364,Assumptions!$C$41:$C$364,$D$4,Assumptions!$E$41:$E$364,$C13)*(Assumptions!$D$12/635)*(Assumptions!$D$18/7.5%) -> 0 | L13: =SUMIFS(Assumptions!$Z$41:$Z$364,Assumptions!$C$41:$C$364,$D$4,Assumptions!$E$41:$E$364,$C13)*(Assumptions!$D$26/50%)*IF(SUMIFS(Assumptions!$AO$41:$AO$364,Assumptions!$C$41:$C$364,$D$4,Assumptions!$E$41:$E$364,$C13)>Assumptions!$D$24,1,0) -> 0 | M13: =SUMIFS(Assumptions!$AB$41:$AB$364,Assumptions!$C$41:$C$364,$D$4,Assumptions!$E$41:$E$364,$C13) -> 0 | N13: =MAX(0,J13-K13-L13-M13) -> 635 | O13: =R12 -> 23.458655 | P13: =SUMIFS(Assumptions!$AE$41:$AE$364,Assumptions!$C$41:$C$364,$D$4,Assumptions!$E$41:$E$364,$C13)+IF((Assumptions!$D$25+IF($C13="P001",-SUMIFS(Assumptions!$L$41:$L$364,Assumptions!$C$41:$C$364,$D$4,Assumptions!$E$41:$E$364,$C13)/365*Assumptions!$D$23,0))<0,MIN(MAX(0,Assumptions!$D$14-Assumptions!$D$16-O13),-(Assumptions!$D$25+IF($C13="P001",-SUMIFS(Assumptions!$L$41:$L$364,Assumptions!$C$41:$C$364,$D$4,Assumptions!$E$41:$E$364,$C13)/365*Assumptions!$D$23,0))),0) -> 0 | Q13: =SUMIFS(Assumptions!$AF$41:$AF$364,Assumptions!$C$41:$C$364,$D$4,Assumptions!$E$41:$E$364,$C13)+IF((Assumptions!$D$25+IF($C13="P001",-SUMIFS(Assumptions!$L$41:$L$364,Assumptions!$C$41:$C$364,$D$4,Assumptions!$E$41:$E$364,$C13)/365*Assumptions!$D$23,0))>0,MIN(O13,(Assumptions!$D$25+IF($C13="P001",-SUMIFS(Assumptions!$L$41:$L$364,Assumptions!$C$41:$C$364,$D$4,Assumptions!$E$41:$E$364,$C13)/365*Assumptions!$D$23,0))),0) -> 6.4744148 | R13: =MAX(0,O13+P13-Q13) -> 16.98424 | S13: =(J13+N13+O13+R13)/2 -> 655.22145 | T13: =IF(Assumptions!$D$19="","",IF(((SUMIFS(Assumptions!$W$41:$W$364,Assumptions!$C$41:$C$364,$D$4,Assumptions!$E$41:$E$364,$C13)+SUMIFS(Assumptions!$AC$41:$AC$364,Assumptions!$C$41:$C$364,$D$4,Assumptions!$E$41:$E$364,$C13)+SUMIFS(Assumptions!$AD$41:$AD$364,Assumptions!$C$41:$C$364,$D$4,Assumptions!$E$41:$E$364,$C13)+SUMIFS(Assumptions!$AG$41:$AG$364,Assumptions!$C$41:$C$364,$D$4,Assumptions!$E$41:$E$364,$C13))/2)=0,0,SUMIFS(Assumptions!$AI$41:$AI$364,Assumptions!$C$41:$C$364,$D$4,Assumptions!$E$41:$E$364,$C13)*S13/((SUMIFS(Assumptions!$W$41:$W$364,Assumptions!$C$41:$C$364,$D$4,Assumptions!$E$41:$E$364,$C13)+SUMIFS(Assumptions!$AC$41:$AC$364,Assumptions!$C$41:$C$364,$D$4,Assumptions!$E$41:$E$364,$C13)+SUMIFS(Assumptions!$AD$41:$AD$364,Assumptions!$C$41:$C$364,$D$4,Assumptions!$E$41:$E$364,$C13)+SUMIFS(Assumptions!$AG$41:$AG$364,Assumptions!$C$41:$C$364,$D$4,Assumptions!$E$41:$E$364,$C13))/2)*(Assumptions!$D$19/6.57%))+Assumptions!$D$20*S13*H13/365) -> 3.5873374 | U13: =SUMIFS(Assumptions!$AJ$41:$AJ$364,Assumptions!$C$41:$C$364,$D$4,Assumptions!$E$41:$E$364,$C13) -> 0.69591667 | V13: =SUMIFS(Assumptions!$AK$41:$AK$364,Assumptions!$C$41:$C$364,$D$4,Assumptions!$E$41:$E$364,$C13)+SUMIFS(Assumptions!$AL$41:$AL$364,Assumptions!$C$41:$C$364,$D$4,Assumptions!$E$41:$E$364,$C13) -> 1.625 | W13: =W12+(SUMIFS(Assumptions!$V$41:$V$364,Assumptions!$C$41:$C$364,$D$4,Assumptions!$E$41:$E$364,$C13)-SUMIFS(Assumptions!$U$41:$U$364,Assumptions!$C$41:$C$364,$D$4,Assumptions!$E$41:$E$364,$C13))+(Assumptions!$D$25+IF($C13="P001",-SUMIFS(Assumptions!$L$41:$L$364,Assumptions!$C$41:$C$364,$D$4,Assumptions!$E$41:$E$364,$C13)/365*Assumptions!$D$23,0))+(IF((Assumptions!$D$25+IF($C13="P001",-SUMIFS(Assumptions!$L$41:$L$364,Assumptions!$C$41:$C$364,$D$4,Assumptions!$E$41:$E$364,$C13)/365*Assumptions!$D$23,0))<0,MIN(MAX(0,Assumptions!$D$14-Assumptions!$D$16-O13),-(Assumptions!$D$25+IF($C13="P001",-SUMIFS(Assumptions!$L$41:$L$364,Assumptions!$C$41:$C$364,$D$4,Assumptions!$E$41:$E$364,$C13)/365*Assumptions!$D$23,0))),0))-(IF((Assumptions!$D$25+IF($C13="P001",-SUMIFS(Assumptions!$L$41:$L$364,Assumptions!$C$41:$C$364,$D$4,Assumptions!$E$41:$E$364,$C13)/365*Assumptions!$D$23,0))>0,MIN(O13,(Assumptions!$D$25+IF($C13="P001",-SUMIFS(Assumptions!$L$41:$L$364,Assumptions!$C$41:$C$364,$D$4,Assumptions!$E$41:$E$364,$C13)/365*Assumptions!$D$23,0))),0)) -> 25 | X13: =N13+R13 -> 651.98424 | Y13: =Assumptions!$D$17 -> 62.619 | Z13: =X13+Y13 -> 714.60324 | AA13: =MAX(0,Assumptions!$D$14-Assumptions!$D$16-R13) -> 276.81576 | AB13: =MAX(0,W13-Assumptions!$D$24)+AA13 -> 276.81576 | AC13: =SUMIFS(Assumptions!$AM$41:$AM$364,Assumptions!$C$41:$C$364,$D$4,Assumptions!$E$41:$E$364,$C13)+MAX(0,-W13) -> 0 | AD13: =IF(COUNTIFS(Assumptions!$C$41:$C$364,$D$4,Assumptions!$E$41:$E$364,$C13,Assumptions!$AR$41:$AR$364,"*shutoff_active*")>0,"SHUTOFF","AVAILABLE") -> AVAILABLE
C14: P003 | D14: 46142 | E14: monthly | F14: FY2026 | G14: Q2 | H14: 30 | I14: =SUMIFS(Assumptions!$T$41:$T$364,Assumptions!$C$41:$C$364,$D$4,Assumptions!$E$41:$E$364,$C14)+(Assumptions!$D$25+IF($C14="P001",-SUMIFS(Assumptions!$L$41:$L$364,Assumptions!$C$41:$C$364,$D$4,Assumptions!$E$41:$E$364,$C14)/365*Assumptions!$D$23,0)) -> 12.382669 | J14: =N13 -> 635 | K14: =SUMIFS(Assumptions!$Y$41:$Y$364,Assumptions!$C$41:$C$364,$D$4,Assumptions!$E$41:$E$364,$C14)*(Assumptions!$D$12/635)*(Assumptions!$D$18/7.5%) -> 11.90625 | L14: =SUMIFS(Assumptions!$Z$41:$Z$364,Assumptions!$C$41:$C$364,$D$4,Assumptions!$E$41:$E$364,$C14)*(Assumptions!$D$26/50%)*IF(SUMIFS(Assumptions!$AO$41:$AO$364,Assumptions!$C$41:$C$364,$D$4,Assumptions!$E$41:$E$364,$C14)>Assumptions!$D$24,1,0) -> 0 | M14: =SUMIFS(Assumptions!$AB$41:$AB$364,Assumptions!$C$41:$C$364,$D$4,Assumptions!$E$41:$E$364,$C14) -> 0 | N14: =MAX(0,J14-K14-L14-M14) -> 623.09375 | O14: =R13 -> 16.98424 | P14: =SUMIFS(Assumptions!$AE$41:$AE$364,Assumptions!$C$41:$C$364,$D$4,Assumptions!$E$41:$E$364,$C14)+IF((Assumptions!$D$25+IF($C14="P001",-SUMIFS(Assumptions!$L$41:$L$364,Assumptions!$C$41:$C$364,$D$4,Assumptions!$E$41:$E$364,$C14)/365*Assumptions!$D$23,0))<0,MIN(MAX(0,Assumptions!$D$14-Assumptions!$D$16-O14),-(Assumptions!$D$25+IF($C14="P001",-SUMIFS(Assumptions!$L$41:$L$364,Assumptions!$C$41:$C$364,$D$4,Assumptions!$E$41:$E$364,$C14)/365*Assumptions!$D$23,0))),0) -> 5.3962905 | Q14: =SUMIFS(Assumptions!$AF$41:$AF$364,Assumptions!$C$41:$C$364,$D$4,Assumptions!$E$41:$E$364,$C14)+IF((Assumptions!$D$25+IF($C14="P001",-SUMIFS(Assumptions!$L$41:$L$364,Assumptions!$C$41:$C$364,$D$4,Assumptions!$E$41:$E$364,$C14)/365*Assumptions!$D$23,0))>0,MIN(O14,(Assumptions!$D$25+IF($C14="P001",-SUMIFS(Assumptions!$L$41:$L$364,Assumptions!$C$41:$C$364,$D$4,Assumptions!$E$41:$E$364,$C14)/365*Assumptions!$D$23,0))),0) -> 0 | R14: =MAX(0,O14+P14-Q14) -> 22.38053 | S14: =(J14+N14+O14+R14)/2 -> 648.72926 | T14: =IF(Assumptions!$D$19="","",IF(((SUMIFS(Assumptions!$W$41:$W$364,Assumptions!$C$41:$C$364,$D$4,Assumptions!$E$41:$E$364,$C14)+SUMIFS(Assumptions!$AC$41:$AC$364,Assumptions!$C$41:$C$364,$D$4,Assumptions!$E$41:$E$364,$C14)+SUMIFS(Assumptions!$AD$41:$AD$364,Assumptions!$C$41:$C$364,$D$4,Assumptions!$E$41:$E$364,$C14)+SUMIFS(Assumptions!$AG$41:$AG$364,Assumptions!$C$41:$C$364,$D$4,Assumptions!$E$41:$E$364,$C14))/2)=0,0,SUMIFS(Assumptions!$AI$41:$AI$364,Assumptions!$C$41:$C$364,$D$4,Assumptions!$E$41:$E$364,$C14)*S14/((SUMIFS(Assumptions!$W$41:$W$364,Assumptions!$C$41:$C$364,$D$4,Assumptions!$E$41:$E$364,$C14)+SUMIFS(Assumptions!$AC$41:$AC$364,Assumptions!$C$41:$C$364,$D$4,Assumptions!$E$41:$E$364,$C14)+SUMIFS(Assumptions!$AD$41:$AD$364,Assumptions!$C$41:$C$364,$D$4,Assumptions!$E$41:$E$364,$C14)+SUMIFS(Assumptions!$AG$41:$AG$364,Assumptions!$C$41:$C$364,$D$4,Assumptions!$E$41:$E$364,$C14))/2)*(Assumptions!$D$19/6.57%))+Assumptions!$D$20*S14*H14/365) -> 3.5517927 | U14: =SUMIFS(Assumptions!$AJ$41:$AJ$364,Assumptions!$C$41:$C$364,$D$4,Assumptions!$E$41:$E$364,$C14) -> 0.69591667 | V14: =SUMIFS(Assumptions!$AK$41:$AK$364,Assumptions!$C$41:$C$364,$D$4,Assumptions!$E$41:$E$364,$C14)+SUMIFS(Assumptions!$AL$41:$AL$364,Assumptions!$C$41:$C$364,$D$4,Assumptions!$E$41:$E$364,$C14) -> 1.625 | W14: =W13+(SUMIFS(Assumptions!$V$41:$V$364,Assumptions!$C$41:$C$364,$D$4,Assumptions!$E$41:$E$364,$C14)-SUMIFS(Assumptions!$U$41:$U$364,Assumptions!$C$41:$C$364,$D$4,Assumptions!$E$41:$E$364,$C14))+(Assumptions!$D$25+IF($C14="P001",-SUMIFS(Assumptions!$L$41:$L$364,Assumptions!$C$41:$C$364,$D$4,Assumptions!$E$41:$E$364,$C14)/365*Assumptions!$D$23,0))+(IF((Assumptions!$D$25+IF($C14="P001",-SUMIFS(Assumptions!$L$41:$L$364,Assumptions!$C$41:$C$364,$D$4,Assumptions!$E$41:$E$364,$C14)/365*Assumptions!$D$23,0))<0,MIN(MAX(0,Assumptions!$D$14-Assumptions!$D$16-O14),-(Assumptions!$D$25+IF($C14="P001",-SUMIFS(Assumptions!$L$41:$L$364,Assumptions!$C$41:$C$364,$D$4,Assumptions!$E$41:$E$364,$C14)/365*Assumptions!$D$23,0))),0))-(IF((Assumptions!$D$25+IF($C14="P001",-SUMIFS(Assumptions!$L$41:$L$364,Assumptions!$C$41:$C$364,$D$4,Assumptions!$E$41:$E$364,$C14)/365*Assumptions!$D$23,0))>0,MIN(O14,(Assumptions!$D$25+IF($C14="P001",-SUMIFS(Assumptions!$L$41:$L$364,Assumptions!$C$41:$C$364,$D$4,Assumptions!$E$41:$E$364,$C14)/365*Assumptions!$D$23,0))),0)) -> 25 | X14: =N14+R14 -> 645.47428 | Y14: =Assumptions!$D$17 -> 62.619 | Z14: =X14+Y14 -> 708.09328 | AA14: =MAX(0,Assumptions!$D$14-Assumptions!$D$16-R14) -> 271.41947 | AB14: =MAX(0,W14-Assumptions!$D$24)+AA14 -> 271.41947 | AC14: =SUMIFS(Assumptions!$AM$41:$AM$364,Assumptions!$C$41:$C$364,$D$4,Assumptions!$E$41:$E$364,$C14)+MAX(0,-W14) -> 0 | AD14: =IF(COUNTIFS(Assumptions!$C$41:$C$364,$D$4,Assumptions!$E$41:$E$364,$C14,Assumptions!$AR$41:$AR$364,"*shutoff_active*")>0,"SHUTOFF","AVAILABLE") -> AVAILABLE
C15: P004 | D15: 46173 | E15: monthly | F15: FY2026 | G15: Q3 | H15: 31 | I15: =SUMIFS(Assumptions!$T$41:$T$364,Assumptions!$C$41:$C$364,$D$4,Assumptions!$E$41:$E$364,$C15)+(Assumptions!$D$25+IF($C15="P001",-SUMIFS(Assumptions!$L$41:$L$364,Assumptions!$C$41:$C$364,$D$4,Assumptions!$E$41:$E$364,$C15)/365*Assumptions!$D$23,0)) -> 12.349254 | J15: =N14 -> 623.09375 | K15: =SUMIFS(Assumptions!$Y$41:$Y$364,Assumptions!$C$41:$C$364,$D$4,Assumptions!$E$41:$E$364,$C15)*(Assumptions!$D$12/635)*(Assumptions!$D$18/7.5%) -> 0 | L15: =SUMIFS(Assumptions!$Z$41:$Z$364,Assumptions!$C$41:$C$364,$D$4,Assumptions!$E$41:$E$364,$C15)*(Assumptions!$D$26/50%)*IF(SUMIFS(Assumptions!$AO$41:$AO$364,Assumptions!$C$41:$C$364,$D$4,Assumptions!$E$41:$E$364,$C15)>Assumptions!$D$24,1,0) -> 0 | M15: =SUMIFS(Assumptions!$AB$41:$AB$364,Assumptions!$C$41:$C$364,$D$4,Assumptions!$E$41:$E$364,$C15) -> 0 | N15: =MAX(0,J15-K15-L15-M15) -> 623.09375 | O15: =R14 -> 22.38053 | P15: =SUMIFS(Assumptions!$AE$41:$AE$364,Assumptions!$C$41:$C$364,$D$4,Assumptions!$E$41:$E$364,$C15)+IF((Assumptions!$D$25+IF($C15="P001",-SUMIFS(Assumptions!$L$41:$L$364,Assumptions!$C$41:$C$364,$D$4,Assumptions!$E$41:$E$364,$C15)/365*Assumptions!$D$23,0))<0,MIN(MAX(0,Assumptions!$D$14-Assumptions!$D$16-O15),-(Assumptions!$D$25+IF($C15="P001",-SUMIFS(Assumptions!$L$41:$L$364,Assumptions!$C$41:$C$364,$D$4,Assumptions!$E$41:$E$364,$C15)/365*Assumptions!$D$23,0))),0) -> 0 | Q15: =SUMIFS(Assumptions!$AF$41:$AF$364,Assumptions!$C$41:$C$364,$D$4,Assumptions!$E$41:$E$364,$C15)+IF((Assumptions!$D$25+IF($C15="P001",-SUMIFS(Assumptions!$L$41:$L$364,Assumptions!$C$41:$C$364,$D$4,Assumptions!$E$41:$E$364,$C15)/365*Assumptions!$D$23,0))>0,MIN(O15,(Assumptions!$D$25+IF($C15="P001",-SUMIFS(Assumptions!$L$41:$L$364,Assumptions!$C$41:$C$364,$D$4,Assumptions!$E$41:$E$364,$C15)/365*Assumptions!$D$23,0))),0) -> 6.512193 | R15: =MAX(0,O15+P15-Q15) -> 15.868337 | S15: =(J15+N15+O15+R15)/2 -> 642.21818 | T15: =IF(Assumptions!$D$19="","",IF(((SUMIFS(Assumptions!$W$41:$W$364,Assumptions!$C$41:$C$364,$D$4,Assumptions!$E$41:$E$364,$C15)+SUMIFS(Assumptions!$AC$41:$AC$364,Assumptions!$C$41:$C$364,$D$4,Assumptions!$E$41:$E$364,$C15)+SUMIFS(Assumptions!$AD$41:$AD$364,Assumptions!$C$41:$C$364,$D$4,Assumptions!$E$41:$E$364,$C15)+SUMIFS(Assumptions!$AG$41:$AG$364,Assumptions!$C$41:$C$364,$D$4,Assumptions!$E$41:$E$364,$C15))/2)=0,0,SUMIFS(Assumptions!$AI$41:$AI$364,Assumptions!$C$41:$C$364,$D$4,Assumptions!$E$41:$E$364,$C15)*S15/((SUMIFS(Assumptions!$W$41:$W$364,Assumptions!$C$41:$C$364,$D$4,Assumptions!$E$41:$E$364,$C15)+SUMIFS(Assumptions!$AC$41:$AC$364,Assumptions!$C$41:$C$364,$D$4,Assumptions!$E$41:$E$364,$C15)+SUMIFS(Assumptions!$AD$41:$AD$364,Assumptions!$C$41:$C$364,$D$4,Assumptions!$E$41:$E$364,$C15)+SUMIFS(Assumptions!$AG$41:$AG$364,Assumptions!$C$41:$C$364,$D$4,Assumptions!$E$41:$E$364,$C15))/2)*(Assumptions!$D$19/6.57%))+Assumptions!$D$20*S15*H15/365) -> 3.5161446 | U15: =SUMIFS(Assumptions!$AJ$41:$AJ$364,Assumptions!$C$41:$C$364,$D$4,Assumptions!$E$41:$E$364,$C15) -> 0.69591667 | V15: =SUMIFS(Assumptions!$AK$41:$AK$364,Assumptions!$C$41:$C$364,$D$4,Assumptions!$E$41:$E$364,$C15)+SUMIFS(Assumptions!$AL$41:$AL$364,Assumptions!$C$41:$C$364,$D$4,Assumptions!$E$41:$E$364,$C15) -> 1.625 | W15: =W14+(SUMIFS(Assumptions!$V$41:$V$364,Assumptions!$C$41:$C$364,$D$4,Assumptions!$E$41:$E$364,$C15)-SUMIFS(Assumptions!$U$41:$U$364,Assumptions!$C$41:$C$364,$D$4,Assumptions!$E$41:$E$364,$C15))+(Assumptions!$D$25+IF($C15="P001",-SUMIFS(Assumptions!$L$41:$L$364,Assumptions!$C$41:$C$364,$D$4,Assumptions!$E$41:$E$364,$C15)/365*Assumptions!$D$23,0))+(IF((Assumptions!$D$25+IF($C15="P001",-SUMIFS(Assumptions!$L$41:$L$364,Assumptions!$C$41:$C$364,$D$4,Assumptions!$E$41:$E$364,$C15)/365*Assumptions!$D$23,0))<0,MIN(MAX(0,Assumptions!$D$14-Assumptions!$D$16-O15),-(Assumptions!$D$25+IF($C15="P001",-SUMIFS(Assumptions!$L$41:$L$364,Assumptions!$C$41:$C$364,$D$4,Assumptions!$E$41:$E$364,$C15)/365*Assumptions!$D$23,0))),0))-(IF((Assumptions!$D$25+IF($C15="P001",-SUMIFS(Assumptions!$L$41:$L$364,Assumptions!$C$41:$C$364,$D$4,Assumptions!$E$41:$E$364,$C15)/365*Assumptions!$D$23,0))>0,MIN(O15,(Assumptions!$D$25+IF($C15="P001",-SUMIFS(Assumptions!$L$41:$L$364,Assumptions!$C$41:$C$364,$D$4,Assumptions!$E$41:$E$364,$C15)/365*Assumptions!$D$23,0))),0)) -> 25 | X15: =N15+R15 -> 638.96209 | Y15: =Assumptions!$D$17 -> 62.619 | Z15: =X15+Y15 -> 701.58109 | AA15: =MAX(0,Assumptions!$D$14-Assumptions!$D$16-R15) -> 277.93166 | AB15: =MAX(0,W15-Assumptions!$D$24)+AA15 -> 277.93166 | AC15: =SUMIFS(Assumptions!$AM$41:$AM$364,Assumptions!$C$41:$C$364,$D$4,Assumptions!$E$41:$E$364,$C15)+MAX(0,-W15) -> 0 | AD15: =IF(COUNTIFS(Assumptions!$C$41:$C$364,$D$4,Assumptions!$E$41:$E$364,$C15,Assumptions!$AR$41:$AR$364,"*shutoff_active*")>0,"SHUTOFF","AVAILABLE") -> AVAILABLE
C16: P005 | D16: 46203 | E16: monthly | F16: FY2026 | G16: Q3 | H16: 30 | I16: =SUMIFS(Assumptions!$T$41:$T$364,Assumptions!$C$41:$C$364,$D$4,Assumptions!$E$41:$E$364,$C16)+(Assumptions!$D$25+IF($C16="P001",-SUMIFS(Assumptions!$L$41:$L$364,Assumptions!$C$41:$C$364,$D$4,Assumptions!$E$41:$E$364,$C16)/365*Assumptions!$D$23,0)) -> 12.349254 | J16: =N15 -> 623.09375 | K16: =SUMIFS(Assumptions!$Y$41:$Y$364,Assumptions!$C$41:$C$364,$D$4,Assumptions!$E$41:$E$364,$C16)*(Assumptions!$D$12/635)*(Assumptions!$D$18/7.5%) -> 0 | L16: =SUMIFS(Assumptions!$Z$41:$Z$364,Assumptions!$C$41:$C$364,$D$4,Assumptions!$E$41:$E$364,$C16)*(Assumptions!$D$26/50%)*IF(SUMIFS(Assumptions!$AO$41:$AO$364,Assumptions!$C$41:$C$364,$D$4,Assumptions!$E$41:$E$364,$C16)>Assumptions!$D$24,1,0) -> 0 | M16: =SUMIFS(Assumptions!$AB$41:$AB$364,Assumptions!$C$41:$C$364,$D$4,Assumptions!$E$41:$E$364,$C16) -> 0 | N16: =MAX(0,J16-K16-L16-M16) -> 623.09375 | O16: =R15 -> 15.868337 | P16: =SUMIFS(Assumptions!$AE$41:$AE$364,Assumptions!$C$41:$C$364,$D$4,Assumptions!$E$41:$E$364,$C16)+IF((Assumptions!$D$25+IF($C16="P001",-SUMIFS(Assumptions!$L$41:$L$364,Assumptions!$C$41:$C$364,$D$4,Assumptions!$E$41:$E$364,$C16)/365*Assumptions!$D$23,0))<0,MIN(MAX(0,Assumptions!$D$14-Assumptions!$D$16-O16),-(Assumptions!$D$25+IF($C16="P001",-SUMIFS(Assumptions!$L$41:$L$364,Assumptions!$C$41:$C$364,$D$4,Assumptions!$E$41:$E$364,$C16)/365*Assumptions!$D$23,0))),0) -> 0 | Q16: =SUMIFS(Assumptions!$AF$41:$AF$364,Assumptions!$C$41:$C$364,$D$4,Assumptions!$E$41:$E$364,$C16)+IF((Assumptions!$D$25+IF($C16="P001",-SUMIFS(Assumptions!$L$41:$L$364,Assumptions!$C$41:$C$364,$D$4,Assumptions!$E$41:$E$364,$C16)/365*Assumptions!$D$23,0))>0,MIN(O16,(Assumptions!$D$25+IF($C16="P001",-SUMIFS(Assumptions!$L$41:$L$364,Assumptions!$C$41:$C$364,$D$4,Assumptions!$E$41:$E$364,$C16)/365*Assumptions!$D$23,0))),0) -> 6.5479451 | R16: =MAX(0,O16+P16-Q16) -> 9.3203922 | S16: =(J16+N16+O16+R16)/2 -> 635.68811 | T16: =IF(Assumptions!$D$19="","",IF(((SUMIFS(Assumptions!$W$41:$W$364,Assumptions!$C$41:$C$364,$D$4,Assumptions!$E$41:$E$364,$C16)+SUMIFS(Assumptions!$AC$41:$AC$364,Assumptions!$C$41:$C$364,$D$4,Assumptions!$E$41:$E$364,$C16)+SUMIFS(Assumptions!$AD$41:$AD$364,Assumptions!$C$41:$C$364,$D$4,Assumptions!$E$41:$E$364,$C16)+SUMIFS(Assumptions!$AG$41:$AG$364,Assumptions!$C$41:$C$364,$D$4,Assumptions!$E$41:$E$364,$C16))/2)=0,0,SUMIFS(Assumptions!$AI$41:$AI$364,Assumptions!$C$41:$C$364,$D$4,Assumptions!$E$41:$E$364,$C16)*S16/((SUMIFS(Assumptions!$W$41:$W$364,Assumptions!$C$41:$C$364,$D$4,Assumptions!$E$41:$E$364,$C16)+SUMIFS(Assumptions!$AC$41:$AC$364,Assumptions!$C$41:$C$364,$D$4,Assumptions!$E$41:$E$364,$C16)+SUMIFS(Assumptions!$AD$41:$AD$364,Assumptions!$C$41:$C$364,$D$4,Assumptions!$E$41:$E$364,$C16)+SUMIFS(Assumptions!$AG$41:$AG$364,Assumptions!$C$41:$C$364,$D$4,Assumptions!$E$41:$E$364,$C16))/2)*(Assumptions!$D$19/6.57%))+Assumptions!$D$20*S16*H16/365) -> 3.4803924 | U16: =SUMIFS(Assumptions!$AJ$41:$AJ$364,Assumptions!$C$41:$C$364,$D$4,Assumptions!$E$41:$E$364,$C16) -> 0.69591667 | V16: =SUMIFS(Assumptions!$AK$41:$AK$364,Assumptions!$C$41:$C$364,$D$4,Assumptions!$E$41:$E$364,$C16)+SUMIFS(Assumptions!$AL$41:$AL$364,Assumptions!$C$41:$C$364,$D$4,Assumptions!$E$41:$E$364,$C16) -> 1.625 | W16: =W15+(SUMIFS(Assumptions!$V$41:$V$364,Assumptions!$C$41:$C$364,$D$4,Assumptions!$E$41:$E$364,$C16)-SUMIFS(Assumptions!$U$41:$U$364,Assumptions!$C$41:$C$364,$D$4,Assumptions!$E$41:$E$364,$C16))+(Assumptions!$D$25+IF($C16="P001",-SUMIFS(Assumptions!$L$41:$L$364,Assumptions!$C$41:$C$364,$D$4,Assumptions!$E$41:$E$364,$C16)/365*Assumptions!$D$23,0))+(IF((Assumptions!$D$25+IF($C16="P001",-SUMIFS(Assumptions!$L$41:$L$364,Assumptions!$C$41:$C$364,$D$4,Assumptions!$E$41:$E$364,$C16)/365*Assumptions!$D$23,0))<0,MIN(MAX(0,Assumptions!$D$14-Assumptions!$D$16-O16),-(Assumptions!$D$25+IF($C16="P001",-SUMIFS(Assumptions!$L$41:$L$364,Assumptions!$C$41:$C$364,$D$4,Assumptions!$E$41:$E$364,$C16)/365*Assumptions!$D$23,0))),0))-(IF((Assumptions!$D$25+IF($C16="P001",-SUMIFS(Assumptions!$L$41:$L$364,Assumptions!$C$41:$C$364,$D$4,Assumptions!$E$41:$E$364,$C16)/365*Assumptions!$D$23,0))>0,MIN(O16,(Assumptions!$D$25+IF($C16="P001",-SUMIFS(Assumptions!$L$41:$L$364,Assumptions!$C$41:$C$364,$D$4,Assumptions!$E$41:$E$364,$C16)/365*Assumptions!$D$23,0))),0)) -> 25 | X16: =N16+R16 -> 632.41414 | Y16: =Assumptions!$D$17 -> 62.619 | Z16: =X16+Y16 -> 695.03314 | AA16: =MAX(0,Assumptions!$D$14-Assumptions!$D$16-R16) -> 284.47961 | AB16: =MAX(0,W16-Assumptions!$D$24)+AA16 -> 284.47961 | AC16: =SUMIFS(Assumptions!$AM$41:$AM$364,Assumptions!$C$41:$C$364,$D$4,Assumptions!$E$41:$E$364,$C16)+MAX(0,-W16) -> 0 | AD16: =IF(COUNTIFS(Assumptions!$C$41:$C$364,$D$4,Assumptions!$E$41:$E$364,$C16,Assumptions!$AR$41:$AR$364,"*shutoff_active*")>0,"SHUTOFF","AVAILABLE") -> AVAILABLE
C17: P006 | D17: 46234 | E17: monthly | F17: FY2026 | G17: Q3 | H17: 31 | I17: =SUMIFS(Assumptions!$T$41:$T$364,Assumptions!$C$41:$C$364,$D$4,Assumptions!$E$41:$E$364,$C17)+(Assumptions!$D$25+IF($C17="P001",-SUMIFS(Assumptions!$L$41:$L$364,Assumptions!$C$41:$C$364,$D$4,Assumptions!$E$41:$E$364,$C17)/365*Assumptions!$D$23,0)) -> 12.349254 | J17: =N16 -> 623.09375 | K17: =SUMIFS(Assumptions!$Y$41:$Y$364,Assumptions!$C$41:$C$364,$D$4,Assumptions!$E$41:$E$364,$C17)*(Assumptions!$D$12/635)*(Assumptions!$D$18/7.5%) -> 11.90625 | L17: =SUMIFS(Assumptions!$Z$41:$Z$364,Assumptions!$C$41:$C$364,$D$4,Assumptions!$E$41:$E$364,$C17)*(Assumptions!$D$26/50%)*IF(SUMIFS(Assumptions!$AO$41:$AO$364,Assumptions!$C$41:$C$364,$D$4,Assumptions!$E$41:$E$364,$C17)>Assumptions!$D$24,1,0) -> 0 | M17: =SUMIFS(Assumptions!$AB$41:$AB$364,Assumptions!$C$41:$C$364,$D$4,Assumptions!$E$41:$E$364,$C17) -> 0 | N17: =MAX(0,J17-K17-L17-M17) -> 611.1875 | O17: =R16 -> 9.3203922 | P17: =SUMIFS(Assumptions!$AE$41:$AE$364,Assumptions!$C$41:$C$364,$D$4,Assumptions!$E$41:$E$364,$C17)+IF((Assumptions!$D$25+IF($C17="P001",-SUMIFS(Assumptions!$L$41:$L$364,Assumptions!$C$41:$C$364,$D$4,Assumptions!$E$41:$E$364,$C17)/365*Assumptions!$D$23,0))<0,MIN(MAX(0,Assumptions!$D$14-Assumptions!$D$16-O17),-(Assumptions!$D$25+IF($C17="P001",-SUMIFS(Assumptions!$L$41:$L$364,Assumptions!$C$41:$C$364,$D$4,Assumptions!$E$41:$E$364,$C17)/365*Assumptions!$D$23,0))),0) -> 5.3223565 | Q17: =SUMIFS(Assumptions!$AF$41:$AF$364,Assumptions!$C$41:$C$364,$D$4,Assumptions!$E$41:$E$364,$C17)+IF((Assumptions!$D$25+IF($C17="P001",-SUMIFS(Assumptions!$L$41:$L$364,Assumptions!$C$41:$C$364,$D$4,Assumptions!$E$41:$E$364,$C17)/365*Assumptions!$D$23,0))>0,MIN(O17,(Assumptions!$D$25+IF($C17="P001",-SUMIFS(Assumptions!$L$41:$L$364,Assumptions!$C$41:$C$364,$D$4,Assumptions!$E$41:$E$364,$C17)/365*Assumptions!$D$23,0))),0) -> 0 | R17: =MAX(0,O17+P17-Q17) -> 14.642749 | S17: =(J17+N17+O17+R17)/2 -> 629.1222 | T17: =IF(Assumptions!$D$19="","",IF(((SUMIFS(Assumptions!$W$41:$W$364,Assumptions!$C$41:$C$364,$D$4,Assumptions!$E$41:$E$364,$C17)+SUMIFS(Assumptions!$AC$41:$AC$364,Assumptions!$C$41:$C$364,$D$4,Assumptions!$E$41:$E$364,$C17)+SUMIFS(Assumptions!$AD$41:$AD$364,Assumptions!$C$41:$C$364,$D$4,Assumptions!$E$41:$E$364,$C17)+SUMIFS(Assumptions!$AG$41:$AG$364,Assumptions!$C$41:$C$364,$D$4,Assumptions!$E$41:$E$364,$C17))/2)=0,0,SUMIFS(Assumptions!$AI$41:$AI$364,Assumptions!$C$41:$C$364,$D$4,Assumptions!$E$41:$E$364,$C17)*S17/((SUMIFS(Assumptions!$W$41:$W$364,Assumptions!$C$41:$C$364,$D$4,Assumptions!$E$41:$E$364,$C17)+SUMIFS(Assumptions!$AC$41:$AC$364,Assumptions!$C$41:$C$364,$D$4,Assumptions!$E$41:$E$364,$C17)+SUMIFS(Assumptions!$AD$41:$AD$364,Assumptions!$C$41:$C$364,$D$4,Assumptions!$E$41:$E$364,$C17)+SUMIFS(Assumptions!$AG$41:$AG$364,Assumptions!$C$41:$C$364,$D$4,Assumptions!$E$41:$E$364,$C17))/2)*(Assumptions!$D$19/6.57%))+Assumptions!$D$20*S17*H17/365) -> 3.444444 | U17: =SUMIFS(Assumptions!$AJ$41:$AJ$364,Assumptions!$C$41:$C$364,$D$4,Assumptions!$E$41:$E$364,$C17) -> 0.69591667 | V17: =SUMIFS(Assumptions!$AK$41:$AK$364,Assumptions!$C$41:$C$364,$D$4,Assumptions!$E$41:$E$364,$C17)+SUMIFS(Assumptions!$AL$41:$AL$364,Assumptions!$C$41:$C$364,$D$4,Assumptions!$E$41:$E$364,$C17) -> 1.625 | W17: =W16+(SUMIFS(Assumptions!$V$41:$V$364,Assumptions!$C$41:$C$364,$D$4,Assumptions!$E$41:$E$364,$C17)-SUMIFS(Assumptions!$U$41:$U$364,Assumptions!$C$41:$C$364,$D$4,Assumptions!$E$41:$E$364,$C17))+(Assumptions!$D$25+IF($C17="P001",-SUMIFS(Assumptions!$L$41:$L$364,Assumptions!$C$41:$C$364,$D$4,Assumptions!$E$41:$E$364,$C17)/365*Assumptions!$D$23,0))+(IF((Assumptions!$D$25+IF($C17="P001",-SUMIFS(Assumptions!$L$41:$L$364,Assumptions!$C$41:$C$364,$D$4,Assumptions!$E$41:$E$364,$C17)/365*Assumptions!$D$23,0))<0,MIN(MAX(0,Assumptions!$D$14-Assumptions!$D$16-O17),-(Assumptions!$D$25+IF($C17="P001",-SUMIFS(Assumptions!$L$41:$L$364,Assumptions!$C$41:$C$364,$D$4,Assumptions!$E$41:$E$364,$C17)/365*Assumptions!$D$23,0))),0))-(IF((Assumptions!$D$25+IF($C17="P001",-SUMIFS(Assumptions!$L$41:$L$364,Assumptions!$C$41:$C$364,$D$4,Assumptions!$E$41:$E$364,$C17)/365*Assumptions!$D$23,0))>0,MIN(O17,(Assumptions!$D$25+IF($C17="P001",-SUMIFS(Assumptions!$L$41:$L$364,Assumptions!$C$41:$C$364,$D$4,Assumptions!$E$41:$E$364,$C17)/365*Assumptions!$D$23,0))),0)) -> 25 | X17: =N17+R17 -> 625.83025 | Y17: =Assumptions!$D$17 -> 62.619 | Z17: =X17+Y17 -> 688.44925 | AA17: =MAX(0,Assumptions!$D$14-Assumptions!$D$16-R17) -> 279.15725 | AB17: =MAX(0,W17-Assumptions!$D$24)+AA17 -> 279.15725 | AC17: =SUMIFS(Assumptions!$AM$41:$AM$364,Assumptions!$C$41:$C$364,$D$4,Assumptions!$E$41:$E$364,$C17)+MAX(0,-W17) -> 0 | AD17: =IF(COUNTIFS(Assumptions!$C$41:$C$364,$D$4,Assumptions!$E$41:$E$364,$C17,Assumptions!$AR$41:$AR$364,"*shutoff_active*")>0,"SHUTOFF","AVAILABLE") -> AVAILABLE
C18: P007 | D18: 46265 | E18: monthly | F18: FY2026 | G18: Q4 | H18: 31 | I18: =SUMIFS(Assumptions!$T$41:$T$364,Assumptions!$C$41:$C$364,$D$4,Assumptions!$E$41:$E$364,$C18)+(Assumptions!$D$25+IF($C18="P001",-SUMIFS(Assumptions!$L$41:$L$364,Assumptions!$C$41:$C$364,$D$4,Assumptions!$E$41:$E$364,$C18)/365*Assumptions!$D$23,0)) -> 12.490378 | J18: =N17 -> 611.1875 | K18: =SUMIFS(Assumptions!$Y$41:$Y$364,Assumptions!$C$41:$C$364,$D$4,Assumptions!$E$41:$E$364,$C18)*(Assumptions!$D$12/635)*(Assumptions!$D$18/7.5%) -> 0 | L18: =SUMIFS(Assumptions!$Z$41:$Z$364,Assumptions!$C$41:$C$364,$D$4,Assumptions!$E$41:$E$364,$C18)*(Assumptions!$D$26/50%)*IF(SUMIFS(Assumptions!$AO$41:$AO$364,Assumptions!$C$41:$C$364,$D$4,Assumptions!$E$41:$E$364,$C18)>Assumptions!$D$24,1,0) -> 0 | M18: =SUMIFS(Assumptions!$AB$41:$AB$364,Assumptions!$C$41:$C$364,$D$4,Assumptions!$E$41:$E$364,$C18) -> 0 | N18: =MAX(0,J18-K18-L18-M18) -> 611.1875 | O18: =R17 -> 14.642749 | P18: =SUMIFS(Assumptions!$AE$41:$AE$364,Assumptions!$C$41:$C$364,$D$4,Assumptions!$E$41:$E$364,$C18)+IF((Assumptions!$D$25+IF($C18="P001",-SUMIFS(Assumptions!$L$41:$L$364,Assumptions!$C$41:$C$364,$D$4,Assumptions!$E$41:$E$364,$C18)/365*Assumptions!$D$23,0))<0,MIN(MAX(0,Assumptions!$D$14-Assumptions!$D$16-O18),-(Assumptions!$D$25+IF($C18="P001",-SUMIFS(Assumptions!$L$41:$L$364,Assumptions!$C$41:$C$364,$D$4,Assumptions!$E$41:$E$364,$C18)/365*Assumptions!$D$23,0))),0) -> 0 | Q18: =SUMIFS(Assumptions!$AF$41:$AF$364,Assumptions!$C$41:$C$364,$D$4,Assumptions!$E$41:$E$364,$C18)+IF((Assumptions!$D$25+IF($C18="P001",-SUMIFS(Assumptions!$L$41:$L$364,Assumptions!$C$41:$C$364,$D$4,Assumptions!$E$41:$E$364,$C18)/365*Assumptions!$D$23,0))>0,MIN(O18,(Assumptions!$D$25+IF($C18="P001",-SUMIFS(Assumptions!$L$41:$L$364,Assumptions!$C$41:$C$364,$D$4,Assumptions!$E$41:$E$364,$C18)/365*Assumptions!$D$23,0))),0) -> 6.76155 | R18: =MAX(0,O18+P18-Q18) -> 7.8811987 | S18: =(J18+N18+O18+R18)/2 -> 622.44947 | T18: =IF(Assumptions!$D$19="","",IF(((SUMIFS(Assumptions!$W$41:$W$364,Assumptions!$C$41:$C$364,$D$4,Assumptions!$E$41:$E$364,$C18)+SUMIFS(Assumptions!$AC$41:$AC$364,Assumptions!$C$41:$C$364,$D$4,Assumptions!$E$41:$E$364,$C18)+SUMIFS(Assumptions!$AD$41:$AD$364,Assumptions!$C$41:$C$364,$D$4,Assumptions!$E$41:$E$364,$C18)+SUMIFS(Assumptions!$AG$41:$AG$364,Assumptions!$C$41:$C$364,$D$4,Assumptions!$E$41:$E$364,$C18))/2)=0,0,SUMIFS(Assumptions!$AI$41:$AI$364,Assumptions!$C$41:$C$364,$D$4,Assumptions!$E$41:$E$364,$C18)*S18/((SUMIFS(Assumptions!$W$41:$W$364,Assumptions!$C$41:$C$364,$D$4,Assumptions!$E$41:$E$364,$C18)+SUMIFS(Assumptions!$AC$41:$AC$364,Assumptions!$C$41:$C$364,$D$4,Assumptions!$E$41:$E$364,$C18)+SUMIFS(Assumptions!$AD$41:$AD$364,Assumptions!$C$41:$C$364,$D$4,Assumptions!$E$41:$E$364,$C18)+SUMIFS(Assumptions!$AG$41:$AG$364,Assumptions!$C$41:$C$364,$D$4,Assumptions!$E$41:$E$364,$C18))/2)*(Assumptions!$D$19/6.57%))+Assumptions!$D$20*S18*H18/365) -> 3.4079109 | U18: =SUMIFS(Assumptions!$AJ$41:$AJ$364,Assumptions!$C$41:$C$364,$D$4,Assumptions!$E$41:$E$364,$C18) -> 0.69591667 | V18: =SUMIFS(Assumptions!$AK$41:$AK$364,Assumptions!$C$41:$C$364,$D$4,Assumptions!$E$41:$E$364,$C18)+SUMIFS(Assumptions!$AL$41:$AL$364,Assumptions!$C$41:$C$364,$D$4,Assumptions!$E$41:$E$364,$C18) -> 1.625 | W18: =W17+(SUMIFS(Assumptions!$V$41:$V$364,Assumptions!$C$41:$C$364,$D$4,Assumptions!$E$41:$E$364,$C18)-SUMIFS(Assumptions!$U$41:$U$364,Assumptions!$C$41:$C$364,$D$4,Assumptions!$E$41:$E$364,$C18))+(Assumptions!$D$25+IF($C18="P001",-SUMIFS(Assumptions!$L$41:$L$364,Assumptions!$C$41:$C$364,$D$4,Assumptions!$E$41:$E$364,$C18)/365*Assumptions!$D$23,0))+(IF((Assumptions!$D$25+IF($C18="P001",-SUMIFS(Assumptions!$L$41:$L$364,Assumptions!$C$41:$C$364,$D$4,Assumptions!$E$41:$E$364,$C18)/365*Assumptions!$D$23,0))<0,MIN(MAX(0,Assumptions!$D$14-Assumptions!$D$16-O18),-(Assumptions!$D$25+IF($C18="P001",-SUMIFS(Assumptions!$L$41:$L$364,Assumptions!$C$41:$C$364,$D$4,Assumptions!$E$41:$E$364,$C18)/365*Assumptions!$D$23,0))),0))-(IF((Assumptions!$D$25+IF($C18="P001",-SUMIFS(Assumptions!$L$41:$L$364,Assumptions!$C$41:$C$364,$D$4,Assumptions!$E$41:$E$364,$C18)/365*Assumptions!$D$23,0))>0,MIN(O18,(Assumptions!$D$25+IF($C18="P001",-SUMIFS(Assumptions!$L$41:$L$364,Assumptions!$C$41:$C$364,$D$4,Assumptions!$E$41:$E$364,$C18)/365*Assumptions!$D$23,0))),0)) -> 25 | X18: =N18+R18 -> 619.0687 | Y18: =Assumptions!$D$17 -> 62.619 | Z18: =X18+Y18 -> 681.6877 | AA18: =MAX(0,Assumptions!$D$14-Assumptions!$D$16-R18) -> 285.9188 | AB18: =MAX(0,W18-Assumptions!$D$24)+AA18 -> 285.9188 | AC18: =SUMIFS(Assumptions!$AM$41:$AM$364,Assumptions!$C$41:$C$364,$D$4,Assumptions!$E$41:$E$364,$C18)+MAX(0,-W18) -> 0 | AD18: =IF(COUNTIFS(Assumptions!$C$41:$C$364,$D$4,Assumptions!$E$41:$E$364,$C18,Assumptions!$AR$41:$AR$364,"*shutoff_active*")>0,"SHUTOFF","AVAILABLE") -> AVAILABLE
C19: P008 | D19: 46295 | E19: monthly | F19: FY2026 | G19: Q4 | H19: 30 | I19: =SUMIFS(Assumptions!$T$41:$T$364,Assumptions!$C$41:$C$364,$D$4,Assumptions!$E$41:$E$364,$C19)+(Assumptions!$D$25+IF($C19="P001",-SUMIFS(Assumptions!$L$41:$L$364,Assumptions!$C$41:$C$364,$D$4,Assumptions!$E$41:$E$364,$C19)/365*Assumptions!$D$23,0)) -> 12.490378 | J19: =N18 -> 611.1875 | K19: =SUMIFS(Assumptions!$Y$41:$Y$364,Assumptions!$C$41:$C$364,$D$4,Assumptions!$E$41:$E$364,$C19)*(Assumptions!$D$12/635)*(Assumptions!$D$18/7.5%) -> 0 | L19: =SUMIFS(Assumptions!$Z$41:$Z$364,Assumptions!$C$41:$C$364,$D$4,Assumptions!$E$41:$E$364,$C19)*(Assumptions!$D$26/50%)*IF(SUMIFS(Assumptions!$AO$41:$AO$364,Assumptions!$C$41:$C$364,$D$4,Assumptions!$E$41:$E$364,$C19)>Assumptions!$D$24,1,0) -> 0 | M19: =SUMIFS(Assumptions!$AB$41:$AB$364,Assumptions!$C$41:$C$364,$D$4,Assumptions!$E$41:$E$364,$C19) -> 0 | N19: =MAX(0,J19-K19-L19-M19) -> 611.1875 | O19: =R18 -> 7.8811987 | P19: =SUMIFS(Assumptions!$AE$41:$AE$364,Assumptions!$C$41:$C$364,$D$4,Assumptions!$E$41:$E$364,$C19)+IF((Assumptions!$D$25+IF($C19="P001",-SUMIFS(Assumptions!$L$41:$L$364,Assumptions!$C$41:$C$364,$D$4,Assumptions!$E$41:$E$364,$C19)/365*Assumptions!$D$23,0))<0,MIN(MAX(0,Assumptions!$D$14-Assumptions!$D$16-O19),-(Assumptions!$D$25+IF($C19="P001",-SUMIFS(Assumptions!$L$41:$L$364,Assumptions!$C$41:$C$364,$D$4,Assumptions!$E$41:$E$364,$C19)/365*Assumptions!$D$23,0))),0) -> 0 | Q19: =SUMIFS(Assumptions!$AF$41:$AF$364,Assumptions!$C$41:$C$364,$D$4,Assumptions!$E$41:$E$364,$C19)+IF((Assumptions!$D$25+IF($C19="P001",-SUMIFS(Assumptions!$L$41:$L$364,Assumptions!$C$41:$C$364,$D$4,Assumptions!$E$41:$E$364,$C19)/365*Assumptions!$D$23,0))>0,MIN(O19,(Assumptions!$D$25+IF($C19="P001",-SUMIFS(Assumptions!$L$41:$L$364,Assumptions!$C$41:$C$364,$D$4,Assumptions!$E$41:$E$364,$C19)/365*Assumptions!$D$23,0))),0) -> 6.7986711 | R19: =MAX(0,O19+P19-Q19) -> 1.0825276 | S19: =(J19+N19+O19+R19)/2 -> 615.66936 | T19: =IF(Assumptions!$D$19="","",IF(((SUMIFS(Assumptions!$W$41:$W$364,Assumptions!$C$41:$C$364,$D$4,Assumptions!$E$41:$E$364,$C19)+SUMIFS(Assumptions!$AC$41:$AC$364,Assumptions!$C$41:$C$364,$D$4,Assumptions!$E$41:$E$364,$C19)+SUMIFS(Assumptions!$AD$41:$AD$364,Assumptions!$C$41:$C$364,$D$4,Assumptions!$E$41:$E$364,$C19)+SUMIFS(Assumptions!$AG$41:$AG$364,Assumptions!$C$41:$C$364,$D$4,Assumptions!$E$41:$E$364,$C19))/2)=0,0,SUMIFS(Assumptions!$AI$41:$AI$364,Assumptions!$C$41:$C$364,$D$4,Assumptions!$E$41:$E$364,$C19)*S19/((SUMIFS(Assumptions!$W$41:$W$364,Assumptions!$C$41:$C$364,$D$4,Assumptions!$E$41:$E$364,$C19)+SUMIFS(Assumptions!$AC$41:$AC$364,Assumptions!$C$41:$C$364,$D$4,Assumptions!$E$41:$E$364,$C19)+SUMIFS(Assumptions!$AD$41:$AD$364,Assumptions!$C$41:$C$364,$D$4,Assumptions!$E$41:$E$364,$C19)+SUMIFS(Assumptions!$AG$41:$AG$364,Assumptions!$C$41:$C$364,$D$4,Assumptions!$E$41:$E$364,$C19))/2)*(Assumptions!$D$19/6.57%))+Assumptions!$D$20*S19*H19/365) -> 3.3707898 | U19: =SUMIFS(Assumptions!$AJ$41:$AJ$364,Assumptions!$C$41:$C$364,$D$4,Assumptions!$E$41:$E$364,$C19) -> 0.69591667 | V19: =SUMIFS(Assumptions!$AK$41:$AK$364,Assumptions!$C$41:$C$364,$D$4,Assumptions!$E$41:$E$364,$C19)+SUMIFS(Assumptions!$AL$41:$AL$364,Assumptions!$C$41:$C$364,$D$4,Assumptions!$E$41:$E$364,$C19) -> 1.625 | W19: =W18+(SUMIFS(Assumptions!$V$41:$V$364,Assumptions!$C$41:$C$364,$D$4,Assumptions!$E$41:$E$364,$C19)-SUMIFS(Assumptions!$U$41:$U$364,Assumptions!$C$41:$C$364,$D$4,Assumptions!$E$41:$E$364,$C19))+(Assumptions!$D$25+IF($C19="P001",-SUMIFS(Assumptions!$L$41:$L$364,Assumptions!$C$41:$C$364,$D$4,Assumptions!$E$41:$E$364,$C19)/365*Assumptions!$D$23,0))+(IF((Assumptions!$D$25+IF($C19="P001",-SUMIFS(Assumptions!$L$41:$L$364,Assumptions!$C$41:$C$364,$D$4,Assumptions!$E$41:$E$364,$C19)/365*Assumptions!$D$23,0))<0,MIN(MAX(0,Assumptions!$D$14-Assumptions!$D$16-O19),-(Assumptions!$D$25+IF($C19="P001",-SUMIFS(Assumptions!$L$41:$L$364,Assumptions!$C$41:$C$364,$D$4,Assumptions!$E$41:$E$364,$C19)/365*Assumptions!$D$23,0))),0))-(IF((Assumptions!$D$25+IF($C19="P001",-SUMIFS(Assumptions!$L$41:$L$364,Assumptions!$C$41:$C$364,$D$4,Assumptions!$E$41:$E$364,$C19)/365*Assumptions!$D$23,0))>0,MIN(O19,(Assumptions!$D$25+IF($C19="P001",-SUMIFS(Assumptions!$L$41:$L$364,Assumptions!$C$41:$C$364,$D$4,Assumptions!$E$41:$E$364,$C19)/365*Assumptions!$D$23,0))),0)) -> 25 | X19: =N19+R19 -> 612.27003 | Y19: =Assumptions!$D$17 -> 62.619 | Z19: =X19+Y19 -> 674.88903 | AA19: =MAX(0,Assumptions!$D$14-Assumptions!$D$16-R19) -> 292.71747 | AB19: =MAX(0,W19-Assumptions!$D$24)+AA19 -> 292.71747 | AC19: =SUMIFS(Assumptions!$AM$41:$AM$364,Assumptions!$C$41:$C$364,$D$4,Assumptions!$E$41:$E$364,$C19)+MAX(0,-W19) -> 0 | AD19: =IF(COUNTIFS(Assumptions!$C$41:$C$364,$D$4,Assumptions!$E$41:$E$364,$C19,Assumptions!$AR$41:$AR$364,"*shutoff_active*")>0,"SHUTOFF","AVAILABLE") -> AVAILABLE
C20: P009 | D20: 46326 | E20: monthly | F20: FY2026 | G20: Q4 | H20: 31 | I20: =SUMIFS(Assumptions!$T$41:$T$364,Assumptions!$C$41:$C$364,$D$4,Assumptions!$E$41:$E$364,$C20)+(Assumptions!$D$25+IF($C20="P001",-SUMIFS(Assumptions!$L$41:$L$364,Assumptions!$C$41:$C$364,$D$4,Assumptions!$E$41:$E$364,$C20)/365*Assumptions!$D$23,0)) -> 12.490378 | J20: =N19 -> 611.1875 | K20: =SUMIFS(Assumptions!$Y$41:$Y$364,Assumptions!$C$41:$C$364,$D$4,Assumptions!$E$41:$E$364,$C20)*(Assumptions!$D$12/635)*(Assumptions!$D$18/7.5%) -> 11.90625 | L20: =SUMIFS(Assumptions!$Z$41:$Z$364,Assumptions!$C$41:$C$364,$D$4,Assumptions!$E$41:$E$364,$C20)*(Assumptions!$D$26/50%)*IF(SUMIFS(Assumptions!$AO$41:$AO$364,Assumptions!$C$41:$C$364,$D$4,Assumptions!$E$41:$E$364,$C20)>Assumptions!$D$24,1,0) -> 0 | M20: =SUMIFS(Assumptions!$AB$41:$AB$364,Assumptions!$C$41:$C$364,$D$4,Assumptions!$E$41:$E$364,$C20) -> 0 | N20: =MAX(0,J20-K20-L20-M20) -> 599.28125 | O20: =R19 -> 1.0825276 | P20: =SUMIFS(Assumptions!$AE$41:$AE$364,Assumptions!$C$41:$C$364,$D$4,Assumptions!$E$41:$E$364,$C20)+IF((Assumptions!$D$25+IF($C20="P001",-SUMIFS(Assumptions!$L$41:$L$364,Assumptions!$C$41:$C$364,$D$4,Assumptions!$E$41:$E$364,$C20)/365*Assumptions!$D$23,0))<0,MIN(MAX(0,Assumptions!$D$14-Assumptions!$D$16-O20),-(Assumptions!$D$25+IF($C20="P001",-SUMIFS(Assumptions!$L$41:$L$364,Assumptions!$C$41:$C$364,$D$4,Assumptions!$E$41:$E$364,$C20)/365*Assumptions!$D$23,0))),0) -> 5.070254 | Q20: =SUMIFS(Assumptions!$AF$41:$AF$364,Assumptions!$C$41:$C$364,$D$4,Assumptions!$E$41:$E$364,$C20)+IF((Assumptions!$D$25+IF($C20="P001",-SUMIFS(Assumptions!$L$41:$L$364,Assumptions!$C$41:$C$364,$D$4,Assumptions!$E$41:$E$364,$C20)/365*Assumptions!$D$23,0))>0,MIN(O20,(Assumptions!$D$25+IF($C20="P001",-SUMIFS(Assumptions!$L$41:$L$364,Assumptions!$C$41:$C$364,$D$4,Assumptions!$E$41:$E$364,$C20)/365*Assumptions!$D$23,0))),0) -> 0 | R20: =MAX(0,O20+P20-Q20) -> 6.1527815 | S20: =(J20+N20+O20+R20)/2 -> 608.85203 | T20: =IF(Assumptions!$D$19="","",IF(((SUMIFS(Assumptions!$W$41:$W$364,Assumptions!$C$41:$C$364,$D$4,Assumptions!$E$41:$E$364,$C20)+SUMIFS(Assumptions!$AC$41:$AC$364,Assumptions!$C$41:$C$364,$D$4,Assumptions!$E$41:$E$364,$C20)+SUMIFS(Assumptions!$AD$41:$AD$364,Assumptions!$C$41:$C$364,$D$4,Assumptions!$E$41:$E$364,$C20)+SUMIFS(Assumptions!$AG$41:$AG$364,Assumptions!$C$41:$C$364,$D$4,Assumptions!$E$41:$E$364,$C20))/2)=0,0,SUMIFS(Assumptions!$AI$41:$AI$364,Assumptions!$C$41:$C$364,$D$4,Assumptions!$E$41:$E$364,$C20)*S20/((SUMIFS(Assumptions!$W$41:$W$364,Assumptions!$C$41:$C$364,$D$4,Assumptions!$E$41:$E$364,$C20)+SUMIFS(Assumptions!$AC$41:$AC$364,Assumptions!$C$41:$C$364,$D$4,Assumptions!$E$41:$E$364,$C20)+SUMIFS(Assumptions!$AD$41:$AD$364,Assumptions!$C$41:$C$364,$D$4,Assumptions!$E$41:$E$364,$C20)+SUMIFS(Assumptions!$AG$41:$AG$364,Assumptions!$C$41:$C$364,$D$4,Assumptions!$E$41:$E$364,$C20))/2)*(Assumptions!$D$19/6.57%))+Assumptions!$D$20*S20*H20/365) -> 3.3334649 | U20: =SUMIFS(Assumptions!$AJ$41:$AJ$364,Assumptions!$C$41:$C$364,$D$4,Assumptions!$E$41:$E$364,$C20) -> 0.69591667 | V20: =SUMIFS(Assumptions!$AK$41:$AK$364,Assumptions!$C$41:$C$364,$D$4,Assumptions!$E$41:$E$364,$C20)+SUMIFS(Assumptions!$AL$41:$AL$364,Assumptions!$C$41:$C$364,$D$4,Assumptions!$E$41:$E$364,$C20) -> 1.625 | W20: =W19+(SUMIFS(Assumptions!$V$41:$V$364,Assumptions!$C$41:$C$364,$D$4,Assumptions!$E$41:$E$364,$C20)-SUMIFS(Assumptions!$U$41:$U$364,Assumptions!$C$41:$C$364,$D$4,Assumptions!$E$41:$E$364,$C20))+(Assumptions!$D$25+IF($C20="P001",-SUMIFS(Assumptions!$L$41:$L$364,Assumptions!$C$41:$C$364,$D$4,Assumptions!$E$41:$E$364,$C20)/365*Assumptions!$D$23,0))+(IF((Assumptions!$D$25+IF($C20="P001",-SUMIFS(Assumptions!$L$41:$L$364,Assumptions!$C$41:$C$364,$D$4,Assumptions!$E$41:$E$364,$C20)/365*Assumptions!$D$23,0))<0,MIN(MAX(0,Assumptions!$D$14-Assumptions!$D$16-O20),-(Assumptions!$D$25+IF($C20="P001",-SUMIFS(Assumptions!$L$41:$L$364,Assumptions!$C$41:$C$364,$D$4,Assumptions!$E$41:$E$364,$C20)/365*Assumptions!$D$23,0))),0))-(IF((Assumptions!$D$25+IF($C20="P001",-SUMIFS(Assumptions!$L$41:$L$364,Assumptions!$C$41:$C$364,$D$4,Assumptions!$E$41:$E$364,$C20)/365*Assumptions!$D$23,0))>0,MIN(O20,(Assumptions!$D$25+IF($C20="P001",-SUMIFS(Assumptions!$L$41:$L$364,Assumptions!$C$41:$C$364,$D$4,Assumptions!$E$41:$E$364,$C20)/365*Assumptions!$D$23,0))),0)) -> 25 | X20: =N20+R20 -> 605.43403 | Y20: =Assumptions!$D$17 -> 62.619 | Z20: =X20+Y20 -> 668.05303 | AA20: =MAX(0,Assumptions!$D$14-Assumptions!$D$16-R20) -> 287.64722 | AB20: =MAX(0,W20-Assumptions!$D$24)+AA20 -> 287.64722 | AC20: =SUMIFS(Assumptions!$AM$41:$AM$364,Assumptions!$C$41:$C$364,$D$4,Assumptions!$E$41:$E$364,$C20)+MAX(0,-W20) -> 0 | AD20: =IF(COUNTIFS(Assumptions!$C$41:$C$364,$D$4,Assumptions!$E$41:$E$364,$C20,Assumptions!$AR$41:$AR$364,"*shutoff_active*")>0,"SHUTOFF","AVAILABLE") -> AVAILABLE
C21: P010 | D21: 46356 | E21: monthly | F21: FY2027 | G21: Q1 | H21: 30 | I21: =SUMIFS(Assumptions!$T$41:$T$364,Assumptions!$C$41:$C$364,$D$4,Assumptions!$E$41:$E$364,$C21)+(Assumptions!$D$25+IF($C21="P001",-SUMIFS(Assumptions!$L$41:$L$364,Assumptions!$C$41:$C$364,$D$4,Assumptions!$E$41:$E$364,$C21)/365*Assumptions!$D$23,0)) -> 5.2161301 | J21: =N20 -> 599.28125 | K21: =SUMIFS(Assumptions!$Y$41:$Y$364,Assumptions!$C$41:$C$364,$D$4,Assumptions!$E$41:$E$364,$C21)*(Assumptions!$D$12/635)*(Assumptions!$D$18/7.5%) -> 0 | L21: =SUMIFS(Assumptions!$Z$41:$Z$364,Assumptions!$C$41:$C$364,$D$4,Assumptions!$E$41:$E$364,$C21)*(Assumptions!$D$26/50%)*IF(SUMIFS(Assumptions!$AO$41:$AO$364,Assumptions!$C$41:$C$364,$D$4,Assumptions!$E$41:$E$364,$C21)>Assumptions!$D$24,1,0) -> 0 | M21: =SUMIFS(Assumptions!$AB$41:$AB$364,Assumptions!$C$41:$C$364,$D$4,Assumptions!$E$41:$E$364,$C21) -> 0 | N21: =MAX(0,J21-K21-L21-M21) -> 599.28125 | O21: =R20 -> 6.1527815 | P21: =SUMIFS(Assumptions!$AE$41:$AE$364,Assumptions!$C$41:$C$364,$D$4,Assumptions!$E$41:$E$364,$C21)+IF((Assumptions!$D$25+IF($C21="P001",-SUMIFS(Assumptions!$L$41:$L$364,Assumptions!$C$41:$C$364,$D$4,Assumptions!$E$41:$E$364,$C21)/365*Assumptions!$D$23,0))<0,MIN(MAX(0,Assumptions!$D$14-Assumptions!$D$16-O21),-(Assumptions!$D$25+IF($C21="P001",-SUMIFS(Assumptions!$L$41:$L$364,Assumptions!$C$41:$C$364,$D$4,Assumptions!$E$41:$E$364,$C21)/365*Assumptions!$D$23,0))),0) -> 0.39394964 | Q21: =SUMIFS(Assumptions!$AF$41:$AF$364,Assumptions!$C$41:$C$364,$D$4,Assumptions!$E$41:$E$364,$C21)+IF((Assumptions!$D$25+IF($C21="P001",-SUMIFS(Assumptions!$L$41:$L$364,Assumptions!$C$41:$C$364,$D$4,Assumptions!$E$41:$E$364,$C21)/365*Assumptions!$D$23,0))>0,MIN(O21,(Assumptions!$D$25+IF($C21="P001",-SUMIFS(Assumptions!$L$41:$L$364,Assumptions!$C$41:$C$364,$D$4,Assumptions!$E$41:$E$364,$C21)/365*Assumptions!$D$23,0))),0) -> 0 | R21: =MAX(0,O21+P21-Q21) -> 6.5467312 | S21: =(J21+N21+O21+R21)/2 -> 605.63101 | T21: =IF(Assumptions!$D$19="","",IF(((SUMIFS(Assumptions!$W$41:$W$364,Assumptions!$C$41:$C$364,$D$4,Assumptions!$E$41:$E$364,$C21)+SUMIFS(Assumptions!$AC$41:$AC$364,Assumptions!$C$41:$C$364,$D$4,Assumptions!$E$41:$E$364,$C21)+SUMIFS(Assumptions!$AD$41:$AD$364,Assumptions!$C$41:$C$364,$D$4,Assumptions!$E$41:$E$364,$C21)+SUMIFS(Assumptions!$AG$41:$AG$364,Assumptions!$C$41:$C$364,$D$4,Assumptions!$E$41:$E$364,$C21))/2)=0,0,SUMIFS(Assumptions!$AI$41:$AI$364,Assumptions!$C$41:$C$364,$D$4,Assumptions!$E$41:$E$364,$C21)*S21/((SUMIFS(Assumptions!$W$41:$W$364,Assumptions!$C$41:$C$364,$D$4,Assumptions!$E$41:$E$364,$C21)+SUMIFS(Assumptions!$AC$41:$AC$364,Assumptions!$C$41:$C$364,$D$4,Assumptions!$E$41:$E$364,$C21)+SUMIFS(Assumptions!$AD$41:$AD$364,Assumptions!$C$41:$C$364,$D$4,Assumptions!$E$41:$E$364,$C21)+SUMIFS(Assumptions!$AG$41:$AG$364,Assumptions!$C$41:$C$364,$D$4,Assumptions!$E$41:$E$364,$C21))/2)*(Assumptions!$D$19/6.57%))+Assumptions!$D$20*S21*H21/365) -> 3.3158298 | U21: =SUMIFS(Assumptions!$AJ$41:$AJ$364,Assumptions!$C$41:$C$364,$D$4,Assumptions!$E$41:$E$364,$C21) -> 0.66925 | V21: =SUMIFS(Assumptions!$AK$41:$AK$364,Assumptions!$C$41:$C$364,$D$4,Assumptions!$E$41:$E$364,$C21)+SUMIFS(Assumptions!$AL$41:$AL$364,Assumptions!$C$41:$C$364,$D$4,Assumptions!$E$41:$E$364,$C21) -> 1.625 | W21: =W20+(SUMIFS(Assumptions!$V$41:$V$364,Assumptions!$C$41:$C$364,$D$4,Assumptions!$E$41:$E$364,$C21)-SUMIFS(Assumptions!$U$41:$U$364,Assumptions!$C$41:$C$364,$D$4,Assumptions!$E$41:$E$364,$C21))+(Assumptions!$D$25+IF($C21="P001",-SUMIFS(Assumptions!$L$41:$L$364,Assumptions!$C$41:$C$364,$D$4,Assumptions!$E$41:$E$364,$C21)/365*Assumptions!$D$23,0))+(IF((Assumptions!$D$25+IF($C21="P001",-SUMIFS(Assumptions!$L$41:$L$364,Assumptions!$C$41:$C$364,$D$4,Assumptions!$E$41:$E$364,$C21)/365*Assumptions!$D$23,0))<0,MIN(MAX(0,Assumptions!$D$14-Assumptions!$D$16-O21),-(Assumptions!$D$25+IF($C21="P001",-SUMIFS(Assumptions!$L$41:$L$364,Assumptions!$C$41:$C$364,$D$4,Assumptions!$E$41:$E$364,$C21)/365*Assumptions!$D$23,0))),0))-(IF((Assumptions!$D$25+IF($C21="P001",-SUMIFS(Assumptions!$L$41:$L$364,Assumptions!$C$41:$C$364,$D$4,Assumptions!$E$41:$E$364,$C21)/365*Assumptions!$D$23,0))>0,MIN(O21,(Assumptions!$D$25+IF($C21="P001",-SUMIFS(Assumptions!$L$41:$L$364,Assumptions!$C$41:$C$364,$D$4,Assumptions!$E$41:$E$364,$C21)/365*Assumptions!$D$23,0))),0)) -> 25 | X21: =N21+R21 -> 605.82798 | Y21: =Assumptions!$D$17 -> 62.619 | Z21: =X21+Y21 -> 668.44698 | AA21: =MAX(0,Assumptions!$D$14-Assumptions!$D$16-R21) -> 287.25327 | AB21: =MAX(0,W21-Assumptions!$D$24)+AA21 -> 287.25327 | AC21: =SUMIFS(Assumptions!$AM$41:$AM$364,Assumptions!$C$41:$C$364,$D$4,Assumptions!$E$41:$E$364,$C21)+MAX(0,-W21) -> 0 | AD21: =IF(COUNTIFS(Assumptions!$C$41:$C$364,$D$4,Assumptions!$E$41:$E$364,$C21,Assumptions!$AR$41:$AR$364,"*shutoff_active*")>0,"SHUTOFF","AVAILABLE") -> AVAILABLE
C22: P011 | D22: 46387 | E22: monthly | F22: FY2027 | G22: Q1 | H22: 31 | I22: =SUMIFS(Assumptions!$T$41:$T$364,Assumptions!$C$41:$C$364,$D$4,Assumptions!$E$41:$E$364,$C22)+(Assumptions!$D$25+IF($C22="P001",-SUMIFS(Assumptions!$L$41:$L$364,Assumptions!$C$41:$C$364,$D$4,Assumptions!$E$41:$E$364,$C22)/365*Assumptions!$D$23,0)) -> 5.2161301 | J22: =N21 -> 599.28125 | K22: =SUMIFS(Assumptions!$Y$41:$Y$364,Assumptions!$C$41:$C$364,$D$4,Assumptions!$E$41:$E$364,$C22)*(Assumptions!$D$12/635)*(Assumptions!$D$18/7.5%) -> 0 | L22: =SUMIFS(Assumptions!$Z$41:$Z$364,Assumptions!$C$41:$C$364,$D$4,Assumptions!$E$41:$E$364,$C22)*(Assumptions!$D$26/50%)*IF(SUMIFS(Assumptions!$AO$41:$AO$364,Assumptions!$C$41:$C$364,$D$4,Assumptions!$E$41:$E$364,$C22)>Assumptions!$D$24,1,0) -> 0 | M22: =SUMIFS(Assumptions!$AB$41:$AB$364,Assumptions!$C$41:$C$364,$D$4,Assumptions!$E$41:$E$364,$C22) -> 0 | N22: =MAX(0,J22-K22-L22-M22) -> 599.28125 | O22: =R21 -> 6.5467312 | P22: =SUMIFS(Assumptions!$AE$41:$AE$364,Assumptions!$C$41:$C$364,$D$4,Assumptions!$E$41:$E$364,$C22)+IF((Assumptions!$D$25+IF($C22="P001",-SUMIFS(Assumptions!$L$41:$L$364,Assumptions!$C$41:$C$364,$D$4,Assumptions!$E$41:$E$364,$C22)/365*Assumptions!$D$23,0))<0,MIN(MAX(0,Assumptions!$D$14-Assumptions!$D$16-O22),-(Assumptions!$D$25+IF($C22="P001",-SUMIFS(Assumptions!$L$41:$L$364,Assumptions!$C$41:$C$364,$D$4,Assumptions!$E$41:$E$364,$C22)/365*Assumptions!$D$23,0))),0) -> 0.39611243 | Q22: =SUMIFS(Assumptions!$AF$41:$AF$364,Assumptions!$C$41:$C$364,$D$4,Assumptions!$E$41:$E$364,$C22)+IF((Assumptions!$D$25+IF($C22="P001",-SUMIFS(Assumptions!$L$41:$L$364,Assumptions!$C$41:$C$364,$D$4,Assumptions!$E$41:$E$364,$C22)/365*Assumptions!$D$23,0))>0,MIN(O22,(Assumptions!$D$25+IF($C22="P001",-SUMIFS(Assumptions!$L$41:$L$364,Assumptions!$C$41:$C$364,$D$4,Assumptions!$E$41:$E$364,$C22)/365*Assumptions!$D$23,0))),0) -> 0 | R22: =MAX(0,O22+P22-Q22) -> 6.9428436 | S22: =(J22+N22+O22+R22)/2 -> 606.02604 | T22: =IF(Assumptions!$D$19="","",IF(((SUMIFS(Assumptions!$W$41:$W$364,Assumptions!$C$41:$C$364,$D$4,Assumptions!$E$41:$E$364,$C22)+SUMIFS(Assumptions!$AC$41:$AC$364,Assumptions!$C$41:$C$364,$D$4,Assumptions!$E$41:$E$364,$C22)+SUMIFS(Assumptions!$AD$41:$AD$364,Assumptions!$C$41:$C$364,$D$4,Assumptions!$E$41:$E$364,$C22)+SUMIFS(Assumptions!$AG$41:$AG$364,Assumptions!$C$41:$C$364,$D$4,Assumptions!$E$41:$E$364,$C22))/2)=0,0,SUMIFS(Assumptions!$AI$41:$AI$364,Assumptions!$C$41:$C$364,$D$4,Assumptions!$E$41:$E$364,$C22)*S22/((SUMIFS(Assumptions!$W$41:$W$364,Assumptions!$C$41:$C$364,$D$4,Assumptions!$E$41:$E$364,$C22)+SUMIFS(Assumptions!$AC$41:$AC$364,Assumptions!$C$41:$C$364,$D$4,Assumptions!$E$41:$E$364,$C22)+SUMIFS(Assumptions!$AD$41:$AD$364,Assumptions!$C$41:$C$364,$D$4,Assumptions!$E$41:$E$364,$C22)+SUMIFS(Assumptions!$AG$41:$AG$364,Assumptions!$C$41:$C$364,$D$4,Assumptions!$E$41:$E$364,$C22))/2)*(Assumptions!$D$19/6.57%))+Assumptions!$D$20*S22*H22/365) -> 3.3179926 | U22: =SUMIFS(Assumptions!$AJ$41:$AJ$364,Assumptions!$C$41:$C$364,$D$4,Assumptions!$E$41:$E$364,$C22) -> 0.66925 | V22: =SUMIFS(Assumptions!$AK$41:$AK$364,Assumptions!$C$41:$C$364,$D$4,Assumptions!$E$41:$E$364,$C22)+SUMIFS(Assumptions!$AL$41:$AL$364,Assumptions!$C$41:$C$364,$D$4,Assumptions!$E$41:$E$364,$C22) -> 1.625 | W22: =W21+(SUMIFS(Assumptions!$V$41:$V$364,Assumptions!$C$41:$C$364,$D$4,Assumptions!$E$41:$E$364,$C22)-SUMIFS(Assumptions!$U$41:$U$364,Assumptions!$C$41:$C$364,$D$4,Assumptions!$E$41:$E$364,$C22))+(Assumptions!$D$25+IF($C22="P001",-SUMIFS(Assumptions!$L$41:$L$364,Assumptions!$C$41:$C$364,$D$4,Assumptions!$E$41:$E$364,$C22)/365*Assumptions!$D$23,0))+(IF((Assumptions!$D$25+IF($C22="P001",-SUMIFS(Assumptions!$L$41:$L$364,Assumptions!$C$41:$C$364,$D$4,Assumptions!$E$41:$E$364,$C22)/365*Assumptions!$D$23,0))<0,MIN(MAX(0,Assumptions!$D$14-Assumptions!$D$16-O22),-(Assumptions!$D$25+IF($C22="P001",-SUMIFS(Assumptions!$L$41:$L$364,Assumptions!$C$41:$C$364,$D$4,Assumptions!$E$41:$E$364,$C22)/365*Assumptions!$D$23,0))),0))-(IF((Assumptions!$D$25+IF($C22="P001",-SUMIFS(Assumptions!$L$41:$L$364,Assumptions!$C$41:$C$364,$D$4,Assumptions!$E$41:$E$364,$C22)/365*Assumptions!$D$23,0))>0,MIN(O22,(Assumptions!$D$25+IF($C22="P001",-SUMIFS(Assumptions!$L$41:$L$364,Assumptions!$C$41:$C$364,$D$4,Assumptions!$E$41:$E$364,$C22)/365*Assumptions!$D$23,0))),0)) -> 25 | X22: =N22+R22 -> 606.22409 | Y22: =Assumptions!$D$17 -> 62.619 | Z22: =X22+Y22 -> 668.84309 | AA22: =MAX(0,Assumptions!$D$14-Assumptions!$D$16-R22) -> 286.85716 | AB22: =MAX(0,W22-Assumptions!$D$24)+AA22 -> 286.85716 | AC22: =SUMIFS(Assumptions!$AM$41:$AM$364,Assumptions!$C$41:$C$364,$D$4,Assumptions!$E$41:$E$364,$C22)+MAX(0,-W22) -> 0 | AD22: =IF(COUNTIFS(Assumptions!$C$41:$C$364,$D$4,Assumptions!$E$41:$E$364,$C22,Assumptions!$AR$41:$AR$364,"*shutoff_active*")>0,"SHUTOFF","AVAILABLE") -> AVAILABLE
C23: P012 | D23: 46418 | E23: monthly | F23: FY2027 | G23: Q1 | H23: 31 | I23: =SUMIFS(Assumptions!$T$41:$T$364,Assumptions!$C$41:$C$364,$D$4,Assumptions!$E$41:$E$364,$C23)+(Assumptions!$D$25+IF($C23="P001",-SUMIFS(Assumptions!$L$41:$L$364,Assumptions!$C$41:$C$364,$D$4,Assumptions!$E$41:$E$364,$C23)/365*Assumptions!$D$23,0)) -> 5.2161301 | J23: =N22 -> 599.28125 | K23: =SUMIFS(Assumptions!$Y$41:$Y$364,Assumptions!$C$41:$C$364,$D$4,Assumptions!$E$41:$E$364,$C23)*(Assumptions!$D$12/635)*(Assumptions!$D$18/7.5%) -> 11.90625 | L23: =SUMIFS(Assumptions!$Z$41:$Z$364,Assumptions!$C$41:$C$364,$D$4,Assumptions!$E$41:$E$364,$C23)*(Assumptions!$D$26/50%)*IF(SUMIFS(Assumptions!$AO$41:$AO$364,Assumptions!$C$41:$C$364,$D$4,Assumptions!$E$41:$E$364,$C23)>Assumptions!$D$24,1,0) -> 0 | M23: =SUMIFS(Assumptions!$AB$41:$AB$364,Assumptions!$C$41:$C$364,$D$4,Assumptions!$E$41:$E$364,$C23) -> 0 | N23: =MAX(0,J23-K23-L23-M23) -> 587.375 | O23: =R22 -> 6.9428436 | P23: =SUMIFS(Assumptions!$AE$41:$AE$364,Assumptions!$C$41:$C$364,$D$4,Assumptions!$E$41:$E$364,$C23)+IF((Assumptions!$D$25+IF($C23="P001",-SUMIFS(Assumptions!$L$41:$L$364,Assumptions!$C$41:$C$364,$D$4,Assumptions!$E$41:$E$364,$C23)/365*Assumptions!$D$23,0))<0,MIN(MAX(0,Assumptions!$D$14-Assumptions!$D$16-O23),-(Assumptions!$D$25+IF($C23="P001",-SUMIFS(Assumptions!$L$41:$L$364,Assumptions!$C$41:$C$364,$D$4,Assumptions!$E$41:$E$364,$C23)/365*Assumptions!$D$23,0))),0) -> 12.304537 | Q23: =SUMIFS(Assumptions!$AF$41:$AF$364,Assumptions!$C$41:$C$364,$D$4,Assumptions!$E$41:$E$364,$C23)+IF((Assumptions!$D$25+IF($C23="P001",-SUMIFS(Assumptions!$L$41:$L$364,Assumptions!$C$41:$C$364,$D$4,Assumptions!$E$41:$E$364,$C23)/365*Assumptions!$D$23,0))>0,MIN(O23,(Assumptions!$D$25+IF($C23="P001",-SUMIFS(Assumptions!$L$41:$L$364,Assumptions!$C$41:$C$364,$D$4,Assumptions!$E$41:$E$364,$C23)/365*Assumptions!$D$23,0))),0) -> 0 | R23: =MAX(0,O23+P23-Q23) -> 19.247381 | S23: =(J23+N23+O23+R23)/2 -> 606.42324 | T23: =IF(Assumptions!$D$19="","",IF(((SUMIFS(Assumptions!$W$41:$W$364,Assumptions!$C$41:$C$364,$D$4,Assumptions!$E$41:$E$364,$C23)+SUMIFS(Assumptions!$AC$41:$AC$364,Assumptions!$C$41:$C$364,$D$4,Assumptions!$E$41:$E$364,$C23)+SUMIFS(Assumptions!$AD$41:$AD$364,Assumptions!$C$41:$C$364,$D$4,Assumptions!$E$41:$E$364,$C23)+SUMIFS(Assumptions!$AG$41:$AG$364,Assumptions!$C$41:$C$364,$D$4,Assumptions!$E$41:$E$364,$C23))/2)=0,0,SUMIFS(Assumptions!$AI$41:$AI$364,Assumptions!$C$41:$C$364,$D$4,Assumptions!$E$41:$E$364,$C23)*S23/((SUMIFS(Assumptions!$W$41:$W$364,Assumptions!$C$41:$C$364,$D$4,Assumptions!$E$41:$E$364,$C23)+SUMIFS(Assumptions!$AC$41:$AC$364,Assumptions!$C$41:$C$364,$D$4,Assumptions!$E$41:$E$364,$C23)+SUMIFS(Assumptions!$AD$41:$AD$364,Assumptions!$C$41:$C$364,$D$4,Assumptions!$E$41:$E$364,$C23)+SUMIFS(Assumptions!$AG$41:$AG$364,Assumptions!$C$41:$C$364,$D$4,Assumptions!$E$41:$E$364,$C23))/2)*(Assumptions!$D$19/6.57%))+Assumptions!$D$20*S23*H23/365) -> 3.3201672 | U23: =SUMIFS(Assumptions!$AJ$41:$AJ$364,Assumptions!$C$41:$C$364,$D$4,Assumptions!$E$41:$E$364,$C23) -> 0.66925 | V23: =SUMIFS(Assumptions!$AK$41:$AK$364,Assumptions!$C$41:$C$364,$D$4,Assumptions!$E$41:$E$364,$C23)+SUMIFS(Assumptions!$AL$41:$AL$364,Assumptions!$C$41:$C$364,$D$4,Assumptions!$E$41:$E$364,$C23) -> 1.625 | W23: =W22+(SUMIFS(Assumptions!$V$41:$V$364,Assumptions!$C$41:$C$364,$D$4,Assumptions!$E$41:$E$364,$C23)-SUMIFS(Assumptions!$U$41:$U$364,Assumptions!$C$41:$C$364,$D$4,Assumptions!$E$41:$E$364,$C23))+(Assumptions!$D$25+IF($C23="P001",-SUMIFS(Assumptions!$L$41:$L$364,Assumptions!$C$41:$C$364,$D$4,Assumptions!$E$41:$E$364,$C23)/365*Assumptions!$D$23,0))+(IF((Assumptions!$D$25+IF($C23="P001",-SUMIFS(Assumptions!$L$41:$L$364,Assumptions!$C$41:$C$364,$D$4,Assumptions!$E$41:$E$364,$C23)/365*Assumptions!$D$23,0))<0,MIN(MAX(0,Assumptions!$D$14-Assumptions!$D$16-O23),-(Assumptions!$D$25+IF($C23="P001",-SUMIFS(Assumptions!$L$41:$L$364,Assumptions!$C$41:$C$364,$D$4,Assumptions!$E$41:$E$364,$C23)/365*Assumptions!$D$23,0))),0))-(IF((Assumptions!$D$25+IF($C23="P001",-SUMIFS(Assumptions!$L$41:$L$364,Assumptions!$C$41:$C$364,$D$4,Assumptions!$E$41:$E$364,$C23)/365*Assumptions!$D$23,0))>0,MIN(O23,(Assumptions!$D$25+IF($C23="P001",-SUMIFS(Assumptions!$L$41:$L$364,Assumptions!$C$41:$C$364,$D$4,Assumptions!$E$41:$E$364,$C23)/365*Assumptions!$D$23,0))),0)) -> 25 | X23: =N23+R23 -> 606.62238 | Y23: =Assumptions!$D$17 -> 62.619 | Z23: =X23+Y23 -> 669.24138 | AA23: =MAX(0,Assumptions!$D$14-Assumptions!$D$16-R23) -> 274.55262 | AB23: =MAX(0,W23-Assumptions!$D$24)+AA23 -> 274.55262 | AC23: =SUMIFS(Assumptions!$AM$41:$AM$364,Assumptions!$C$41:$C$364,$D$4,Assumptions!$E$41:$E$364,$C23)+MAX(0,-W23) -> 0 | AD23: =IF(COUNTIFS(Assumptions!$C$41:$C$364,$D$4,Assumptions!$E$41:$E$364,$C23,Assumptions!$AR$41:$AR$364,"*shutoff_active*")>0,"SHUTOFF","AVAILABLE") -> AVAILABLE
C24: P013 | D24: 46446 | E24: monthly | F24: FY2027 | G24: Q2 | H24: 28 | I24: =SUMIFS(Assumptions!$T$41:$T$364,Assumptions!$C$41:$C$364,$D$4,Assumptions!$E$41:$E$364,$C24)+(Assumptions!$D$25+IF($C24="P001",-SUMIFS(Assumptions!$L$41:$L$364,Assumptions!$C$41:$C$364,$D$4,Assumptions!$E$41:$E$364,$C24)/365*Assumptions!$D$23,0)) -> 12.640974 | J24: =N23 -> 587.375 | K24: =SUMIFS(Assumptions!$Y$41:$Y$364,Assumptions!$C$41:$C$364,$D$4,Assumptions!$E$41:$E$364,$C24)*(Assumptions!$D$12/635)*(Assumptions!$D$18/7.5%) -> 0 | L24: =SUMIFS(Assumptions!$Z$41:$Z$364,Assumptions!$C$41:$C$364,$D$4,Assumptions!$E$41:$E$364,$C24)*(Assumptions!$D$26/50%)*IF(SUMIFS(Assumptions!$AO$41:$AO$364,Assumptions!$C$41:$C$364,$D$4,Assumptions!$E$41:$E$364,$C24)>Assumptions!$D$24,1,0) -> 0 | M24: =SUMIFS(Assumptions!$AB$41:$AB$364,Assumptions!$C$41:$C$364,$D$4,Assumptions!$E$41:$E$364,$C24) -> 0 | N24: =MAX(0,J24-K24-L24-M24) -> 587.375 | O24: =R23 -> 19.247381 | P24: =SUMIFS(Assumptions!$AE$41:$AE$364,Assumptions!$C$41:$C$364,$D$4,Assumptions!$E$41:$E$364,$C24)+IF((Assumptions!$D$25+IF($C24="P001",-SUMIFS(Assumptions!$L$41:$L$364,Assumptions!$C$41:$C$364,$D$4,Assumptions!$E$41:$E$364,$C24)/365*Assumptions!$D$23,0))<0,MIN(MAX(0,Assumptions!$D$14-Assumptions!$D$16-O24),-(Assumptions!$D$25+IF($C24="P001",-SUMIFS(Assumptions!$L$41:$L$364,Assumptions!$C$41:$C$364,$D$4,Assumptions!$E$41:$E$364,$C24)/365*Assumptions!$D$23,0))),0) -> 0 | Q24: =SUMIFS(Assumptions!$AF$41:$AF$364,Assumptions!$C$41:$C$364,$D$4,Assumptions!$E$41:$E$364,$C24)+IF((Assumptions!$D$25+IF($C24="P001",-SUMIFS(Assumptions!$L$41:$L$364,Assumptions!$C$41:$C$364,$D$4,Assumptions!$E$41:$E$364,$C24)/365*Assumptions!$D$23,0))>0,MIN(O24,(Assumptions!$D$25+IF($C24="P001",-SUMIFS(Assumptions!$L$41:$L$364,Assumptions!$C$41:$C$364,$D$4,Assumptions!$E$41:$E$364,$C24)/365*Assumptions!$D$23,0))),0) -> 7.0447512 | R24: =MAX(0,O24+P24-Q24) -> 12.20263 | S24: =(J24+N24+O24+R24)/2 -> 603.10001 | T24: =IF(Assumptions!$D$19="","",IF(((SUMIFS(Assumptions!$W$41:$W$364,Assumptions!$C$41:$C$364,$D$4,Assumptions!$E$41:$E$364,$C24)+SUMIFS(Assumptions!$AC$41:$AC$364,Assumptions!$C$41:$C$364,$D$4,Assumptions!$E$41:$E$364,$C24)+SUMIFS(Assumptions!$AD$41:$AD$364,Assumptions!$C$41:$C$364,$D$4,Assumptions!$E$41:$E$364,$C24)+SUMIFS(Assumptions!$AG$41:$AG$364,Assumptions!$C$41:$C$364,$D$4,Assumptions!$E$41:$E$364,$C24))/2)=0,0,SUMIFS(Assumptions!$AI$41:$AI$364,Assumptions!$C$41:$C$364,$D$4,Assumptions!$E$41:$E$364,$C24)*S24/((SUMIFS(Assumptions!$W$41:$W$364,Assumptions!$C$41:$C$364,$D$4,Assumptions!$E$41:$E$364,$C24)+SUMIFS(Assumptions!$AC$41:$AC$364,Assumptions!$C$41:$C$364,$D$4,Assumptions!$E$41:$E$364,$C24)+SUMIFS(Assumptions!$AD$41:$AD$364,Assumptions!$C$41:$C$364,$D$4,Assumptions!$E$41:$E$364,$C24)+SUMIFS(Assumptions!$AG$41:$AG$364,Assumptions!$C$41:$C$364,$D$4,Assumptions!$E$41:$E$364,$C24))/2)*(Assumptions!$D$19/6.57%))+Assumptions!$D$20*S24*H24/365) -> 3.3019725 | U24: =SUMIFS(Assumptions!$AJ$41:$AJ$364,Assumptions!$C$41:$C$364,$D$4,Assumptions!$E$41:$E$364,$C24) -> 0.66925 | V24: =SUMIFS(Assumptions!$AK$41:$AK$364,Assumptions!$C$41:$C$364,$D$4,Assumptions!$E$41:$E$364,$C24)+SUMIFS(Assumptions!$AL$41:$AL$364,Assumptions!$C$41:$C$364,$D$4,Assumptions!$E$41:$E$364,$C24) -> 1.625 | W24: =W23+(SUMIFS(Assumptions!$V$41:$V$364,Assumptions!$C$41:$C$364,$D$4,Assumptions!$E$41:$E$364,$C24)-SUMIFS(Assumptions!$U$41:$U$364,Assumptions!$C$41:$C$364,$D$4,Assumptions!$E$41:$E$364,$C24))+(Assumptions!$D$25+IF($C24="P001",-SUMIFS(Assumptions!$L$41:$L$364,Assumptions!$C$41:$C$364,$D$4,Assumptions!$E$41:$E$364,$C24)/365*Assumptions!$D$23,0))+(IF((Assumptions!$D$25+IF($C24="P001",-SUMIFS(Assumptions!$L$41:$L$364,Assumptions!$C$41:$C$364,$D$4,Assumptions!$E$41:$E$364,$C24)/365*Assumptions!$D$23,0))<0,MIN(MAX(0,Assumptions!$D$14-Assumptions!$D$16-O24),-(Assumptions!$D$25+IF($C24="P001",-SUMIFS(Assumptions!$L$41:$L$364,Assumptions!$C$41:$C$364,$D$4,Assumptions!$E$41:$E$364,$C24)/365*Assumptions!$D$23,0))),0))-(IF((Assumptions!$D$25+IF($C24="P001",-SUMIFS(Assumptions!$L$41:$L$364,Assumptions!$C$41:$C$364,$D$4,Assumptions!$E$41:$E$364,$C24)/365*Assumptions!$D$23,0))>0,MIN(O24,(Assumptions!$D$25+IF($C24="P001",-SUMIFS(Assumptions!$L$41:$L$364,Assumptions!$C$41:$C$364,$D$4,Assumptions!$E$41:$E$364,$C24)/365*Assumptions!$D$23,0))),0)) -> 25 | X24: =N24+R24 -> 599.57763 | Y24: =Assumptions!$D$17 -> 62.619 | Z24: =X24+Y24 -> 662.19663 | AA24: =MAX(0,Assumptions!$D$14-Assumptions!$D$16-R24) -> 281.59737 | AB24: =MAX(0,W24-Assumptions!$D$24)+AA24 -> 281.59737 | AC24: =SUMIFS(Assumptions!$AM$41:$AM$364,Assumptions!$C$41:$C$364,$D$4,Assumptions!$E$41:$E$364,$C24)+MAX(0,-W24) -> 0 | AD24: =IF(COUNTIFS(Assumptions!$C$41:$C$364,$D$4,Assumptions!$E$41:$E$364,$C24,Assumptions!$AR$41:$AR$364,"*shutoff_active*")>0,"SHUTOFF","AVAILABLE") -> AVAILABLE
